{"code":1000,"msg":"success","data":{"start":3020,"limit":20,"total":3150,"checkable":false,"rows":[{"id":530554,"cells":{"audience_realfans_ratio":-1,"can_origin":2,"reward":0,"account_id":530554,"user_id":204921,"owner_admin_id":839,"weibo_id":"423895","url":"http:\/\/www.douyu.com\/423895","identity_name":"\u9999\u8549\u6e38\u620f","weibo_name":"&#x80d6;&#x864e;&#x7684;&#x72d7;&#x59ae;&#x59ae;","followers_count":"13\u4e07","retweet_price":null,"tweet_price":null,"content_price":null,"original_zhifa_price":null,"soft_tweet_price":null,"soft_retweet_price":null,"orders_monthly":0,"orders_monthly_amount":"0.00","orders_weekly":0,"orders_weekly_amount":"0.00","reservation_order_complete_count_monthly":0,"reservation_order_complete_amount_monthly":0,"weibo_type":107,"verification_info":"","introduction":"","area_id":-1,"location":null,"freedata_picpath":null,"is_vip":2,"is_bluevip":2,"keywords":null,"hand_tags":"","content_tags":"","profit_grade":434,"account_type":null,"is_famous":1,"face_url":"https:\/\/apic.douyucdn.cn\/upload\/avanew\/face\/201610\/05\/07\/14a2437d30be98480a9a217c47cced8f_middle.jpg?rltime","is_daren":2,"is_sensitive":2,"gender":3,"is_enable_micro_task":1,"is_extend":1,"active_score":"0.00","audience_female_ratio":"-1.000000","audience_gender":3,"follower_be_identified":2,"is_prepayment":2,"is_original_zhifa":2,"is_sign":2,"sign_note":null,"order_settings":0,"posts_avgretweet_count":"-1.000","posts_avgcomment_count":"-1.000","soft_single_graphic_price":null,"is_reservation_promotion":false,"age":null,"area_name":"","reservation_num":0,"price_maintain_time":"2017-02-22 17:01:03","account_avatar":"https:\/\/apic.douyucdn.cn\/upload\/avanew\/face\/201610\/05\/07\/14a2437d30be98480a9a217c47cced8f_middle.jpg?rltime","video_play_num":null,"video_down_num_avg":null,"video_subscribe_num":null,"average_live_play_num":null,"video_up_num_total":null,"avg_collection_count":null,"follower_be_identified_time":"1970\u5e7401\u670801\u65e5","flag":0,"is_verify":2,"is_shield":2,"is_contacted":1,"is_fake":2,"is_open":1,"cooperation_type":1,"is_closed":2,"account_introduction":"FPS\u6e38\u620f\u4e3b\u64ad","id":"38977","pack_type":1,"pack_name":"\u80d6\u864e\u7684\u72d7\u59ae\u59ae","pack_info":{"pack_name":"\u80d6\u864e\u7684\u72d7\u59ae\u59ae","pack_type":1,"face_url":"https:\/\/apic.douyucdn.cn\/upload\/avanew\/face\/201610\/05\/07\/14a2437d30be98480a9a217c47cced8f_middle.jpg","sex":3,"pack_id":31070,"related_url_a":"","base_info":{"cooperation_index":null}},"domains":"","professions":"\u7f51\u7edc\u7ea2\u4eba","cooperation_index":"\u9ad8","reference_price_range_default":{"min":0,"max":0},"reference_price_range_multi_top":{"min":0,"max":0},"reference_price_range_multi_second":{"min":0,"max":0},"reference_price_range_multi_other":{"min":0,"max":0},"reference_price_range_single":{"min":0,"max":0},"audience_profile":"","work_nature":"","company_name":"","work_position":"","school_name":"","work_nature_be_identified":"","work_nature_be_identified_time":"","creations":[],"pyq_account_daily_update_images":"","reference_gross_price_original_release":"","reference_gross_price_video_release":"","reference_gross_price_guerilla_advertising":"","reference_gross_price_filed_events":"15000.00","reference_gross_price_guerilla_advertising_live":"10000.00","reference_net_price_original_release":"","reference_net_price_video_release":"","reference_net_price_guerilla_advertising":"","reference_net_price_filed_events":"15000.00","reference_net_price_guerilla_advertising_live":"10000.00","account_level":"","retweet_average_like_num":"","retweet_average_posts_num":"","retweet_average_send_num":"","tweet_average_like_num":"","tweet_average_posts_num":"","tweet_average_send_num":"","operation_tag":[],"fav_info":{"account_note":"","group_type":0},"average_play_num":0,"average_like_num":0,"average_posts_num":0,"max_live_audience_num":0,"average_live_audience_num":0,"average_bullet_screen_num":0,"is_select":true,"is_show_select":false,"in_picking_cart":false,"reservation_notice_short":"","external_reference_price":{"price_validity_period":{"start":"2018-09-21","end":"2018-10-31"},"filed_events":{"quote":20400},"guerilla_advertising_live":{"quote":13600}},"external_original_zhifa_price":null,"only_support_original":2,"has_pyq_account_daily_update_images":[],"in_shopping_cart":false,"screen_shot_qr_code":null,"weibo_name_cut":"&#x80d6;&#x864e;&#x7684;&#x72d7;&#x59ae;&#x59ae;","video_type_cate":1,"detail_url":"\/single\/video?weibo_id=423895&weibo_type=107&sign=e46a853fb8"}},{"id":530191,"cells":{"audience_realfans_ratio":-1,"can_origin":2,"reward":0,"account_id":530191,"user_id":191340,"owner_admin_id":922,"weibo_id":"94998","url":null,"identity_name":"\u6c88\u66fc","weibo_name":"Mc&#x963f;&#x54f2;","followers_count":"1,190\u4e07","retweet_price":null,"tweet_price":null,"content_price":null,"original_zhifa_price":null,"soft_tweet_price":null,"soft_retweet_price":null,"orders_monthly":0,"orders_monthly_amount":"0.00","orders_weekly":0,"orders_weekly_amount":"0.00","reservation_order_complete_count_monthly":0,"reservation_order_complete_amount_monthly":0,"weibo_type":104,"verification_info":"","introduction":"","area_id":101,"location":null,"freedata_picpath":null,"is_vip":2,"is_bluevip":2,"keywords":null,"hand_tags":"","content_tags":"","profit_grade":434,"account_type":null,"is_famous":1,"face_url":"http:\/\/img.weiboyi.com\/img\/uploadimg\/weixin_follower_img\/downlogo3.yy.duowan.com\/user_logo\/08\/28\/38\/0022382808\/b6aeaadaea3f49a1b3ba1bfc19ba640c.gif?20170217101751","is_daren":2,"is_sensitive":2,"gender":3,"is_enable_micro_task":1,"is_extend":1,"active_score":"0.00","audience_female_ratio":"-1.000000","audience_gender":3,"follower_be_identified":2,"is_prepayment":1,"is_original_zhifa":2,"is_sign":2,"sign_note":null,"order_settings":0,"posts_avgretweet_count":"-1.000","posts_avgcomment_count":"-1.000","soft_single_graphic_price":null,"is_reservation_promotion":false,"age":null,"area_name":"","reservation_num":7,"price_maintain_time":"2017-02-18 17:54:26","account_avatar":"http:\/\/img.weiboyi.com\/img\/uploadimg\/weixin_follower_img\/downlogo3.yy.duowan.com\/user_logo\/08\/28\/38\/0022382808\/b6aeaadaea3f49a1b3ba1bfc19ba640c.gif?20170217101751","video_play_num":null,"video_down_num_avg":null,"video_subscribe_num":null,"average_live_play_num":null,"video_up_num_total":null,"avg_collection_count":null,"follower_be_identified_time":"1970\u5e7401\u670801\u65e5","flag":0,"is_verify":2,"is_shield":2,"is_contacted":1,"is_fake":2,"is_open":1,"cooperation_type":1,"is_closed":2,"id":"38864","pack_type":1,"pack_name":"Mc\u963f\u54f2","pack_info":{"pack_name":"Mc\u963f\u54f2","pack_type":1,"face_url":"http:\/\/img.weiboyi.com\/img\/uploadimg\/weixin_follower_img\/\/\/downlogo3.yy.duowan.com\/user_logo\/08\/28\/3","sex":3,"pack_id":30971,"related_url_a":"","base_info":{"cooperation_index":null}},"domains":"","professions":"\u7f51\u7edc\u7ea2\u4eba","cooperation_index":"\u9ad8","reference_price_range_default":{"min":0,"max":0},"reference_price_range_multi_top":{"min":0,"max":0},"reference_price_range_multi_second":{"min":0,"max":0},"reference_price_range_multi_other":{"min":0,"max":0},"reference_price_range_single":{"min":0,"max":0},"audience_profile":"","work_nature":"","company_name":"","work_position":"","school_name":"","work_nature_be_identified":"","work_nature_be_identified_time":"","creations":[],"pyq_account_daily_update_images":"","reference_gross_price_original_release":"","reference_gross_price_video_release":"","reference_gross_price_guerilla_advertising":"","reference_gross_price_filed_events":"210000.00","reference_gross_price_guerilla_advertising_live":"","reference_net_price_original_release":"","reference_net_price_video_release":"","reference_net_price_guerilla_advertising":"","reference_net_price_filed_events":"210000.00","reference_net_price_guerilla_advertising_live":"","account_level":"","retweet_average_like_num":"","retweet_average_posts_num":"","retweet_average_send_num":"","tweet_average_like_num":"","tweet_average_posts_num":"","tweet_average_send_num":"","operation_tag":[],"fav_info":{"account_note":"","group_type":0},"average_play_num":0,"average_like_num":0,"average_posts_num":0,"max_live_audience_num":0,"average_live_audience_num":0,"average_bullet_screen_num":0,"is_select":true,"is_show_select":false,"in_picking_cart":false,"reservation_notice_short":"","external_reference_price":{"price_validity_period":{"start":"2017-06-11","end":"2017-06-11"},"filed_events":{"quote":239400},"guerilla_advertising_live":{"quote":0}},"external_original_zhifa_price":null,"only_support_original":2,"has_pyq_account_daily_update_images":[],"in_shopping_cart":false,"screen_shot_qr_code":null,"weibo_name_cut":"Mc&#x963f;&#x54f2;","video_type_cate":1,"detail_url":"\/single\/video?weibo_id=94998&weibo_type=104&sign=8c3dec00ef"}},{"id":530168,"cells":{"audience_realfans_ratio":-1,"can_origin":2,"reward":0,"account_id":530168,"user_id":187468,"owner_admin_id":696,"weibo_id":"641496","url":"http:\/\/www.douyu.com\/641496","identity_name":"\u6b66\u6c49\u6597\u9c7c\u7f51\u7edc\u79d1\u6280\u6709\u9650\u516c\u53f8","weibo_name":"&#x963f;&#x9e9f;&#x73a9;&#x6c7d;&#x8f66;","followers_count":"10\u4e07","retweet_price":null,"tweet_price":null,"content_price":null,"original_zhifa_price":null,"soft_tweet_price":null,"soft_retweet_price":null,"orders_monthly":0,"orders_monthly_amount":"0.00","orders_weekly":0,"orders_weekly_amount":"0.00","reservation_order_complete_count_monthly":0,"reservation_order_complete_amount_monthly":0,"weibo_type":107,"verification_info":"","introduction":"","area_id":-1,"location":null,"freedata_picpath":null,"is_vip":2,"is_bluevip":2,"keywords":null,"hand_tags":"","content_tags":"","profit_grade":434,"account_type":null,"is_famous":1,"face_url":"https:\/\/apic.douyucdn.cn\/upload\/avatar\/face\/201605\/18\/14382ff56300eb0803abf137ad284586_middle.jpg?rltime","is_daren":2,"is_sensitive":2,"gender":3,"is_enable_micro_task":1,"is_extend":1,"active_score":"0.00","audience_female_ratio":"-1.000000","audience_gender":3,"follower_be_identified":2,"is_prepayment":1,"is_original_zhifa":2,"is_sign":2,"sign_note":null,"order_settings":0,"posts_avgretweet_count":"-1.000","posts_avgcomment_count":"-1.000","soft_single_graphic_price":null,"is_reservation_promotion":false,"age":null,"area_name":"","reservation_num":2,"price_maintain_time":"2017-02-20 14:07:13","account_avatar":"https:\/\/apic.douyucdn.cn\/upload\/avatar\/face\/201605\/18\/14382ff56300eb0803abf137ad284586_middle.jpg?rltime","video_play_num":null,"video_down_num_avg":null,"video_subscribe_num":null,"average_live_play_num":null,"video_up_num_total":null,"avg_collection_count":null,"follower_be_identified_time":"1970\u5e7401\u670801\u65e5","flag":0,"is_verify":2,"is_shield":2,"is_contacted":1,"is_fake":2,"is_open":1,"cooperation_type":1,"is_closed":2,"account_introduction":"\u6c7d\u8f66\u4e3b\u64ad","id":"38859","pack_type":1,"pack_name":"\u963f\u9e9f\u73a9\u6c7d\u8f66","pack_info":{"pack_name":"\u963f\u9e9f\u73a9\u6c7d\u8f66","pack_type":1,"face_url":"https:\/\/apic.douyucdn.cn\/upload\/avatar\/face\/201605\/18\/14382ff56300eb0803abf137ad284586_middle.jpg?rl","sex":3,"pack_id":30966,"related_url_a":"","base_info":{"cooperation_index":null}},"domains":"","professions":"\u7f51\u7edc\u7ea2\u4eba","cooperation_index":"\u9ad8","reference_price_range_default":{"min":0,"max":0},"reference_price_range_multi_top":{"min":0,"max":0},"reference_price_range_multi_second":{"min":0,"max":0},"reference_price_range_multi_other":{"min":0,"max":0},"reference_price_range_single":{"min":0,"max":0},"audience_profile":"","work_nature":"","company_name":"","work_position":"","school_name":"","work_nature_be_identified":"","work_nature_be_identified_time":"","creations":[],"pyq_account_daily_update_images":"","reference_gross_price_original_release":"","reference_gross_price_video_release":"","reference_gross_price_guerilla_advertising":"","reference_gross_price_filed_events":"6000.00","reference_gross_price_guerilla_advertising_live":"5000.00","reference_net_price_original_release":"","reference_net_price_video_release":"","reference_net_price_guerilla_advertising":"","reference_net_price_filed_events":"6000.00","reference_net_price_guerilla_advertising_live":"5000.00","account_level":"","retweet_average_like_num":"","retweet_average_posts_num":"","retweet_average_send_num":"","tweet_average_like_num":"","tweet_average_posts_num":"","tweet_average_send_num":"","operation_tag":[],"fav_info":{"account_note":"","group_type":0},"average_play_num":0,"average_like_num":0,"average_posts_num":0,"max_live_audience_num":0,"average_live_audience_num":0,"average_bullet_screen_num":0,"is_select":true,"is_show_select":false,"in_picking_cart":false,"reservation_notice_short":"","external_reference_price":{"price_validity_period":{"start":"2018-07-25","end":"2018-08-31"},"filed_events":{"quote":8200},"guerilla_advertising_live":{"quote":6800}},"external_original_zhifa_price":null,"only_support_original":2,"has_pyq_account_daily_update_images":[],"in_shopping_cart":false,"screen_shot_qr_code":null,"weibo_name_cut":"&#x963f;&#x9e9f;&#x73a9;&#x6c7d;&#x8f66;","video_type_cate":1,"detail_url":"\/single\/video?weibo_id=641496&weibo_type=107&sign=8beaaeedc6"}},{"id":526128,"cells":{"audience_realfans_ratio":-1,"can_origin":2,"reward":0,"account_id":526128,"user_id":187468,"owner_admin_id":696,"weibo_id":"63623","url":"http:\/\/www.douyu.com\/63623","identity_name":"\u6b66\u6c49\u6597\u9c7c\u7f51\u7edc\u79d1\u6280\u6709\u9650\u516c\u53f8","weibo_name":"&#x9c8d;&#x9c8d;&#x89e3;&#x8bf4;","followers_count":"67\u4e07","retweet_price":null,"tweet_price":null,"content_price":null,"original_zhifa_price":null,"soft_tweet_price":null,"soft_retweet_price":null,"orders_monthly":0,"orders_monthly_amount":"0.00","orders_weekly":0,"orders_weekly_amount":"0.00","reservation_order_complete_count_monthly":0,"reservation_order_complete_amount_monthly":0,"weibo_type":107,"verification_info":"","introduction":"","area_id":-1,"location":null,"freedata_picpath":null,"is_vip":2,"is_bluevip":2,"keywords":null,"hand_tags":"","content_tags":"","profit_grade":605,"account_type":null,"is_famous":1,"face_url":"https:\/\/apic.douyucdn.cn\/upload\/avatar\/face\/201607\/12\/badc470240e502609798bb3de564e1f3_middle.jpg?rltime","is_daren":2,"is_sensitive":2,"gender":3,"is_enable_micro_task":1,"is_extend":1,"active_score":"0.00","audience_female_ratio":"-1.000000","audience_gender":3,"follower_be_identified":2,"is_prepayment":1,"is_original_zhifa":2,"is_sign":2,"sign_note":null,"order_settings":0,"posts_avgretweet_count":"-1.000","posts_avgcomment_count":"-1.000","soft_single_graphic_price":null,"is_reservation_promotion":false,"age":null,"area_name":"","reservation_num":4,"price_maintain_time":"2017-04-01 13:46:00","account_avatar":"https:\/\/apic.douyucdn.cn\/upload\/avatar\/face\/201607\/12\/badc470240e502609798bb3de564e1f3_middle.jpg?rltime","video_play_num":null,"video_down_num_avg":null,"video_subscribe_num":null,"average_live_play_num":null,"video_up_num_total":null,"avg_collection_count":null,"follower_be_identified_time":"1970\u5e7401\u670801\u65e5","flag":0,"is_verify":2,"is_shield":2,"is_contacted":1,"is_fake":2,"is_open":1,"cooperation_type":1,"is_closed":2,"account_introduction":"\u82f1\u96c4\u8054\u76df\u6e38\u620f\u4e3b\u64ad","id":"37612","pack_type":1,"pack_name":"\u9c8d\u9c8d\u89e3\u8bf4","pack_info":{"pack_name":"\u9c8d\u9c8d\u89e3\u8bf4","pack_type":1,"face_url":"https:\/\/apic.douyucdn.cn\/upload\/avatar\/face\/201607\/12\/badc470240e502609798bb3de564e1f3_middle.jpg?rl","sex":3,"pack_id":29807,"related_url_a":"","base_info":{"cooperation_index":null}},"domains":"","professions":"\u7f51\u7edc\u7ea2\u4eba","cooperation_index":"\u9ad8","reference_price_range_default":{"min":0,"max":0},"reference_price_range_multi_top":{"min":0,"max":0},"reference_price_range_multi_second":{"min":0,"max":0},"reference_price_range_multi_other":{"min":0,"max":0},"reference_price_range_single":{"min":0,"max":0},"audience_profile":"","work_nature":"","company_name":"","work_position":"","school_name":"","work_nature_be_identified":"","work_nature_be_identified_time":"","creations":[],"pyq_account_daily_update_images":"","reference_gross_price_original_release":"","reference_gross_price_video_release":"","reference_gross_price_guerilla_advertising":"","reference_gross_price_filed_events":"","reference_gross_price_guerilla_advertising_live":"31200.00","reference_net_price_original_release":"","reference_net_price_video_release":"","reference_net_price_guerilla_advertising":"","reference_net_price_filed_events":"","reference_net_price_guerilla_advertising_live":"31200.00","account_level":"","retweet_average_like_num":"","retweet_average_posts_num":"","retweet_average_send_num":"","tweet_average_like_num":"","tweet_average_posts_num":"","tweet_average_send_num":"","operation_tag":[],"fav_info":{"account_note":"","group_type":0},"average_play_num":0,"average_like_num":0,"average_posts_num":0,"max_live_audience_num":0,"average_live_audience_num":0,"average_bullet_screen_num":0,"is_select":true,"is_show_select":false,"in_picking_cart":false,"reservation_notice_short":"","external_reference_price":{"price_validity_period":{"start":"2018-07-25","end":"2018-08-31"},"filed_events":{"quote":0},"guerilla_advertising_live":{"quote":37600}},"external_original_zhifa_price":null,"only_support_original":2,"has_pyq_account_daily_update_images":[],"in_shopping_cart":false,"screen_shot_qr_code":null,"weibo_name_cut":"&#x9c8d;&#x9c8d;&#x89e3;&#x8bf4;","video_type_cate":1,"detail_url":"\/single\/video?weibo_id=63623&weibo_type=107&sign=3f63cb944c"}},{"id":524447,"cells":{"audience_realfans_ratio":-1,"can_origin":2,"reward":0,"account_id":524447,"user_id":197988,"owner_admin_id":754,"weibo_id":"229346","url":"http:\/\/www.douyu.com\/229346","identity_name":"\u9ad8\u51b7\u7537\u795e\u94b1\u5c0f\u4f73","weibo_name":"&#x9ad8;&#x51b7;&#x7537;&#x795e;&#x94b1;&#x5c0f;&#x4f73;","followers_count":"68\u4e07","retweet_price":null,"tweet_price":null,"content_price":null,"original_zhifa_price":null,"soft_tweet_price":null,"soft_retweet_price":null,"orders_monthly":0,"orders_monthly_amount":"0.00","orders_weekly":0,"orders_weekly_amount":"0.00","reservation_order_complete_count_monthly":0,"reservation_order_complete_amount_monthly":0,"weibo_type":107,"verification_info":"","introduction":"","area_id":-1,"location":null,"freedata_picpath":null,"is_vip":2,"is_bluevip":2,"keywords":null,"hand_tags":"","content_tags":"","profit_grade":668,"account_type":null,"is_famous":1,"face_url":"https:\/\/apic.douyucdn.cn\/upload\/avatar\/012\/73\/32\/89_avatar_middle.jpg?rltime4","is_daren":2,"is_sensitive":2,"gender":1,"is_enable_micro_task":1,"is_extend":1,"active_score":"0.00","audience_female_ratio":"-1.000000","audience_gender":3,"follower_be_identified":2,"is_prepayment":1,"is_original_zhifa":2,"is_sign":2,"sign_note":null,"order_settings":0,"posts_avgretweet_count":"-1.000","posts_avgcomment_count":"-1.000","soft_single_graphic_price":null,"is_reservation_promotion":false,"age":null,"area_name":"","reservation_num":2,"price_maintain_time":"2018-08-03 15:04:48","account_avatar":"https:\/\/apic.douyucdn.cn\/upload\/avatar\/012\/73\/32\/89_avatar_middle.jpg?rltime4","video_play_num":null,"video_down_num_avg":null,"video_subscribe_num":null,"average_live_play_num":null,"video_up_num_total":null,"avg_collection_count":null,"follower_be_identified_time":"1970\u5e7401\u670801\u65e5","flag":0,"is_verify":2,"is_shield":2,"is_contacted":1,"is_fake":2,"is_open":1,"cooperation_type":1,"is_closed":2,"account_introduction":"\u6237\u5916\u4e3b\u64ad\u3001\u8857\u5934\u8fbe\u4eba","id":"36839","pack_type":1,"pack_name":"\u9ad8\u51b7\u7537\u795e\u94b1\u5c0f\u4f73","pack_info":{"pack_name":"\u9ad8\u51b7\u7537\u795e\u94b1\u5c0f\u4f73","pack_type":1,"face_url":"https:\/\/apic.douyucdn.cn\/upload\/avatar\/012\/73\/32\/89_avatar_middle.jpg?rltime4","sex":3,"pack_id":29196,"related_url_a":"","base_info":{"cooperation_index":null}},"domains":"","professions":"\u7f51\u7edc\u7ea2\u4eba","cooperation_index":"\u9ad8","reference_price_range_default":{"min":0,"max":0},"reference_price_range_multi_top":{"min":0,"max":0},"reference_price_range_multi_second":{"min":0,"max":0},"reference_price_range_multi_other":{"min":0,"max":0},"reference_price_range_single":{"min":0,"max":0},"audience_profile":"","work_nature":"","company_name":"","work_position":"","school_name":"","work_nature_be_identified":"","work_nature_be_identified_time":"","creations":[],"pyq_account_daily_update_images":"","reference_gross_price_original_release":"","reference_gross_price_video_release":"","reference_gross_price_guerilla_advertising":"","reference_gross_price_filed_events":"","reference_gross_price_guerilla_advertising_live":"100000.00","reference_net_price_original_release":"","reference_net_price_video_release":"","reference_net_price_guerilla_advertising":"","reference_net_price_filed_events":"","reference_net_price_guerilla_advertising_live":"100000.00","account_level":"","retweet_average_like_num":"","retweet_average_posts_num":"","retweet_average_send_num":"","tweet_average_like_num":"","tweet_average_posts_num":"","tweet_average_send_num":"","operation_tag":[],"fav_info":{"account_note":"","group_type":0},"average_play_num":0,"average_like_num":0,"average_posts_num":0,"max_live_audience_num":0,"average_live_audience_num":0,"average_bullet_screen_num":0,"is_select":true,"is_show_select":false,"in_picking_cart":false,"reservation_notice_short":"","external_reference_price":{"price_validity_period":{"start":"2018-08-03","end":"2018-09-15"},"filed_events":{"quote":0},"guerilla_advertising_live":{"quote":114000}},"external_original_zhifa_price":null,"only_support_original":2,"has_pyq_account_daily_update_images":[],"in_shopping_cart":false,"screen_shot_qr_code":null,"weibo_name_cut":"&#x9ad8;&#x51b7;&#x7537;&#x795e;&#x94b1;&#x5c0f;&#x4f73;","video_type_cate":1,"detail_url":"\/single\/video?weibo_id=229346&weibo_type=107&sign=f1482665a5"}},{"id":524024,"cells":{"audience_realfans_ratio":-1,"can_origin":2,"reward":0,"account_id":524024,"user_id":187468,"owner_admin_id":696,"weibo_id":"228866","url":"http:\/\/www.douyu.com\/228866","identity_name":"\u6b66\u6c49\u6597\u9c7c\u7f51\u7edc\u79d1\u6280\u6709\u9650\u516c\u53f8","weibo_name":"M3&#x5f90;&#x82e5;&#x66e6;","followers_count":"14\u4e07","retweet_price":null,"tweet_price":null,"content_price":null,"original_zhifa_price":null,"soft_tweet_price":null,"soft_retweet_price":null,"orders_monthly":0,"orders_monthly_amount":"0.00","orders_weekly":0,"orders_weekly_amount":"0.00","reservation_order_complete_count_monthly":0,"reservation_order_complete_amount_monthly":0,"weibo_type":107,"verification_info":"","introduction":"","area_id":-1,"location":null,"freedata_picpath":null,"is_vip":2,"is_bluevip":2,"keywords":null,"hand_tags":"","content_tags":"","profit_grade":434,"account_type":null,"is_famous":1,"face_url":"https:\/\/apic.douyucdn.cn\/upload\/avatar\/face\/201608\/14\/39603b5821c1672ae456f327a506eb98_middle.jpg?rltime4","is_daren":2,"is_sensitive":2,"gender":3,"is_enable_micro_task":1,"is_extend":1,"active_score":"0.00","audience_female_ratio":"-1.000000","audience_gender":3,"follower_be_identified":2,"is_prepayment":1,"is_original_zhifa":2,"is_sign":2,"sign_note":null,"order_settings":0,"posts_avgretweet_count":"-1.000","posts_avgcomment_count":"-1.000","soft_single_graphic_price":null,"is_reservation_promotion":false,"age":null,"area_name":"","reservation_num":1,"price_maintain_time":"2017-03-15 15:07:05","account_avatar":"https:\/\/apic.douyucdn.cn\/upload\/avatar\/face\/201608\/14\/39603b5821c1672ae456f327a506eb98_middle.jpg?rltime4","video_play_num":null,"video_down_num_avg":null,"video_subscribe_num":null,"average_live_play_num":null,"video_up_num_total":null,"avg_collection_count":null,"follower_be_identified_time":"1970\u5e7401\u670801\u65e5","flag":0,"is_verify":2,"is_shield":2,"is_contacted":1,"is_fake":2,"is_open":1,"cooperation_type":1,"is_closed":2,"account_introduction":"\u8f66\u8bc4\u5973\u4e3b\u64ad","id":"36689","pack_type":1,"pack_name":"M3\u5f90\u82e5\u66e6","pack_info":{"pack_name":"M3\u5f90\u82e5\u66e6","pack_type":1,"face_url":"https:\/\/apic.douyucdn.cn\/upload\/avatar\/face\/201608\/14\/39603b5821c1672ae456f327a506eb98_middle.jpg?rl","sex":3,"pack_id":29047,"related_url_a":"","base_info":{"cooperation_index":null}},"domains":"","professions":"\u7f51\u7edc\u7ea2\u4eba","cooperation_index":"\u9ad8","reference_price_range_default":{"min":0,"max":0},"reference_price_range_multi_top":{"min":0,"max":0},"reference_price_range_multi_second":{"min":0,"max":0},"reference_price_range_multi_other":{"min":0,"max":0},"reference_price_range_single":{"min":0,"max":0},"audience_profile":"","work_nature":"","company_name":"","work_position":"","school_name":"","work_nature_be_identified":"","work_nature_be_identified_time":"","creations":[],"pyq_account_daily_update_images":"","reference_gross_price_original_release":"","reference_gross_price_video_release":"","reference_gross_price_guerilla_advertising":"","reference_gross_price_filed_events":"","reference_gross_price_guerilla_advertising_live":"31200.00","reference_net_price_original_release":"","reference_net_price_video_release":"","reference_net_price_guerilla_advertising":"","reference_net_price_filed_events":"","reference_net_price_guerilla_advertising_live":"31200.00","account_level":"","retweet_average_like_num":"","retweet_average_posts_num":"","retweet_average_send_num":"","tweet_average_like_num":"","tweet_average_posts_num":"","tweet_average_send_num":"","operation_tag":[],"fav_info":{"account_note":"","group_type":0},"average_play_num":0,"average_like_num":0,"average_posts_num":0,"max_live_audience_num":0,"average_live_audience_num":0,"average_bullet_screen_num":0,"is_select":true,"is_show_select":false,"in_picking_cart":false,"reservation_notice_short":"","external_reference_price":{"price_validity_period":{"start":"2018-07-25","end":"2018-08-31"},"filed_events":{"quote":0},"guerilla_advertising_live":{"quote":37600}},"external_original_zhifa_price":null,"only_support_original":2,"has_pyq_account_daily_update_images":[],"in_shopping_cart":false,"screen_shot_qr_code":null,"weibo_name_cut":"M3&#x5f90;&#x82e5;&#x66e6;","video_type_cate":1,"detail_url":"\/single\/video?weibo_id=228866&weibo_type=107&sign=77d3cbd0e4"}},{"id":520681,"cells":{"audience_realfans_ratio":-1,"can_origin":1,"reward":0,"account_id":520681,"user_id":219268,"owner_admin_id":754,"weibo_id":"mctianyou","url":"http:\/\/m.kuaishou.com\/user\/8303439","identity_name":"\u8d3a\u9633\u9f99\u7199\u4f20\u5a92","weibo_name":"&#x674e;&#x5929;&#x4f51;","followers_count":"3,967\u4e07","retweet_price":null,"tweet_price":null,"content_price":null,"original_zhifa_price":null,"soft_tweet_price":null,"soft_retweet_price":null,"orders_monthly":0,"orders_monthly_amount":"0.00","orders_weekly":0,"orders_weekly_amount":"0.00","reservation_order_complete_count_monthly":0,"reservation_order_complete_amount_monthly":0,"weibo_type":103,"verification_info":"","introduction":"\u6c42\u51e0\u4e2a\u5173\u6ce8","area_id":0,"location":null,"freedata_picpath":null,"is_vip":0,"is_bluevip":-1,"keywords":null,"hand_tags":"","content_tags":"","profit_grade":668,"account_type":null,"is_famous":1,"face_url":"http:\/\/tx2.a.yximgs.com\/s1\/i\/def\/head_u.png","is_daren":-1,"is_sensitive":2,"gender":1,"is_enable_micro_task":1,"is_extend":1,"active_score":"0.00","audience_female_ratio":"-1.000000","audience_gender":-1,"follower_be_identified":2,"is_prepayment":2,"is_original_zhifa":2,"is_sign":2,"sign_note":null,"order_settings":0,"posts_avgretweet_count":"-1.000","posts_avgcomment_count":"-1.000","soft_single_graphic_price":null,"is_reservation_promotion":false,"age":null,"area_name":"","reservation_num":3,"price_maintain_time":"2018-07-06 17:34:19","account_avatar":"http:\/\/tx2.a.yximgs.com\/s1\/i\/def\/head_u.png","operation_tag":[{"id":55,"name":"\u6e38\u620f\u884c\u4e1a\u70ed\u9009","description":"\u8fd1\u4e00\u5e74\u5185\u6e38\u620f\u5382\u5546\u70ed\u9009KOL","icon_path":"","show_A":1,"show_B":1,"marked_graph":""}],"video_play_num":null,"video_down_num_avg":null,"video_subscribe_num":null,"average_live_play_num":null,"video_up_num_total":null,"avg_collection_count":null,"follower_be_identified_time":"1970\u5e7401\u670801\u65e5","flag":0,"is_verify":2,"is_shield":2,"is_contacted":1,"is_fake":2,"is_open":1,"cooperation_type":1,"is_closed":2,"account_introduction":"\u5feb\u624b\u4e00\u54e5","id":"38104","pack_type":1,"pack_name":"MC\u5929\u4f51","pack_info":{"pack_name":"MC\u5929\u4f51","pack_type":1,"face_url":"http:\/\/img.weiboyi.com\/vol1\/3\/102\/139\/v\/q\/57r88p6pn72211r69p9p40qn8613p9o9\/a8ec8a13632762d02f95dcf9a","sex":1,"pack_id":30256,"related_url_a":"","base_info":{"cooperation_index":null}},"domains":"","professions":"\u7f51\u7edc\u7ea2\u4eba","cooperation_index":"\u4e2d","reference_price_range_default":{"min":0,"max":0},"reference_price_range_multi_top":{"min":0,"max":0},"reference_price_range_multi_second":{"min":0,"max":0},"reference_price_range_multi_other":{"min":0,"max":0},"reference_price_range_single":{"min":0,"max":0},"audience_profile":"","work_nature":"","company_name":"","work_position":"","school_name":"","work_nature_be_identified":"","work_nature_be_identified_time":"","creations":[],"pyq_account_daily_update_images":"","reference_gross_price_original_release":"500000.00","reference_gross_price_video_release":"800000.00","reference_gross_price_guerilla_advertising":"","reference_gross_price_filed_events":"1000000.00","reference_gross_price_guerilla_advertising_live":"400000.00","reference_net_price_original_release":"500000.00","reference_net_price_video_release":"800000.00","reference_net_price_guerilla_advertising":"","reference_net_price_filed_events":"1000000.00","reference_net_price_guerilla_advertising_live":"400000.00","account_level":"","retweet_average_like_num":"","retweet_average_posts_num":"","retweet_average_send_num":"","tweet_average_like_num":"","tweet_average_posts_num":"","tweet_average_send_num":"","fav_info":{"account_note":"","group_type":0},"average_play_num":0,"average_like_num":0,"average_posts_num":0,"max_live_audience_num":0,"average_live_audience_num":0,"average_bullet_screen_num":0,"is_select":true,"is_show_select":false,"in_picking_cart":false,"reservation_notice_short":"","external_reference_price":{"price_validity_period":{"start":"2018-07-06","end":"2018-08-31"},"original_release":{"quote":640400},"video_release":{"quote":1024600},"filed_events":{"quote":1280700},"guerilla_advertising_live":{"quote":512300}},"external_original_zhifa_price":null,"only_support_original":2,"has_pyq_account_daily_update_images":[],"in_shopping_cart":false,"screen_shot_qr_code":null,"weibo_name_cut":"&#x674e;&#x5929;&#x4f51;","video_type_cate":1,"detail_url":"\/single\/video?weibo_id=mctianyou&weibo_type=103&sign=31318112c0"}},{"id":517797,"cells":{"audience_realfans_ratio":-1,"can_origin":2,"reward":0,"account_id":517797,"user_id":234011,"owner_admin_id":754,"weibo_id":"450028565","url":"http:\/\/www.yy.com\/u\/450028565","identity_name":"\u6469\u767b\u5144\u5f1fYY","weibo_name":"&#x6469;&#x767b;&#x5144;&#x5f1f;","followers_count":"112\u4e07","retweet_price":null,"tweet_price":null,"content_price":null,"original_zhifa_price":null,"soft_tweet_price":null,"soft_retweet_price":null,"orders_monthly":0,"orders_monthly_amount":"0.00","orders_weekly":0,"orders_weekly_amount":"0.00","reservation_order_complete_count_monthly":0,"reservation_order_complete_amount_monthly":0,"weibo_type":104,"verification_info":"","introduction":"","area_id":1010101,"location":null,"freedata_picpath":null,"is_vip":2,"is_bluevip":2,"keywords":null,"hand_tags":"","content_tags":"","profit_grade":434,"account_type":null,"is_famous":1,"face_url":"http:\/\/downhdlogo.yy.com\/hdlogo\/6060\/60\/60\/18\/0526189789\/u526189789b04RjzfT.gif?44011302000069","is_daren":2,"is_sensitive":2,"gender":1,"is_enable_micro_task":1,"is_extend":1,"active_score":"0.00","audience_female_ratio":"-1.000000","audience_gender":3,"follower_be_identified":2,"is_prepayment":2,"is_original_zhifa":2,"is_sign":2,"sign_note":null,"order_settings":0,"posts_avgretweet_count":"-1.000","posts_avgcomment_count":"-1.000","soft_single_graphic_price":null,"is_reservation_promotion":false,"age":null,"area_name":"\u5317\u4eac","reservation_num":0,"price_maintain_time":"2016-10-31 14:42:44","account_avatar":"http:\/\/downhdlogo.yy.com\/hdlogo\/6060\/60\/60\/18\/0526189789\/u526189789b04RjzfT.gif?44011302000069","video_play_num":null,"video_down_num_avg":null,"video_subscribe_num":null,"average_live_play_num":null,"video_up_num_total":null,"avg_collection_count":null,"follower_be_identified_time":"1970\u5e7401\u670801\u65e5","flag":0,"is_verify":2,"is_shield":2,"is_contacted":1,"is_fake":2,"is_open":1,"cooperation_type":1,"is_closed":2,"id":"36071","pack_type":1,"pack_name":"\u6469\u767b\u5144\u5f1f","pack_info":{"pack_name":"\u6469\u767b\u5144\u5f1f","pack_type":1,"face_url":"http:\/\/downhdlogo.yy.com\/hdlogo\/6060\/60\/60\/18\/0526189789\/u526189789b04RjzfT.gif?44011302000069","sex":1,"pack_id":28439,"related_url_a":"","base_info":{"cooperation_index":null}},"domains":"","professions":"\u7f51\u7edc\u7ea2\u4eba","cooperation_index":"\u9ad8","reference_price_range_default":{"min":0,"max":0},"reference_price_range_multi_top":{"min":0,"max":0},"reference_price_range_multi_second":{"min":0,"max":0},"reference_price_range_multi_other":{"min":0,"max":0},"reference_price_range_single":{"min":0,"max":0},"audience_profile":"","work_nature":"","company_name":"","work_position":"","school_name":"","work_nature_be_identified":"","work_nature_be_identified_time":"","creations":[],"pyq_account_daily_update_images":"","reference_gross_price_original_release":"","reference_gross_price_video_release":"","reference_gross_price_guerilla_advertising":"","reference_gross_price_filed_events":"40000.00","reference_gross_price_guerilla_advertising_live":"20000.00","reference_net_price_original_release":"","reference_net_price_video_release":"","reference_net_price_guerilla_advertising":"","reference_net_price_filed_events":"40000.00","reference_net_price_guerilla_advertising_live":"20000.00","account_level":"","retweet_average_like_num":"","retweet_average_posts_num":"","retweet_average_send_num":"","tweet_average_like_num":"","tweet_average_posts_num":"","tweet_average_send_num":"","operation_tag":[],"fav_info":{"account_note":"","group_type":0},"average_play_num":0,"average_like_num":0,"average_posts_num":0,"max_live_audience_num":0,"average_live_audience_num":0,"average_bullet_screen_num":0,"is_select":true,"is_show_select":false,"in_picking_cart":false,"reservation_notice_short":"","external_reference_price":{"price_validity_period":{"start":"2017-06-11","end":"2017-06-11"},"filed_events":{"quote":51300},"guerilla_advertising_live":{"quote":27200}},"external_original_zhifa_price":null,"only_support_original":2,"has_pyq_account_daily_update_images":[],"in_shopping_cart":false,"screen_shot_qr_code":null,"weibo_name_cut":"&#x6469;&#x767b;&#x5144;&#x5f1f;","video_type_cate":1,"detail_url":"\/single\/video?weibo_id=450028565&weibo_type=104&sign=3d388d710b"}},{"id":516087,"cells":{"audience_realfans_ratio":-1,"can_origin":2,"reward":0,"account_id":516087,"user_id":215299,"owner_admin_id":569,"weibo_id":"25451766","url":null,"identity_name":"\u738b\u5c0f\u5708","weibo_name":"&#x9648;&#x5c0f;&#x4e54;","followers_count":2043,"retweet_price":null,"tweet_price":null,"content_price":null,"original_zhifa_price":null,"soft_tweet_price":null,"soft_retweet_price":null,"orders_monthly":0,"orders_monthly_amount":"0.00","orders_weekly":0,"orders_weekly_amount":"0.00","reservation_order_complete_count_monthly":0,"reservation_order_complete_amount_monthly":0,"weibo_type":105,"verification_info":"","introduction":"","area_id":0,"location":null,"freedata_picpath":null,"is_vip":0,"is_bluevip":-1,"keywords":null,"hand_tags":"","content_tags":"","profit_grade":434,"account_type":null,"is_famous":1,"face_url":"http:\/\/img.meelive.cn\/NzEzOTgxNDYzMzg1MDAy.jpg","is_daren":-1,"is_sensitive":2,"gender":2,"is_enable_micro_task":1,"is_extend":1,"active_score":"0.00","audience_female_ratio":"-1.000000","audience_gender":-1,"follower_be_identified":2,"is_prepayment":2,"is_original_zhifa":2,"is_sign":2,"sign_note":null,"order_settings":0,"posts_avgretweet_count":"-1.000","posts_avgcomment_count":"-1.000","soft_single_graphic_price":null,"is_reservation_promotion":false,"age":"95\u540e","area_name":"","reservation_num":1,"price_maintain_time":"2016-10-18 16:00:32","account_avatar":"http:\/\/img.meelive.cn\/NzEzOTgxNDYzMzg1MDAy.jpg","video_play_num":null,"video_down_num_avg":null,"video_subscribe_num":null,"average_live_play_num":null,"video_up_num_total":null,"avg_collection_count":null,"follower_be_identified_time":"1970\u5e7401\u670801\u65e5","flag":0,"is_verify":2,"is_shield":2,"is_contacted":1,"is_fake":2,"is_open":1,"is_closed":2,"id":"35931","pack_type":1,"pack_name":"\u9648\u5c0f\u4e54","pack_info":{"pack_name":"\u9648\u5c0f\u4e54","pack_type":1,"face_url":"http:\/\/img.meelive.cn\/NzEzOTgxNDYzMzg1MDAy.jpg","sex":2,"pack_id":28319,"related_url_a":"","base_info":{"cooperation_index":null}},"domains":"","professions":"\u7f51\u7edc\u7ea2\u4eba","cooperation_index":"\u4e2d","reference_price_range_default":{"min":0,"max":0},"reference_price_range_multi_top":{"min":0,"max":0},"reference_price_range_multi_second":{"min":0,"max":0},"reference_price_range_multi_other":{"min":0,"max":0},"reference_price_range_single":{"min":0,"max":0},"audience_profile":"","work_nature":"","company_name":"","work_position":"","school_name":"","work_nature_be_identified":"","work_nature_be_identified_time":"","creations":[],"pyq_account_daily_update_images":"","reference_gross_price_original_release":"","reference_gross_price_video_release":"","reference_gross_price_guerilla_advertising":"","reference_gross_price_filed_events":"6440.00","reference_gross_price_guerilla_advertising_live":"6440.00","reference_net_price_original_release":"","reference_net_price_video_release":"","reference_net_price_guerilla_advertising":"","reference_net_price_filed_events":"6440.00","reference_net_price_guerilla_advertising_live":"6440.00","account_level":8,"retweet_average_like_num":"","retweet_average_posts_num":"","retweet_average_send_num":"","tweet_average_like_num":"","tweet_average_posts_num":"","tweet_average_send_num":"","operation_tag":[],"fav_info":{"account_note":"","group_type":0},"average_play_num":0,"average_like_num":0,"average_posts_num":0,"max_live_audience_num":0,"average_live_audience_num":0,"average_bullet_screen_num":0,"is_select":true,"is_show_select":false,"in_picking_cart":false,"reservation_notice_short":"","external_reference_price":{"price_validity_period":{"start":"2018-07-21","end":"2018-12-31"},"filed_events":{"quote":9400},"guerilla_advertising_live":{"quote":9400}},"external_original_zhifa_price":null,"only_support_original":2,"has_pyq_account_daily_update_images":[],"in_shopping_cart":false,"screen_shot_qr_code":null,"weibo_name_cut":"&#x9648;&#x5c0f;&#x4e54;","video_type_cate":1,"detail_url":"\/single\/video?weibo_id=25451766&weibo_type=105&sign=2e52c7d42a"}},{"id":515667,"cells":{"audience_realfans_ratio":-1,"can_origin":2,"reward":0,"account_id":515667,"user_id":223705,"owner_admin_id":1007,"weibo_id":"2089","url":null,"identity_name":"longxichuanmei1","weibo_name":"mc&#x4e5d;&#x5c40;","followers_count":"594\u4e07","retweet_price":null,"tweet_price":null,"content_price":null,"original_zhifa_price":null,"soft_tweet_price":null,"soft_retweet_price":null,"orders_monthly":0,"orders_monthly_amount":"0.00","orders_weekly":0,"orders_weekly_amount":"0.00","reservation_order_complete_count_monthly":0,"reservation_order_complete_amount_monthly":0,"weibo_type":104,"verification_info":"","introduction":"","area_id":-1,"location":null,"freedata_picpath":null,"is_vip":2,"is_bluevip":2,"keywords":null,"hand_tags":"","content_tags":"","profit_grade":668,"account_type":null,"is_famous":1,"face_url":"http:\/\/img.weiboyi.com\/img\/uploadimg\/weixin_follower_img\/?20160921190359","is_daren":2,"is_sensitive":2,"gender":3,"is_enable_micro_task":1,"is_extend":1,"active_score":"0.00","audience_female_ratio":"-1.000000","audience_gender":3,"follower_be_identified":2,"is_prepayment":2,"is_original_zhifa":2,"is_sign":2,"sign_note":null,"order_settings":0,"posts_avgretweet_count":"-1.000","posts_avgcomment_count":"-1.000","soft_single_graphic_price":null,"is_reservation_promotion":false,"age":null,"area_name":"","reservation_num":7,"price_maintain_time":"2018-08-14 14:02:55","account_avatar":"http:\/\/img.weiboyi.com\/img\/uploadimg\/weixin_follower_img\/?20160921190359","video_play_num":null,"video_down_num_avg":null,"video_subscribe_num":null,"average_live_play_num":null,"video_up_num_total":null,"avg_collection_count":null,"follower_be_identified_time":"1970\u5e7401\u670801\u65e5","flag":0,"is_verify":2,"is_shield":2,"is_contacted":1,"is_fake":2,"is_open":1,"is_closed":2,"account_introduction":"\u7f51\u7edcMC\u7684\u53d1\u626c\u8005\uff0c\u4e5d\u5bb6\u97f3\u4e50\u4f20\u5a92\u521b\u59cb\u4eba\u3002","id":"35759","pack_type":1,"pack_name":"mc\u4e5d\u5c40","pack_info":{"pack_name":"mc\u4e5d\u5c40","pack_type":1,"face_url":"http:\/\/img.weiboyi.com\/img\/uploadimg\/weixin_follower_img\/?20160921190359","sex":3,"pack_id":28160,"related_url_a":"","base_info":{"cooperation_index":null}},"domains":"","professions":"\u7f51\u7edc\u7ea2\u4eba","cooperation_index":"\u9ad8","reference_price_range_default":{"min":0,"max":0},"reference_price_range_multi_top":{"min":0,"max":0},"reference_price_range_multi_second":{"min":0,"max":0},"reference_price_range_multi_other":{"min":0,"max":0},"reference_price_range_single":{"min":0,"max":0},"audience_profile":"","work_nature":"","company_name":"","work_position":"","school_name":"","work_nature_be_identified":"","work_nature_be_identified_time":"","creations":[],"pyq_account_daily_update_images":"","reference_gross_price_original_release":"","reference_gross_price_video_release":"","reference_gross_price_guerilla_advertising":"","reference_gross_price_filed_events":"80000.00","reference_gross_price_guerilla_advertising_live":"80000.00","reference_net_price_original_release":"","reference_net_price_video_release":"","reference_net_price_guerilla_advertising":"","reference_net_price_filed_events":"80000.00","reference_net_price_guerilla_advertising_live":"80000.00","account_level":"","retweet_average_like_num":"","retweet_average_posts_num":"","retweet_average_send_num":"","tweet_average_like_num":"","tweet_average_posts_num":"","tweet_average_send_num":"","operation_tag":[],"fav_info":{"account_note":"","group_type":0},"average_play_num":0,"average_like_num":0,"average_posts_num":0,"max_live_audience_num":0,"average_live_audience_num":0,"average_bullet_screen_num":0,"is_select":true,"is_show_select":false,"in_picking_cart":false,"reservation_notice_short":"","external_reference_price":{"price_validity_period":{"start":"2018-08-14","end":"2018-09-30"},"filed_events":{"quote":102600},"guerilla_advertising_live":{"quote":102600}},"external_original_zhifa_price":null,"only_support_original":2,"has_pyq_account_daily_update_images":[],"in_shopping_cart":false,"screen_shot_qr_code":null,"weibo_name_cut":"mc&#x4e5d;&#x5c40;","video_type_cate":1,"detail_url":"\/single\/video?weibo_id=2089&weibo_type=104&sign=485a606c12"}},{"id":515636,"cells":{"audience_realfans_ratio":-1,"can_origin":2,"reward":0,"account_id":515636,"user_id":191340,"owner_admin_id":922,"weibo_id":"2391","url":null,"identity_name":"\u6c88\u66fc","weibo_name":"&#x6c88;&#x66fc;","followers_count":"717\u4e07","retweet_price":null,"tweet_price":null,"content_price":null,"original_zhifa_price":null,"soft_tweet_price":null,"soft_retweet_price":null,"orders_monthly":0,"orders_monthly_amount":"0.00","orders_weekly":0,"orders_weekly_amount":"0.00","reservation_order_complete_count_monthly":0,"reservation_order_complete_amount_monthly":0,"weibo_type":104,"verification_info":"","introduction":"","area_id":1012501,"location":null,"freedata_picpath":null,"is_vip":2,"is_bluevip":2,"keywords":null,"hand_tags":"","content_tags":"","profit_grade":668,"account_type":null,"is_famous":1,"face_url":"http:\/\/img.weiboyi.com\/img\/uploadimg\/weixin_follower_img\/?20160921190359","is_daren":2,"is_sensitive":2,"gender":2,"is_enable_micro_task":1,"is_extend":1,"active_score":"0.00","audience_female_ratio":"-1.000000","audience_gender":3,"follower_be_identified":2,"is_prepayment":1,"is_original_zhifa":2,"is_sign":2,"sign_note":null,"order_settings":0,"posts_avgretweet_count":"-1.000","posts_avgcomment_count":"-1.000","soft_single_graphic_price":null,"is_reservation_promotion":false,"age":null,"area_name":"\u56db\u5ddd.\u6210\u90fd","reservation_num":3,"price_maintain_time":"2018-04-02 10:45:01","account_avatar":"http:\/\/img.weiboyi.com\/img\/uploadimg\/weixin_follower_img\/?20160921190359","operation_tag":[],"video_play_num":null,"video_down_num_avg":null,"video_subscribe_num":null,"average_live_play_num":null,"video_up_num_total":null,"avg_collection_count":null,"follower_be_identified_time":"1970\u5e7401\u670801\u65e5","flag":0,"is_verify":2,"is_shield":2,"is_contacted":1,"is_fake":2,"is_open":1,"cooperation_type":1,"is_closed":2,"account_introduction":"YY\u5a31\u4e5017\u5e74\u97f3\u4e50\u51a0\u519b\uff0c\u4ee3\u8868\u4f5c\uff08\u76d0\u4e0d\u53ca\u6cea\u54b8\uff09\uff08\u7b49\u4e00\u4e2a\u4eba\uff09\u7b49","id":"35736","pack_type":1,"pack_name":"\u6c88\u66fc","pack_info":{"pack_name":"\u6c88\u66fc","pack_type":1,"face_url":"http:\/\/img.weiboyi.com\/img\/uploadimg\/weixin_follower_img\/?20160921190359","sex":3,"pack_id":28137,"related_url_a":"","base_info":{"cooperation_index":null}},"domains":"","professions":"\u7f51\u7edc\u7ea2\u4eba","cooperation_index":"\u9ad8","reference_price_range_default":{"min":0,"max":0},"reference_price_range_multi_top":{"min":0,"max":0},"reference_price_range_multi_second":{"min":0,"max":0},"reference_price_range_multi_other":{"min":0,"max":0},"reference_price_range_single":{"min":0,"max":0},"audience_profile":"","work_nature":"","company_name":"","work_position":"","school_name":"","work_nature_be_identified":"","work_nature_be_identified_time":"","creations":[],"pyq_account_daily_update_images":"","reference_gross_price_original_release":"","reference_gross_price_video_release":"","reference_gross_price_guerilla_advertising":"","reference_gross_price_filed_events":"200000.00","reference_gross_price_guerilla_advertising_live":"","reference_net_price_original_release":"","reference_net_price_video_release":"","reference_net_price_guerilla_advertising":"","reference_net_price_filed_events":"200000.00","reference_net_price_guerilla_advertising_live":"","account_level":"","retweet_average_like_num":"","retweet_average_posts_num":"","retweet_average_send_num":"","tweet_average_like_num":"","tweet_average_posts_num":"","tweet_average_send_num":"","fav_info":{"account_note":"","group_type":0},"average_play_num":0,"average_like_num":0,"average_posts_num":0,"max_live_audience_num":0,"average_live_audience_num":0,"average_bullet_screen_num":0,"is_select":true,"is_show_select":false,"in_picking_cart":false,"reservation_notice_short":"","external_reference_price":{"price_validity_period":{"start":"2018-04-02","end":"2018-05-05"},"filed_events":{"quote":228000},"guerilla_advertising_live":{"quote":0}},"external_original_zhifa_price":null,"only_support_original":2,"has_pyq_account_daily_update_images":[],"in_shopping_cart":false,"screen_shot_qr_code":null,"weibo_name_cut":"&#x6c88;&#x66fc;","video_type_cate":1,"detail_url":"\/single\/video?weibo_id=2391&weibo_type=104&sign=5daa353be5"}},{"id":514951,"cells":{"audience_realfans_ratio":-1,"can_origin":2,"reward":0,"account_id":514951,"user_id":123966,"owner_admin_id":669,"weibo_id":"46476297","url":null,"identity_name":"\u9057\u843d\u7684\u9b54\u672f","weibo_name":"&#x9057;&#x843d;&#x7684;&#x9b54;&#x672f;&#x7cbe;","followers_count":"23\u4e07","retweet_price":null,"tweet_price":null,"content_price":null,"original_zhifa_price":null,"soft_tweet_price":null,"soft_retweet_price":null,"orders_monthly":0,"orders_monthly_amount":"0.00","orders_weekly":0,"orders_weekly_amount":"0.00","reservation_order_complete_count_monthly":0,"reservation_order_complete_amount_monthly":0,"weibo_type":105,"verification_info":"\u4e0a\u6d77\u83b1\u59ff\u5316\u5986\u54c1\u6709\u9650\u516c\u53f8 \u8d22\u52a1\u90e8\u603b\u76d1","introduction":"","area_id":0,"location":null,"freedata_picpath":null,"is_vip":1,"is_bluevip":-1,"keywords":null,"hand_tags":"","content_tags":"","profit_grade":605,"account_type":null,"is_famous":1,"face_url":"http:\/\/tva4.sinaimg.cn\/crop.0.0.482.482.1024\/87de42dfjw1ehfw38ywy1j20dh0lgwh2.jpg","is_daren":-1,"is_sensitive":2,"gender":2,"is_enable_micro_task":1,"is_extend":1,"active_score":"0.00","audience_female_ratio":"-1.000000","audience_gender":-1,"follower_be_identified":2,"is_prepayment":2,"is_original_zhifa":2,"is_sign":2,"sign_note":null,"order_settings":0,"posts_avgretweet_count":"-1.000","posts_avgcomment_count":"-1.000","soft_single_graphic_price":null,"is_reservation_promotion":false,"age":"95\u540e","area_name":"","reservation_num":1,"price_maintain_time":"2017-07-07 15:15:02","account_avatar":"http:\/\/tva4.sinaimg.cn\/crop.0.0.482.482.1024\/87de42dfjw1ehfw38ywy1j20dh0lgwh2.jpg","video_play_num":null,"video_down_num_avg":null,"video_subscribe_num":null,"average_live_play_num":null,"video_up_num_total":null,"avg_collection_count":null,"follower_be_identified_time":"1970\u5e7401\u670801\u65e5","flag":0,"is_verify":2,"is_shield":2,"is_contacted":1,"is_fake":2,"is_open":1,"cooperation_type":1,"is_closed":2,"account_introduction":"\u7f8e\u5986","id":"35702","pack_type":1,"pack_name":"\u9057\u843d\u7684\u9b54\u672f\u7cbe","pack_info":{"pack_name":"\u9057\u843d\u7684\u9b54\u672f\u7cbe","pack_type":1,"face_url":"http:\/\/tva4.sinaimg.cn\/crop.0.0.482.482.180\/87de42dfjw1ehfw38ywy1j20dh0lgwh2.jpg","sex":2,"pack_id":28103,"related_url_a":"","base_info":{"cooperation_index":null}},"domains":"","professions":"\u7f51\u7edc\u7ea2\u4eba","cooperation_index":"\u4e2d","reference_price_range_default":{"min":0,"max":0},"reference_price_range_multi_top":{"min":0,"max":0},"reference_price_range_multi_second":{"min":0,"max":0},"reference_price_range_multi_other":{"min":0,"max":0},"reference_price_range_single":{"min":0,"max":0},"audience_profile":"","work_nature":"","company_name":"","work_position":"","school_name":"","work_nature_be_identified":"","work_nature_be_identified_time":"","creations":[],"pyq_account_daily_update_images":"","reference_gross_price_original_release":"","reference_gross_price_video_release":"","reference_gross_price_guerilla_advertising":"","reference_gross_price_filed_events":"7000.00","reference_gross_price_guerilla_advertising_live":"5000.00","reference_net_price_original_release":"","reference_net_price_video_release":"","reference_net_price_guerilla_advertising":"","reference_net_price_filed_events":"7000.00","reference_net_price_guerilla_advertising_live":"","account_level":11,"retweet_average_like_num":"","retweet_average_posts_num":"","retweet_average_send_num":"","tweet_average_like_num":"","tweet_average_posts_num":"","tweet_average_send_num":"","operation_tag":[],"fav_info":{"account_note":"","group_type":0},"average_play_num":0,"average_like_num":0,"average_posts_num":0,"max_live_audience_num":0,"average_live_audience_num":0,"average_bullet_screen_num":0,"is_select":true,"is_show_select":false,"in_picking_cart":false,"reservation_notice_short":"","external_reference_price":{"price_validity_period":{"start":"2017-07-07","end":"2017-08-05"},"filed_events":{"quote":10200},"guerilla_advertising_live":{"quote":0}},"external_original_zhifa_price":null,"only_support_original":2,"has_pyq_account_daily_update_images":[],"in_shopping_cart":false,"screen_shot_qr_code":null,"weibo_name_cut":"&#x9057;&#x843d;&#x7684;&#x9b54;&#x672f;&#x7cbe;","video_type_cate":1,"detail_url":"\/single\/video?weibo_id=46476297&weibo_type=105&sign=31647ffb91"}},{"id":514735,"cells":{"audience_realfans_ratio":-1,"can_origin":2,"reward":0,"account_id":514735,"user_id":14182,"owner_admin_id":669,"weibo_id":"143200283","url":null,"identity_name":"\u8349\u8393\u5c0f\u73a9\u5b50","weibo_name":"&#x8349;&#x8393;&#x5c0f;&#x73a9;&#x5b50;&#x4e28;","followers_count":"10\u4e07","retweet_price":null,"tweet_price":null,"content_price":null,"original_zhifa_price":null,"soft_tweet_price":null,"soft_retweet_price":null,"orders_monthly":0,"orders_monthly_amount":"0.00","orders_weekly":0,"orders_weekly_amount":"0.00","reservation_order_complete_count_monthly":0,"reservation_order_complete_amount_monthly":0,"weibo_type":105,"verification_info":"Onlystar\u7b7e\u7ea6\u8fbe\u4eba \u7f8e\u5986\u5927\u8d5b\u51a0\u519b \u65f6\u5c1a\u64b0\u7a3f\u4eba \u65b0\u6d6a\u65f6\u5c1a\u7f8e\u642d\u4e13\u5bb6","introduction":"\u77e5\u540d\u65f6\u5c1a\u535a\u4e3b\uff0c\u7f8e\u5bb9\u8fbe\u4eba\uff0c\u5f69\u5986\u8fbe\u4eba\uff0c\u65c5\u6e38\u8fbe\u4eba\uff0c\u65f6\u5c1a\u8fbe\u4eba\uff0c\u642d\u914d\u8fbe\u4eba\u3002","area_id":101030101,"location":null,"freedata_picpath":null,"is_vip":1,"is_bluevip":-1,"keywords":null,"hand_tags":"","content_tags":"","profit_grade":668,"account_type":null,"is_famous":1,"face_url":"http:\/\/tva2.sinaimg.cn\/crop.83.650.1666.1666.1024\/6d5a67d1jw8f6rcgnavduj21jk2bce81.jpg","is_daren":-1,"is_sensitive":2,"gender":2,"is_enable_micro_task":1,"is_extend":1,"active_score":"0.00","audience_female_ratio":"-1.000000","audience_gender":-1,"follower_be_identified":2,"is_prepayment":2,"is_original_zhifa":2,"is_sign":2,"sign_note":null,"order_settings":0,"posts_avgretweet_count":"-1.000","posts_avgcomment_count":"-1.000","soft_single_graphic_price":null,"is_reservation_promotion":false,"age":"90\u540e","area_name":"\u798f\u5efa.\u798f\u5dde","reservation_num":0,"price_maintain_time":"2018-05-08 16:45:24","account_avatar":"http:\/\/tva2.sinaimg.cn\/crop.83.650.1666.1666.1024\/6d5a67d1jw8f6rcgnavduj21jk2bce81.jpg","video_play_num":null,"video_down_num_avg":null,"video_subscribe_num":null,"average_live_play_num":null,"video_up_num_total":null,"avg_collection_count":null,"follower_be_identified_time":"1970\u5e7401\u670801\u65e5","flag":0,"is_verify":2,"is_shield":2,"is_contacted":1,"is_fake":2,"is_open":1,"is_closed":2,"account_introduction":"\u7f8e\u5986\u535a\u4e3b","id":"35405","pack_type":1,"pack_name":"\u8349\u8393\u5c0f\u73a9\u5b50\u4e28","pack_info":{"pack_name":"\u8349\u8393\u5c0f\u73a9\u5b50\u4e28","pack_type":1,"face_url":"http:\/\/tva2.sinaimg.cn\/crop.83.650.1666.1666.1024\/6d5a67d1jw8f6rcgnavduj21jk2bce81.jpg","brief_introduction":"","reservation_notice":"","location":"","choose_me_reason":"","success_case":"","industry":"","history_case":"","blood_type":"","hometown":"","height":"","alias":"","eng_name":"","birth_date":"","nationality":"","ethnic":"","education":"","feature":"","full_introduction":"","weight":"","achievement":"","related_url":"","sex":2,"pack_id":27822,"related_url_a":"","base_info":{"cooperation_index":null}},"domains":"","professions":"\u7f51\u7edc\u7ea2\u4eba","cooperation_index":"\u4e2d","reference_price_range_default":{"min":0,"max":0},"reference_price_range_multi_top":{"min":0,"max":0},"reference_price_range_multi_second":{"min":0,"max":0},"reference_price_range_multi_other":{"min":0,"max":0},"reference_price_range_single":{"min":0,"max":0},"audience_profile":"","work_nature":"","company_name":"","work_position":"","school_name":"","work_nature_be_identified":"","work_nature_be_identified_time":"","creations":[],"pyq_account_daily_update_images":"","reference_gross_price_original_release":"","reference_gross_price_video_release":"","reference_gross_price_guerilla_advertising":"","reference_gross_price_filed_events":"5000.00","reference_gross_price_guerilla_advertising_live":"3000.00","reference_net_price_original_release":"","reference_net_price_video_release":"","reference_net_price_guerilla_advertising":"","reference_net_price_filed_events":"5000.00","reference_net_price_guerilla_advertising_live":"3000.00","account_level":3,"retweet_average_like_num":"","retweet_average_posts_num":"","retweet_average_send_num":"","tweet_average_like_num":"","tweet_average_posts_num":"","tweet_average_send_num":"","operation_tag":[],"fav_info":{"account_note":"","group_type":0},"average_play_num":0,"average_like_num":0,"average_posts_num":0,"max_live_audience_num":0,"average_live_audience_num":0,"average_bullet_screen_num":0,"is_select":true,"is_show_select":false,"in_picking_cart":false,"reservation_notice_short":"","external_reference_price":{"price_validity_period":{"start":"2018-01-03","end":"2018-12-31"},"filed_events":{"quote":7300},"guerilla_advertising_live":{"quote":4700}},"external_original_zhifa_price":null,"only_support_original":2,"has_pyq_account_daily_update_images":[],"in_shopping_cart":false,"screen_shot_qr_code":null,"weibo_name_cut":"&#x8349;&#x8393;&#x5c0f;&#x73a9;&#x5b50;&#x4e28;","video_type_cate":1,"detail_url":"\/single\/video?weibo_id=143200283&weibo_type=105&sign=908de0f122"}},{"id":513969,"cells":{"audience_realfans_ratio":-1,"can_origin":2,"reward":0,"account_id":513969,"user_id":193555,"owner_admin_id":949,"weibo_id":"41673549","url":null,"identity_name":"tiffany","weibo_name":"Tiffany_cmo","followers_count":"26\u4e07","retweet_price":null,"tweet_price":null,"content_price":null,"original_zhifa_price":null,"soft_tweet_price":null,"soft_retweet_price":null,"orders_monthly":0,"orders_monthly_amount":"0.00","orders_weekly":0,"orders_weekly_amount":"0.00","reservation_order_complete_count_monthly":0,"reservation_order_complete_amount_monthly":0,"weibo_type":105,"verification_info":"","introduction":"\u627f\u63a5\u4e3b\u64ad\u7ebf\u4e0a\u7ebf\u4e0b\u63a8\u5e7f","area_id":0,"location":null,"freedata_picpath":null,"is_vip":0,"is_bluevip":2,"keywords":null,"hand_tags":"","content_tags":"","profit_grade":434,"account_type":null,"is_famous":1,"face_url":"http:\/\/img2.inke.cn\/MTQ5MjQ5NTI1MzkwMyM4NjIjanBn.jpg","is_daren":2,"is_sensitive":2,"gender":2,"is_enable_micro_task":1,"is_extend":1,"active_score":"0.00","audience_female_ratio":"-1.000000","audience_gender":3,"follower_be_identified":2,"is_prepayment":2,"is_original_zhifa":2,"is_sign":2,"sign_note":null,"order_settings":0,"posts_avgretweet_count":"-1.000","posts_avgcomment_count":"-1.000","soft_single_graphic_price":null,"is_reservation_promotion":false,"age":"90\u540e","area_name":"","reservation_num":1,"price_maintain_time":"2017-07-19 19:29:11","account_avatar":"http:\/\/img2.inke.cn\/MTQ5MjQ5NTI1MzkwMyM4NjIjanBn.jpg","video_play_num":null,"video_down_num_avg":null,"video_subscribe_num":null,"average_live_play_num":null,"video_up_num_total":null,"avg_collection_count":null,"follower_be_identified_time":"1970\u5e7401\u670801\u65e5","flag":0,"is_verify":2,"is_shield":2,"is_contacted":1,"is_fake":2,"is_open":1,"cooperation_type":1,"is_closed":2,"account_introduction":"\u9b45\u529b\u7a7a\u95f4 \u804c\u5458","id":"34995","pack_type":1,"pack_name":"Xiao\u6cab","pack_info":{"pack_name":"Xiao\u6cab","pack_type":1,"face_url":"http:\/\/img.meelive.cn\/MTQ3MjM2MTU1Mjg2OCMxNDUjanBn.jpg","sex":2,"pack_id":27416,"related_url_a":"","base_info":{"cooperation_index":null}},"domains":"","professions":"\u7f51\u7edc\u7ea2\u4eba","cooperation_index":"\u9ad8","reference_price_range_default":{"min":0,"max":0},"reference_price_range_multi_top":{"min":0,"max":0},"reference_price_range_multi_second":{"min":0,"max":0},"reference_price_range_multi_other":{"min":0,"max":0},"reference_price_range_single":{"min":0,"max":0},"audience_profile":"","work_nature":"","company_name":"","work_position":"","school_name":"","work_nature_be_identified":"","work_nature_be_identified_time":"","creations":[],"pyq_account_daily_update_images":"","reference_gross_price_original_release":"","reference_gross_price_video_release":"","reference_gross_price_guerilla_advertising":"","reference_gross_price_filed_events":"3000.00","reference_gross_price_guerilla_advertising_live":"1800.00","reference_net_price_original_release":"","reference_net_price_video_release":"","reference_net_price_guerilla_advertising":"","reference_net_price_filed_events":"3000.00","reference_net_price_guerilla_advertising_live":"1800.00","account_level":18,"retweet_average_like_num":"","retweet_average_posts_num":"","retweet_average_send_num":"","tweet_average_like_num":"","tweet_average_posts_num":"","tweet_average_send_num":"","operation_tag":[],"fav_info":{"account_note":"","group_type":0},"average_play_num":0,"average_like_num":0,"average_posts_num":0,"max_live_audience_num":0,"average_live_audience_num":0,"average_bullet_screen_num":0,"is_select":true,"is_show_select":false,"in_picking_cart":false,"reservation_notice_short":"","external_reference_price":{"price_validity_period":{"start":"2018-05-18","end":"2018-07-01"},"filed_events":{"quote":4700},"guerilla_advertising_live":{"quote":2800}},"external_original_zhifa_price":null,"only_support_original":2,"has_pyq_account_daily_update_images":[],"in_shopping_cart":false,"screen_shot_qr_code":null,"weibo_name_cut":"Tiffany_cmo","video_type_cate":1,"detail_url":"\/single\/video?weibo_id=41673549&weibo_type=105&sign=0c8622d173"}},{"id":513117,"cells":{"audience_realfans_ratio":-1,"can_origin":2,"reward":0,"account_id":513117,"user_id":199928,"owner_admin_id":651,"weibo_id":"462253","url":"http:\/\/www.douyu.com\/462253","identity_name":"\u83f2\u60a6","weibo_name":"&#x83f2;&#x60a6;&#x4e36;&#x53ee;&#x53ee;","followers_count":"14\u4e07","retweet_price":null,"tweet_price":null,"content_price":null,"original_zhifa_price":null,"soft_tweet_price":null,"soft_retweet_price":null,"orders_monthly":0,"orders_monthly_amount":"0.00","orders_weekly":0,"orders_weekly_amount":"0.00","reservation_order_complete_count_monthly":0,"reservation_order_complete_amount_monthly":0,"weibo_type":107,"verification_info":"","introduction":"\u65b0\u6d6a\u5fae\u535a\uff1a\u53ee\u53eelan","area_id":1012501,"location":null,"freedata_picpath":null,"is_vip":0,"is_bluevip":-1,"keywords":null,"hand_tags":"","content_tags":"","profit_grade":605,"account_type":null,"is_famous":1,"face_url":"https:\/\/apic.douyucdn.cn\/upload\/avatar\/028\/27\/92\/11_avatar_middle.jpg?rltime","is_daren":-1,"is_sensitive":2,"gender":2,"is_enable_micro_task":1,"is_extend":1,"active_score":"0.00","audience_female_ratio":"-1.000000","audience_gender":-1,"follower_be_identified":2,"is_prepayment":2,"is_original_zhifa":2,"is_sign":2,"sign_note":null,"order_settings":0,"posts_avgretweet_count":"-1.000","posts_avgcomment_count":"-1.000","soft_single_graphic_price":null,"is_reservation_promotion":false,"age":"90\u540e","area_name":"\u56db\u5ddd.\u6210\u90fd","reservation_num":1,"price_maintain_time":"2017-09-27 17:40:40","account_avatar":"https:\/\/apic.douyucdn.cn\/upload\/avatar\/028\/27\/92\/11_avatar_middle.jpg?rltime","video_play_num":null,"video_down_num_avg":null,"video_subscribe_num":null,"average_live_play_num":null,"video_up_num_total":null,"avg_collection_count":null,"follower_be_identified_time":"1970\u5e7401\u670801\u65e5","flag":0,"is_verify":2,"is_shield":2,"is_contacted":1,"is_fake":2,"is_open":1,"cooperation_type":1,"is_closed":2,"account_introduction":"\u989c\u503c\u4e3b\u64ad\u3002\u83f2\u60a6\u7b7e\u7ea6\u4e3b\u64ad","id":"34583","pack_type":1,"pack_name":"\u83f2\u60a6\u4e36\u53ee\u53ee","pack_info":{"pack_name":"\u83f2\u60a6\u4e36\u53ee\u53ee","pack_type":1,"face_url":"https:\/\/apic.douyucdn.cn\/upload\/avatar\/028\/27\/92\/11_avatar_middle.jpg?rltime","sex":2,"pack_id":27012,"related_url_a":"","base_info":{"cooperation_index":null}},"domains":"","professions":"\u7f51\u7edc\u7ea2\u4eba","cooperation_index":"\u4e2d","reference_price_range_default":{"min":0,"max":0},"reference_price_range_multi_top":{"min":0,"max":0},"reference_price_range_multi_second":{"min":0,"max":0},"reference_price_range_multi_other":{"min":0,"max":0},"reference_price_range_single":{"min":0,"max":0},"audience_profile":"","work_nature":"","company_name":"","work_position":"","school_name":"","work_nature_be_identified":"","work_nature_be_identified_time":"","creations":[],"pyq_account_daily_update_images":"","reference_gross_price_original_release":"","reference_gross_price_video_release":"","reference_gross_price_guerilla_advertising":"","reference_gross_price_filed_events":"","reference_gross_price_guerilla_advertising_live":"12000.00","reference_net_price_original_release":"","reference_net_price_video_release":"","reference_net_price_guerilla_advertising":"","reference_net_price_filed_events":"","reference_net_price_guerilla_advertising_live":"12000.00","account_level":"","retweet_average_like_num":"","retweet_average_posts_num":"","retweet_average_send_num":"","tweet_average_like_num":"","tweet_average_posts_num":"","tweet_average_send_num":"","operation_tag":[],"fav_info":{"account_note":"","group_type":0},"average_play_num":0,"average_like_num":0,"average_posts_num":0,"max_live_audience_num":0,"average_live_audience_num":0,"average_bullet_screen_num":0,"is_select":true,"is_show_select":false,"in_picking_cart":false,"reservation_notice_short":"","external_reference_price":{"price_validity_period":{"start":"2017-09-27","end":"2017-10-31"},"filed_events":{"quote":0},"guerilla_advertising_live":{"quote":16400}},"external_original_zhifa_price":null,"only_support_original":2,"has_pyq_account_daily_update_images":[],"in_shopping_cart":false,"screen_shot_qr_code":null,"weibo_name_cut":"&#x83f2;&#x60a6;&#x4e36;&#x53ee;&#x53ee;","video_type_cate":1,"detail_url":"\/single\/video?weibo_id=462253&weibo_type=107&sign=4154fc0aaf"}},{"id":513072,"cells":{"audience_realfans_ratio":-1,"can_origin":2,"reward":0,"account_id":513072,"user_id":102974,"owner_admin_id":716,"weibo_id":"16825343","url":"http:\/\/www.yy.com\/16825343","identity_name":"\u73a9\u8f66\u6559\u6388\u5fae\u4fe1","weibo_name":"&#x73a9;&#x8f66;&#x6559;&#x6388;","followers_count":"2\u4e07","retweet_price":null,"tweet_price":null,"content_price":null,"original_zhifa_price":null,"soft_tweet_price":null,"soft_retweet_price":null,"orders_monthly":0,"orders_monthly_amount":"0.00","orders_weekly":0,"orders_weekly_amount":"0.00","reservation_order_complete_count_monthly":0,"reservation_order_complete_amount_monthly":0,"weibo_type":104,"verification_info":"","introduction":"","area_id":1010501,"location":null,"freedata_picpath":null,"is_vip":2,"is_bluevip":2,"keywords":null,"hand_tags":"","content_tags":"","profit_grade":434,"account_type":null,"is_famous":1,"face_url":"http:\/\/img.weiboyi.com\/vol1\/1\/102\/139\/g\/v\/s90n7o3373r211r69p9p40qn8613p9o9\/11.jpg","is_daren":2,"is_sensitive":2,"gender":3,"is_enable_micro_task":1,"is_extend":1,"active_score":"0.00","audience_female_ratio":"-1.000000","audience_gender":3,"follower_be_identified":2,"is_prepayment":2,"is_original_zhifa":2,"is_sign":2,"sign_note":null,"order_settings":0,"posts_avgretweet_count":"-1.000","posts_avgcomment_count":"-1.000","soft_single_graphic_price":null,"is_reservation_promotion":false,"age":null,"area_name":"\u5e7f\u4e1c.\u5e7f\u5dde","reservation_num":4,"price_maintain_time":"2017-05-13 11:16:42","account_avatar":"http:\/\/img.weiboyi.com\/vol1\/1\/102\/139\/g\/v\/s90n7o3373r211r69p9p40qn8613p9o9\/11.jpg","video_play_num":null,"video_down_num_avg":null,"video_subscribe_num":null,"average_live_play_num":null,"video_up_num_total":null,"avg_collection_count":null,"follower_be_identified_time":"1970\u5e7401\u670801\u65e5","flag":0,"is_verify":2,"is_shield":2,"is_contacted":1,"is_fake":2,"is_open":1,"is_closed":2,"id":"34533","pack_type":1,"pack_name":"\u73a9\u8f66\u6559\u6388","pack_info":{"pack_name":"\u73a9\u8f66\u6559\u6388","pack_type":1,"face_url":"http:\/\/img.weiboyi.com\/vol1\/1\/102\/139\/g\/v\/s90n7o3373r211r69p9p40qn8613p9o9\/11.jpg","sex":3,"pack_id":26963,"related_url_a":"","base_info":{"cooperation_index":null}},"domains":"","professions":"\u7f51\u7edc\u7ea2\u4eba","cooperation_index":"\u9ad8","reference_price_range_default":{"min":0,"max":0},"reference_price_range_multi_top":{"min":0,"max":0},"reference_price_range_multi_second":{"min":0,"max":0},"reference_price_range_multi_other":{"min":0,"max":0},"reference_price_range_single":{"min":0,"max":0},"audience_profile":"","work_nature":"","company_name":"","work_position":"","school_name":"","work_nature_be_identified":"","work_nature_be_identified_time":"","creations":[],"pyq_account_daily_update_images":"","reference_gross_price_original_release":"","reference_gross_price_video_release":"","reference_gross_price_guerilla_advertising":"","reference_gross_price_filed_events":"100000.00","reference_gross_price_guerilla_advertising_live":"50000.00","reference_net_price_original_release":"","reference_net_price_video_release":"","reference_net_price_guerilla_advertising":"","reference_net_price_filed_events":"100000.00","reference_net_price_guerilla_advertising_live":"50000.00","account_level":"","retweet_average_like_num":"","retweet_average_posts_num":"","retweet_average_send_num":"","tweet_average_like_num":"","tweet_average_posts_num":"","tweet_average_send_num":"","operation_tag":[],"fav_info":{"account_note":"","group_type":0},"average_play_num":0,"average_like_num":0,"average_posts_num":0,"max_live_audience_num":0,"average_live_audience_num":0,"average_bullet_screen_num":0,"is_select":true,"is_show_select":false,"in_picking_cart":false,"reservation_notice_short":"","external_reference_price":{"price_validity_period":{"start":"2018-07-25","end":"2018-12-31"},"filed_events":{"quote":114000},"guerilla_advertising_live":{"quote":60300}},"external_original_zhifa_price":null,"only_support_original":2,"has_pyq_account_daily_update_images":[],"in_shopping_cart":false,"screen_shot_qr_code":null,"weibo_name_cut":"&#x73a9;&#x8f66;&#x6559;&#x6388;","video_type_cate":1,"detail_url":"\/single\/video?weibo_id=16825343&weibo_type=104&sign=2931c5b182"}},{"id":513071,"cells":{"audience_realfans_ratio":-1,"can_origin":2,"reward":0,"account_id":513071,"user_id":102974,"owner_admin_id":716,"weibo_id":"793029","url":"http:\/\/www.douyu.com\/793029","identity_name":"\u73a9\u8f66\u6559\u6388\u5fae\u4fe1","weibo_name":"&#x73a9;&#x8f66;&#x6559;&#x6388;Jacky","followers_count":1688,"retweet_price":null,"tweet_price":null,"content_price":null,"original_zhifa_price":null,"soft_tweet_price":null,"soft_retweet_price":null,"orders_monthly":0,"orders_monthly_amount":"0.00","orders_weekly":0,"orders_weekly_amount":"0.00","reservation_order_complete_count_monthly":0,"reservation_order_complete_amount_monthly":0,"weibo_type":107,"verification_info":"","introduction":"","area_id":0,"location":null,"freedata_picpath":null,"is_vip":2,"is_bluevip":2,"keywords":null,"hand_tags":"","content_tags":"","profit_grade":434,"account_type":null,"is_famous":1,"face_url":"https:\/\/apic.douyucdn.cn\/upload\/avatar\/face\/201607\/24\/5e0ec5a899187baab4508c9b11d3232f_middle.jpg?rltime","is_daren":2,"is_sensitive":2,"gender":3,"is_enable_micro_task":1,"is_extend":1,"active_score":"0.00","audience_female_ratio":"-1.000000","audience_gender":3,"follower_be_identified":2,"is_prepayment":2,"is_original_zhifa":2,"is_sign":2,"sign_note":null,"order_settings":0,"posts_avgretweet_count":"-1.000","posts_avgcomment_count":"-1.000","soft_single_graphic_price":null,"is_reservation_promotion":false,"age":null,"area_name":"","reservation_num":1,"price_maintain_time":"2017-05-13 11:16:42","account_avatar":"https:\/\/apic.douyucdn.cn\/upload\/avatar\/face\/201607\/24\/5e0ec5a899187baab4508c9b11d3232f_middle.jpg?rltime","video_play_num":null,"video_down_num_avg":null,"video_subscribe_num":null,"average_live_play_num":null,"video_up_num_total":null,"avg_collection_count":null,"follower_be_identified_time":"1970\u5e7401\u670801\u65e5","flag":0,"is_verify":2,"is_shield":2,"is_contacted":1,"is_fake":2,"is_open":1,"is_closed":2,"id":"34536","pack_type":1,"pack_name":"\u73a9\u8f66\u6559\u6388Jacky","pack_info":{"pack_name":"\u73a9\u8f66\u6559\u6388Jacky","pack_type":1,"face_url":"https:\/\/apic.douyucdn.cn\/upload\/avatar\/face\/201607\/24\/5e0ec5a899187baab4508c9b11d3232f_middle.jpg?rl","sex":3,"pack_id":26966,"related_url_a":"","base_info":{"cooperation_index":null}},"domains":"","professions":"\u7f51\u7edc\u7ea2\u4eba","cooperation_index":"\u9ad8","reference_price_range_default":{"min":0,"max":0},"reference_price_range_multi_top":{"min":0,"max":0},"reference_price_range_multi_second":{"min":0,"max":0},"reference_price_range_multi_other":{"min":0,"max":0},"reference_price_range_single":{"min":0,"max":0},"audience_profile":"","work_nature":"","company_name":"","work_position":"","school_name":"","work_nature_be_identified":"","work_nature_be_identified_time":"","creations":[],"pyq_account_daily_update_images":"","reference_gross_price_original_release":"","reference_gross_price_video_release":"","reference_gross_price_guerilla_advertising":"","reference_gross_price_filed_events":"100000.00","reference_gross_price_guerilla_advertising_live":"50000.00","reference_net_price_original_release":"","reference_net_price_video_release":"","reference_net_price_guerilla_advertising":"","reference_net_price_filed_events":"100000.00","reference_net_price_guerilla_advertising_live":"50000.00","account_level":"","retweet_average_like_num":"","retweet_average_posts_num":"","retweet_average_send_num":"","tweet_average_like_num":"","tweet_average_posts_num":"","tweet_average_send_num":"","operation_tag":[],"fav_info":{"account_note":"","group_type":0},"average_play_num":0,"average_like_num":0,"average_posts_num":0,"max_live_audience_num":0,"average_live_audience_num":0,"average_bullet_screen_num":0,"is_select":true,"is_show_select":false,"in_picking_cart":false,"reservation_notice_short":"","external_reference_price":{"price_validity_period":{"start":"2018-07-25","end":"2018-12-31"},"filed_events":{"quote":114000},"guerilla_advertising_live":{"quote":60300}},"external_original_zhifa_price":null,"only_support_original":2,"has_pyq_account_daily_update_images":[],"in_shopping_cart":false,"screen_shot_qr_code":null,"weibo_name_cut":"&#x73a9;&#x8f66;&#x6559;&#x6388;Jacky","video_type_cate":1,"detail_url":"\/single\/video?weibo_id=793029&weibo_type=107&sign=e4eb9d448d"}},{"id":512638,"cells":{"audience_realfans_ratio":-1,"can_origin":2,"reward":0,"account_id":512638,"user_id":64884,"owner_admin_id":604,"weibo_id":"139143147","url":null,"identity_name":"kittywenny","weibo_name":"kittywenny","followers_count":"25\u4e07","retweet_price":null,"tweet_price":null,"content_price":null,"original_zhifa_price":null,"soft_tweet_price":null,"soft_retweet_price":null,"orders_monthly":0,"orders_monthly_amount":"0.00","orders_weekly":0,"orders_weekly_amount":"0.00","reservation_order_complete_count_monthly":0,"reservation_order_complete_amount_monthly":0,"weibo_type":105,"verification_info":"\u8d44\u6df1\u65f6\u5c1a\u7f8e\u5bb9\u8fbe\u4eba\uff0c\u7f8e\u5bb9\u6742\u5fd7\u81ea\u7531\u64b0\u7a3f\u4eba\uff0c\u5ba2\u4e32\u54c1\u724c\u5e73\u9762\u6a21\u7279\u3002 \u5fae\u535a\u7b7e\u7ea6\u81ea\u5a92\u4f53","introduction":"\u535a\u5ba2\u8fbe\u4eba\uff0c\u5343\u4e07\u535a\u4e3b\u3002\u65b0\u6d6a\u8ba4\u8bc1\u7f8e\u5bb9\u65f6\u5c1a\u8fbe\u4eba\uff0c\u5fae\u8584\u7b7e\u7ea6\u81ea\u5a92\u4f53\u3002","area_id":0,"location":null,"freedata_picpath":null,"is_vip":1,"is_bluevip":-1,"keywords":null,"hand_tags":"","content_tags":"","profit_grade":434,"account_type":null,"is_famous":1,"face_url":"http:\/\/img2.inke.cn\/MTQ5OTM5NTg1MDU4NyM1NjYjanBn.jpg","is_daren":-1,"is_sensitive":2,"gender":2,"is_enable_micro_task":1,"is_extend":1,"active_score":"0.00","audience_female_ratio":"-1.000000","audience_gender":-1,"follower_be_identified":2,"is_prepayment":2,"is_original_zhifa":2,"is_sign":2,"sign_note":null,"order_settings":0,"posts_avgretweet_count":"-1.000","posts_avgcomment_count":"-1.000","soft_single_graphic_price":null,"is_reservation_promotion":false,"age":"95\u540e","area_name":"","reservation_num":0,"price_maintain_time":"2018-07-11 20:20:04","account_avatar":"http:\/\/img2.inke.cn\/MTQ5OTM5NTg1MDU4NyM1NjYjanBn.jpg","video_play_num":null,"video_down_num_avg":null,"video_subscribe_num":null,"average_live_play_num":null,"video_up_num_total":null,"avg_collection_count":null,"follower_be_identified_time":"1970\u5e7401\u670801\u65e5","flag":0,"is_verify":2,"is_shield":2,"is_contacted":1,"is_fake":2,"is_open":1,"cooperation_type":1,"is_closed":2,"id":"35842","pack_type":1,"pack_name":"kittywenny","pack_info":{"pack_name":"kittywenny","pack_type":1,"face_url":"http:\/\/img.meelive.cn\/OTAwMDkxNDY4NzUyMzA1.jpg","sex":2,"pack_id":28232,"related_url_a":"","base_info":{"cooperation_index":null}},"domains":"","professions":"\u7f51\u7edc\u7ea2\u4eba","cooperation_index":"\u4e2d","reference_price_range_default":{"min":0,"max":0},"reference_price_range_multi_top":{"min":0,"max":0},"reference_price_range_multi_second":{"min":0,"max":0},"reference_price_range_multi_other":{"min":0,"max":0},"reference_price_range_single":{"min":0,"max":0},"audience_profile":"","work_nature":"","company_name":"","work_position":"","school_name":"","work_nature_be_identified":"","work_nature_be_identified_time":"","creations":[],"pyq_account_daily_update_images":"","reference_gross_price_original_release":"","reference_gross_price_video_release":"","reference_gross_price_guerilla_advertising":"","reference_gross_price_filed_events":"9000.00","reference_gross_price_guerilla_advertising_live":"7000.00","reference_net_price_original_release":"","reference_net_price_video_release":"","reference_net_price_guerilla_advertising":"","reference_net_price_filed_events":"9000.00","reference_net_price_guerilla_advertising_live":"7000.00","account_level":7,"retweet_average_like_num":"","retweet_average_posts_num":"","retweet_average_send_num":"","tweet_average_like_num":"","tweet_average_posts_num":"","tweet_average_send_num":"","operation_tag":[],"fav_info":{"account_note":"","group_type":0},"average_play_num":0,"average_like_num":0,"average_posts_num":0,"max_live_audience_num":0,"average_live_audience_num":0,"average_bullet_screen_num":0,"is_select":true,"is_show_select":false,"in_picking_cart":false,"reservation_notice_short":"","external_reference_price":{"price_validity_period":{"start":"2018-07-11","end":"2018-12-31"},"filed_events":{"quote":13100},"guerilla_advertising_live":{"quote":10200}},"external_original_zhifa_price":null,"only_support_original":2,"has_pyq_account_daily_update_images":[],"in_shopping_cart":false,"screen_shot_qr_code":null,"weibo_name_cut":"kittywenny","video_type_cate":1,"detail_url":"\/single\/video?weibo_id=139143147&weibo_type=105&sign=b7333d752e"}},{"id":511109,"cells":{"audience_realfans_ratio":-1,"can_origin":2,"reward":0,"account_id":511109,"user_id":189146,"owner_admin_id":651,"weibo_id":"488789","url":"http:\/\/www.douyu.com\/488789","identity_name":"momo\u6843\u5b50\u9171","weibo_name":"MoMo&#x6843;&#x5b50;&#x9171;","followers_count":"1\u4e07","retweet_price":null,"tweet_price":null,"content_price":null,"original_zhifa_price":null,"soft_tweet_price":null,"soft_retweet_price":null,"orders_monthly":0,"orders_monthly_amount":"0.00","orders_weekly":0,"orders_weekly_amount":"0.00","reservation_order_complete_count_monthly":0,"reservation_order_complete_amount_monthly":0,"weibo_type":107,"verification_info":"","introduction":"","area_id":101050102,"location":null,"freedata_picpath":null,"is_vip":2,"is_bluevip":2,"keywords":null,"hand_tags":"","content_tags":"","profit_grade":605,"account_type":null,"is_famous":1,"face_url":"http:\/\/apic.douyucdn.cn\/upload\/avatar\/face\/201608\/09\/693e3817b7e67c2c702e210ba0ff42b7_middle.jpg?rltime","is_daren":2,"is_sensitive":2,"gender":2,"is_enable_micro_task":1,"is_extend":1,"active_score":"0.00","audience_female_ratio":"-1.000000","audience_gender":3,"follower_be_identified":2,"is_prepayment":1,"is_original_zhifa":2,"is_sign":2,"sign_note":null,"order_settings":0,"posts_avgretweet_count":"-1.000","posts_avgcomment_count":"-1.000","soft_single_graphic_price":null,"is_reservation_promotion":false,"age":"00\u540e","area_name":"\u5e7f\u4e1c.\u5e7f\u5dde","reservation_num":2,"price_maintain_time":"2017-06-07 19:10:05","account_avatar":"http:\/\/apic.douyucdn.cn\/upload\/avatar\/face\/201608\/09\/693e3817b7e67c2c702e210ba0ff42b7_middle.jpg?rltime","video_play_num":null,"video_down_num_avg":null,"video_subscribe_num":null,"average_live_play_num":null,"video_up_num_total":null,"avg_collection_count":null,"follower_be_identified_time":"1970\u5e7401\u670801\u65e5","flag":0,"is_verify":2,"is_shield":2,"is_contacted":1,"is_fake":2,"is_open":1,"is_closed":2,"account_introduction":"coser","id":"34027","pack_type":1,"pack_name":"MoMo\u6843\u5b50\u9171","pack_info":{"pack_name":"MoMo\u6843\u5b50\u9171","pack_type":1,"face_url":"http:\/\/apic.douyucdn.cn\/upload\/avatar\/face\/201608\/09\/693e3817b7e67c2c702e210ba0ff42b7_middle.jpg?rlt","sex":3,"pack_id":26476,"related_url_a":"","base_info":{"cooperation_index":null}},"domains":"","professions":"\u7f51\u7edc\u7ea2\u4eba","cooperation_index":"\u9ad8","reference_price_range_default":{"min":0,"max":0},"reference_price_range_multi_top":{"min":0,"max":0},"reference_price_range_multi_second":{"min":0,"max":0},"reference_price_range_multi_other":{"min":0,"max":0},"reference_price_range_single":{"min":0,"max":0},"audience_profile":"","work_nature":"","company_name":"","work_position":"","school_name":"","work_nature_be_identified":"","work_nature_be_identified_time":"","creations":[],"pyq_account_daily_update_images":"","reference_gross_price_original_release":"","reference_gross_price_video_release":"","reference_gross_price_guerilla_advertising":"","reference_gross_price_filed_events":"10000.00","reference_gross_price_guerilla_advertising_live":"","reference_net_price_original_release":"","reference_net_price_video_release":"","reference_net_price_guerilla_advertising":"","reference_net_price_filed_events":"10000.00","reference_net_price_guerilla_advertising_live":"","account_level":"","retweet_average_like_num":"","retweet_average_posts_num":"","retweet_average_send_num":"","tweet_average_like_num":"","tweet_average_posts_num":"","tweet_average_send_num":"","operation_tag":[],"fav_info":{"account_note":"","group_type":0},"average_play_num":0,"average_like_num":0,"average_posts_num":0,"max_live_audience_num":0,"average_live_audience_num":0,"average_bullet_screen_num":0,"is_select":true,"is_show_select":false,"in_picking_cart":false,"reservation_notice_short":"","external_reference_price":{"price_validity_period":{"start":"2017-07-19","end":"2017-08-31"},"filed_events":{"quote":15300},"guerilla_advertising_live":{"quote":0}},"external_original_zhifa_price":null,"only_support_original":2,"has_pyq_account_daily_update_images":[],"in_shopping_cart":false,"screen_shot_qr_code":null,"weibo_name_cut":"MoMo&#x6843;&#x5b50;&#x9171;","video_type_cate":1,"detail_url":"\/single\/video?weibo_id=488789&weibo_type=107&sign=5c11813f07"}},{"id":511008,"cells":{"audience_realfans_ratio":-1,"can_origin":2,"reward":0,"account_id":511008,"user_id":88270,"owner_admin_id":750,"weibo_id":"142092198","url":null,"identity_name":"\u9093\u654f\u8d24PYQ","weibo_name":"mandy_014","followers_count":"24\u4e07","retweet_price":null,"tweet_price":null,"content_price":null,"original_zhifa_price":null,"soft_tweet_price":null,"soft_retweet_price":null,"orders_monthly":0,"orders_monthly_amount":"0.00","orders_weekly":0,"orders_weekly_amount":"0.00","reservation_order_complete_count_monthly":0,"reservation_order_complete_amount_monthly":0,"weibo_type":105,"verification_info":"\u65f6\u5c1a\u8fbe\u4eba \u5e7f\u5dde\u5e02\u5929\u76c8\u5316\u5986\u54c1\u6709\u9650\u516c\u53f8\u5e02\u573a\u7b56\u5212\u4e3b\u7ba1","introduction":"\u65f6\u5c1a\u64b0\u7a3f\u4eba\u3001\u6bcd\u5a74\u8fbe\u4eba\u3001\u65c5\u6e38\u8fbe\u4eba\u3001\u65f6\u5c1a\u7f8e\u5986\u535a\u4e3b\u3002\u5728\u65f6\u5c1a\u884c\u4e1a\u6253\u6df7\u8d85\u8fc76\u5e74\uff0c\u66fe\u4e3a\u7231\u7f8e\u7f51\u7f8e\u5bb9\u7ec4\u4e0e\u65f6\u5c1a\u7ec4\u7684\u9ad8\u7ea7\u7f16\u8f91\u3002PClady\u660e\u661f\u8fbe\u4eba\u3001\u95fa\u871c\u7f51\u8ba4\u8bc1\u8fbe\u4eba\u3001\u7231\u7f8e\u7f51\u3001\u7231\u4e3d\u7f51\u7b49\u5404\u5927\u8bba\u575b\u7684\u8d44\u6df1\u8fbe\u4eba\u3002\u65b0\u6d6a\u767e\u4e07\u540d\u535a\u3001\u65b0\u6d6a\u5fae\u535a\u7b7e\u7ea6\u81ea\u5a92\u4f53\u3001\u65b0\u6d6a\u5fae\u535a\u65f6\u5c1a\u8fbe\u4eba\u3002\u641c\u72d0\u81ea\u5a92\u4f53&\u4eca\u65e5\u5934\u6761\u65f6\u5c1a\u535a\u4e3b\u3002","area_id":0,"location":null,"freedata_picpath":null,"is_vip":1,"is_bluevip":-1,"keywords":null,"hand_tags":"","content_tags":"","profit_grade":434,"account_type":null,"is_famous":1,"face_url":"http:\/\/img2.inke.cn\/MTUwMzAyODQ2ODA1MyM0NzUjanBn.jpg","is_daren":-1,"is_sensitive":2,"gender":2,"is_enable_micro_task":1,"is_extend":1,"active_score":"0.00","audience_female_ratio":"-1.000000","audience_gender":-1,"follower_be_identified":2,"is_prepayment":2,"is_original_zhifa":2,"is_sign":2,"sign_note":null,"order_settings":0,"posts_avgretweet_count":"-1.000","posts_avgcomment_count":"-1.000","soft_single_graphic_price":null,"is_reservation_promotion":false,"age":"95\u540e","area_name":"","reservation_num":3,"price_maintain_time":"2016-11-17 11:50:15","account_avatar":"http:\/\/img2.inke.cn\/MTUwMzAyODQ2ODA1MyM0NzUjanBn.jpg","video_play_num":null,"video_down_num_avg":null,"video_subscribe_num":null,"average_live_play_num":null,"video_up_num_total":null,"avg_collection_count":null,"follower_be_identified_time":"1970\u5e7401\u670801\u65e5","flag":0,"is_verify":2,"is_shield":2,"is_contacted":1,"is_fake":2,"is_open":1,"cooperation_type":1,"is_closed":2,"id":"34080","pack_type":1,"pack_name":"mandy_014","pack_info":{"pack_name":"mandy_014","pack_type":1,"face_url":"http:\/\/tva4.sinaimg.cn\/crop.0.11.490.490.1024\/4018f039jw8f5a0yxfxq7j20dm0e8aag.jpg","brief_introduction":"\u2605\u65f6\u5c1a\u64b0\u7a3f\u4eba\u3001\u6bcd\u5a74\u8fbe\u4eba\u3001\u65c5\u6e38\u8fbe\u4eba\u3001\u65f6\u5c1a\u7f8e\u5986\u535a\u4e3b\u3002\r\n\u2605\u5728\u65f6\u5c1a\u884c\u4e1a\u6253\u6df7\u8d85\u8fc76\u5e74\uff0c\u66fe\u4e3a\u7231\u7f8e\u7f51\u7f8e\u5bb9\u7ec4\u4e0e\u65f6\u5c1a\u7ec4\u7684\u9ad8\u7ea7\u7f16\u8f91\u3002\r\n\u2605PClady\u660e\u661f\u8fbe\u4eba\u3001\u95fa\u871c\u7f51\u8ba4\u8bc1\u8fbe\u4eba\u3001\u7231\u7f8e\u7f51\u3001\u7231\u4e3d\u7f51\u7b49\u5404\u5927\u8bba\u575b\u7684\u8d44\u6df1\u8fbe\u4eba\u3002\r\n\u2605\u65b0\u6d6a\u767e\u4e07\u540d\u535a\u3001\u65b0\u6d6a\u5fae\u535a\u7b7e\u7ea6\u81ea\u5a92\u4f53\u3001\u65b0\u6d6a\u5fae\u535a\u65f6\u5c1a\u8fbe\u4eba\u3002\r\n\u2605\u641c\u72d0\u81ea\u5a92\u4f53&\u4eca\u65e5\u5934\u6761\u65f6\u5c1a\u535a\u4e3b\u3002\r\n\u2605\u66fe\u4e3a\u300a...","reservation_notice":"\u5408\u4f5c\u5f62\u5f0f\u53ef\u5177\u4f53\u5546\u8bae","location":"\u5e7f\u4e1c,\u5e7f\u5dde","choose_me_reason":"\u2605\u65f6\u5c1a\u64b0\u7a3f\u4eba\u3001\u6bcd\u5a74\u8fbe\u4eba\u3001\u65c5\u6e38\u8fbe\u4eba\u3001\u65f6\u5c1a\u7f8e\u5986\u535a\u4e3b\u3002\r\n\u2605\u5728\u65f6\u5c1a\u884c\u4e1a\u6253\u6df7\u8d85\u8fc76\u5e74\uff0c\u66fe\u4e3a\u7231\u7f8e\u7f51\u7f8e\u5bb9\u7ec4\u4e0e\u65f6\u5c1a\u7ec4\u7684\u9ad8\u7ea7\u7f16\u8f91\u3002\r\n\u2605PClady\u660e\u661f\u8fbe\u4eba\u3001\u95fa\u871c\u7f51\u8ba4\u8bc1\u8fbe\u4eba\u3001\u7231\u7f8e\u7f51\u3001\u7231\u4e3d\u7f51\u7b49\u5404\u5927\u8bba\u575b\u7684\u8d44\u6df1\u8fbe\u4eba\u3002\r\n\u2605\u65b0\u6d6a\u767e\u4e07\u540d\u535a\u3001\u65b0\u6d6a\u5fae\u535a\u7b7e\u7ea6\u81ea\u5a92\u4f53\u3001\u65b0\u6d6a\u5fae\u535a\u65f6\u5c1a\u8fbe\u4eba\u3002\r\n\u2605\u641c\u72d0\u81ea\u5a92\u4f53&\u4eca\u65e5\u5934\u6761\u65f6\u5c1a\u535a\u4e3b\u3002\r\n\u2605\u66fe\u4e3a\u300a\u9999\u6e2f\u5468\u672b\u300b\u300a\u5609\u4eba\u7f8e\u5986\u300b\u7b49\u6742\u5fd7\u62a5\u520a\u64b0\u7a3f\u3002\r\n\u2605TVS2\u7535\u89c6\u8282\u76ee\u300a\u5357\u65b9\u98ce\u5c1a\u300b\u680f\u76ee\u5609\u5bbe\r\n\u2605\u2605\u4e2a\u4eba\u5fae\u535a\u7c89\u4e1d56\u4e07+\uff0c\u516c\u4f17\u53f7\u7c89\u4e1d10\u4e07+\uff0c\u670b\u53cb\u5708\u597d\u53cb5000+\uff0c\u5c0f\u7ea2\u4e66\u7c89\u4e1d3000+\u3001\u6dd8\u5b9d\u7c89\u4e1d5000+\u3001nice\u7c89\u4e1d1000+\u3001\u7f8e\u5566\u7c89\u4e1d1\u4e07+\u3001\u5988\u5988\u5708\u7c89\u4e1d6000+\r\n\r\n\u76f4\u64ad\u7ecf\u5386\uff1a\r\n\u819c\u6cd5\u4e16\u5bb6\u9762\u819c\u7ebf\u4e0a\u76f4\u64ad\u3001\u5987\u708e\u6d01\u7ebf\u4e0a\u76f4\u64ad\u3001LUX\u529b\u58eb\u643a\u624b\u989c\u8d28\u4ee3\u8a00\u4eba\u9648\u5b66\u51ac\u65b0\u54c1\u53d1\u5e03\u4f1a\u7ebf\u4e0b\u76f4\u64ad\u3001\u5e7f\u5dde\u592a\u53e4\u4ed3\u65c5\u6e38\u7ebf\u4e0b\u76f4\u64ad\u3001\u4f5b\u7f57\u4f26\u8428\u5c0f\u9547\u65c5\u6e38\u7ebf\u4e0b\u76f4\u64ad\u3001\u5b50\u521d\u7ebf\u4e0b\u76f4\u64ad\uff0c\u98ce\u884c\u725b\u5976\u6d3b\u52a8\u7ebf\u4e0b\u76f4\u64ad\uff0c58\u8f6c\u8f6capp\u7ebf\u4e0a\u76f4\u64ad\u3001\u4e09\u661fGalaxy C9Pro\u8def\u6f14\u7ebf\u4e0b\u76f4\u64ad\uff0c\u201c\u94fe\u63a5\u00b7\u672a\u6765\u7684\u5bb6\u201dTHINK\u300c\u5bb6\u300d \u5cf0\u4f1a\u66a82016\u4e2d\u56fd\u5bb6\u5c45\u5efa\u6750\u54c1\u724c\u53d1\u5c55\u8bba\u575b\u7ebf\u4e0b\u76f4\u64ad\uff0c\u5fae\u8d62\u96c6\u56e22\u5468\u5e74\u5e86\u5178\u5168\u660e\u661f\u6f14\u5531\u4f1a\u7ebf\u4e0b\u76f4\u64ad\uff0c\u7ca4\u6218\u7ca4\u52c7\u683c\u6597\u7cfb\u5217\u8d5b\u4e4b\u62f3\u4e58\u51fa\u51fb\u7ebf\u4e0b\u76f4\u64ad\uff0c\u5408\u751f\u5e7f\u573aqq family\u5723\u8bde\u4eae\u706f\u4eea\u5f0f\u7ebf\u4e0b\u76f4\u64ad\u7b49\r\n\r\n\u76f4\u64ad\u8d26\u53f7ID\r\n\u6620\u5ba2 142092198 \u7c89\u4e1d31\u4e07 \u5e73\u5747\u89c2\u770b\u4eba\u65701.7\u4e07\r\n\u7f8e\u62cd 14068247 \u7c89\u4e1d5\u4e07 \u5e73\u5747\u89c2\u770b\u4eba\u65701.5\u4e07\r\n\u4e00\u76f4\u64ad 49088458 \u7c89\u4e1d57\u4e07 \u5e73\u5747\u603b\u89c2\u770b\u4eba\u657080\u4e07","success_case":"\u76f4\u64ad\u7ecf\u5386\uff1a\r\n\u819c\u6cd5\u4e16\u5bb6\u9762\u819c\u7ebf\u4e0a\u76f4\u64ad\u3001\u5987\u708e\u6d01\u7ebf\u4e0a\u76f4\u64ad\u3001LUX\u529b\u58eb\u643a\u624b\u989c\u8d28\u4ee3\u8a00\u4eba\u9648\u5b66\u51ac\u65b0\u54c1\u53d1\u5e03\u4f1a\u7ebf\u4e0b\u76f4\u64ad\u3001\u5e7f\u5dde\u592a\u53e4\u4ed3\u65c5\u6e38\u7ebf\u4e0b\u76f4\u64ad\u3001\u4f5b\u7f57\u4f26\u8428\u5c0f\u9547\u65c5\u6e38\u7ebf\u4e0b\u76f4\u64ad\u3001\u5b50\u521d\u7ebf\u4e0b\u76f4\u64ad\uff0c\u98ce\u884c\u725b\u5976\u6d3b\u52a8\u7ebf\u4e0b\u76f4\u64ad\uff0c58\u8f6c\u8f6capp\u7ebf\u4e0a\u76f4\u64ad\u3001\u4e09\u661fGalaxy C9Pro\u8def\u6f14\u7ebf\u4e0b\u76f4\u64ad\uff0c\u201c\u94fe\u63a5\u00b7\u672a\u6765\u7684\u5bb6\u201dTHINK\u300c\u5bb6\u300d \u5cf0\u4f1a\u66a82016\u4e2d\u56fd\u5bb6\u5c45\u5efa\u6750\u54c1\u724c\u53d1\u5c55\u8bba\u575b\u7ebf\u4e0b\u76f4\u64ad\uff0c\u5fae\u8d62\u96c6\u56e22\u5468\u5e74\u5e86\u5178\u5168\u660e\u661f\u6f14\u5531\u4f1a\u7ebf\u4e0b\u76f4\u64ad\uff0c\u7ca4\u6218\u7ca4\u52c7\u683c\u6597\u7cfb\u5217\u8d5b\u4e4b\u62f3\u4e58\u51fa\u51fb\u7ebf\u4e0b\u76f4\u64ad\uff0c\u5408\u751f\u5e7f\u573aqq family\u5723\u8bde\u4eae\u706f\u4eea\u5f0f\u7ebf\u4e0b\u76f4\u64ad\u7b49","industry":"1\u3001\u65f6\u5c1a\r\n2\u3001\u7f8e\u5986\u62a4\u80a4 \u7f8e\u4f53\u7f8e\u53d1 \u670d\u9970\u642d\u914d\r\n3\u3001\u6bcd\u5a74 \u4eb2\u5b50\r\n4\u3001\u7f8e\u98df\u3001\u65c5\u6e38\u3001\u9152\u5e97\r\n5\u3001\u7535\u5b50\u4ea7\u54c1\r\n6\u3001\u53d1\u5e03\u4f1a","history_case":"\u76f4\u64ad\u7ecf\u5386\uff1a\r\n\u819c\u6cd5\u4e16\u5bb6\u9762\u819c\u7ebf\u4e0a\u76f4\u64ad\u3001\u5987\u708e\u6d01\u7ebf\u4e0a\u76f4\u64ad\u3001LUX\u529b\u58eb\u643a\u624b\u989c\u8d28\u4ee3\u8a00\u4eba\u9648\u5b66\u51ac\u65b0\u54c1\u53d1\u5e03\u4f1a\u7ebf\u4e0b\u76f4\u64ad\u3001\u5e7f\u5dde\u592a\u53e4\u4ed3\u65c5\u6e38\u7ebf\u4e0b\u76f4\u64ad\u3001\u4f5b\u7f57\u4f26\u8428\u5c0f\u9547\u65c5\u6e38\u7ebf\u4e0b\u76f4\u64ad\u3001\u5b50\u521d\u7ebf\u4e0b\u76f4\u64ad\uff0c\u98ce\u884c\u725b\u5976\u6d3b\u52a8\u7ebf\u4e0b\u76f4\u64ad\uff0c58\u8f6c\u8f6capp\u7ebf\u4e0a\u76f4\u64ad\u3001\u4e09\u661fGalaxy C9Pro\u8def\u6f14\u7ebf\u4e0b\u76f4\u64ad\uff0c\u201c\u94fe\u63a5\u00b7\u672a\u6765\u7684\u5bb6\u201dTHINK\u300c\u5bb6\u300d \u5cf0\u4f1a\u66a82016\u4e2d\u56fd\u5bb6\u5c45\u5efa\u6750\u54c1\u724c\u53d1\u5c55\u8bba\u575b\u7ebf\u4e0b\u76f4\u64ad\uff0c\u5fae\u8d62\u96c6\u56e22\u5468\u5e74\u5e86\u5178\u5168\u660e\u661f\u6f14\u5531\u4f1a\u7ebf\u4e0b\u76f4\u64ad\uff0c\u7ca4\u6218\u7ca4\u52c7\u683c\u6597\u7cfb\u5217\u8d5b\u4e4b\u62f3\u4e58\u51fa\u51fb\u7ebf\u4e0b\u76f4\u64ad\uff0c\u5408\u751f\u5e7f\u573aqq family\u5723\u8bde\u4eae\u706f\u4eea\u5f0f\u7ebf\u4e0b\u76f4\u64ad\u7b49","full_introduction":"<pre class=\"js_message_plain ng-binding\" ng-bind-html=\"message.MMActualContent\" style=\"margin-top: 0px; margin-bottom: 0px; font-family: inherit; font-size: 14px; white-space: pre-wrap; word-break: initial; color: rgb(0, 0, 0); line-height: 22.4px; background-color: rgb(178, 226, 129);\">\u2605\u65f6\u5c1a\u64b0\u7a3f\u4eba\u3001\u6bcd\u5a74\u8fbe\u4eba\u3001\u65c5\u6e38\u8fbe\u4eba\u3001\u65f6\u5c1a\u7f8e\u5986\u535a\u4e3b\u3002\n\u2605\u5728\u65f6\u5c1a\u884c\u4e1a\u6253\u6df7\u8d85\u8fc76\u5e74\uff0c\u66fe\u4e3a\u7231\u7f8e\u7f51\u7f8e\u5bb9\u7ec4\u4e0e\u65f6\u5c1a\u7ec4\u7684\u9ad8\u7ea7\u7f16\u8f91\u3002\n\u2605PClady\u660e\u661f\u8fbe\u4eba\u3001\u95fa\u871c\u7f51\u8ba4\u8bc1\u8fbe\u4eba\u3001\u7231\u7f8e\u7f51\u3001\u7231\u4e3d\u7f51\u7b49\u5404\u5927\u8bba\u575b\u7684\u8d44\u6df1\u8fbe\u4eba\u3002\n\u2605\u65b0\u6d6a\u767e\u4e07\u540d\u535a\u3001\u65b0\u6d6a\u5fae\u535a\u7b7e\u7ea6\u81ea\u5a92\u4f53\u3001\u65b0\u6d6a\u5fae\u535a\u65f6\u5c1a\u8fbe\u4eba\u3002\n\u2605\u641c\u72d0\u81ea\u5a92\u4f53&amp;\u4eca\u65e5\u5934\u6761\u65f6\u5c1a\u535a\u4e3b\u3002\n\u2605\u66fe\u4e3a\u300a\u9999\u6e2f\u5468\u672b\u300b\u300a\u5609\u4eba\u7f8e\u5986\u300b\u7b49\u6742\u5fd7\u62a5\u520a\u64b0\u7a3f\u3002\n\u2605TVS2\u7535\u89c6\u8282\u76ee\u300a\u5357\u65b9\u98ce\u5c1a\u300b\u680f\u76ee\u5609\u5bbe\n\u2605\u2605\u4e2a\u4eba\u5fae\u535a\u7c89\u4e1d56\u4e07+\uff0c\u516c\u4f17\u53f7\u7c89\u4e1d10\u4e07+\uff0c\u670b\u53cb\u5708\u597d\u53cb5000+\uff0c\u5c0f\u7ea2\u4e66\u7c89\u4e1d3000+\u3001\u6dd8\u5b9d\u7c89\u4e1d5000+\u3001nice\u7c89\u4e1d1000+\u3001\u7f8e\u5566\u7c89\u4e1d1\u4e07+\u3001\u5988\u5988\u5708\u7c89\u4e1d6000+\n\n\u76f4\u64ad\u7ecf\u5386\uff1a\n\u819c\u6cd5\u4e16\u5bb6\u9762\u819c\u7ebf\u4e0a\u76f4\u64ad\u3001\u5987\u708e\u6d01\u7ebf\u4e0a\u76f4\u64ad\u3001LUX\u529b\u58eb\u643a\u624b\u989c\u8d28\u4ee3\u8a00\u4eba\u9648\u5b66\u51ac\u65b0\u54c1\u53d1\u5e03\u4f1a\u7ebf\u4e0b\u76f4\u64ad\u3001\u5e7f\u5dde\u592a\u53e4\u4ed3\u65c5\u6e38\u7ebf\u4e0b\u76f4\u64ad\u3001\u4f5b\u7f57\u4f26\u8428\u5c0f\u9547\u65c5\u6e38\u7ebf\u4e0b\u76f4\u64ad\u3001\u5b50\u521d\u7ebf\u4e0b\u76f4\u64ad\uff0c\u98ce\u884c\u725b\u5976\u6d3b\u52a8\u7ebf\u4e0b\u76f4\u64ad\uff0c58\u8f6c\u8f6capp\u7ebf\u4e0a\u76f4\u64ad\u3001\u4e09\u661fGalaxy&nbsp;C9Pro\u8def\u6f14\u7ebf\u4e0b\u76f4\u64ad\uff0c\u201c\u94fe\u63a5\u00b7\u672a\u6765\u7684\u5bb6\u201dTHINK\u300c\u5bb6\u300d&nbsp;\u5cf0\u4f1a\u66a82016\u4e2d\u56fd\u5bb6\u5c45\u5efa\u6750\u54c1\u724c\u53d1\u5c55\u8bba\u575b\u7ebf\u4e0b\u76f4\u64ad\uff0c\u5fae\u8d62\u96c6\u56e22\u5468\u5e74\u5e86\u5178\u5168\u660e\u661f\u6f14\u5531\u4f1a\u7ebf\u4e0b\u76f4\u64ad\uff0c\u7ca4\u6218\u7ca4\u52c7\u683c\u6597\u7cfb\u5217\u8d5b\u4e4b\u62f3\u4e58\u51fa\u51fb\u7ebf\u4e0b\u76f4\u64ad\uff0c\u5408\u751f\u5e7f\u573aqq&nbsp;family\u5723\u8bde\u4eae\u706f\u4eea\u5f0f\u7ebf\u4e0b\u76f4\u64ad\u7b49\n\n\u76f4\u64ad\u8d26\u53f7ID\n\u6620\u5ba2&nbsp;142092198&nbsp;\u7c89\u4e1d31\u4e07&nbsp;\u5e73\u5747\u89c2\u770b\u4eba\u65701.7\u4e07\n\u7f8e\u62cd&nbsp;14068247&nbsp;\u7c89\u4e1d5\u4e07&nbsp;\u5e73\u5747\u89c2\u770b\u4eba\u65701.5\u4e07\n\u4e00\u76f4\u64ad&nbsp;49088458&nbsp;\u7c89\u4e1d57\u4e07&nbsp;\u5e73\u5747\u603b\u89c2\u770b\u4eba\u657080\u4e07<\/pre><p><br\/><\/p>","related_url":"http:\/\/weibo.com\/1075376185","sex":2,"pack_id":26529,"related_url_a":"<a href='http:\/\/weibo.com\/1075376185' target='_blank'>http:\/\/weibo.com\/1075376185<\/a>","base_info":{"cooperation_index":null}},"domains":"","professions":"\u7f51\u7edc\u7ea2\u4eba \u65f6\u5c1a\u8fbe\u4eba","cooperation_index":"\u4e2d","reference_price_range_default":{"min":0,"max":0},"reference_price_range_multi_top":{"min":0,"max":0},"reference_price_range_multi_second":{"min":0,"max":0},"reference_price_range_multi_other":{"min":0,"max":0},"reference_price_range_single":{"min":0,"max":0},"audience_profile":"\u7c89\u4e1d\u53d7\u4f17\u4e3b\u8981\u662f80\u300190\u540e\u5e74\u8f7b\u6d88\u8d39\u7fa4\u4f53\uff0c\u6d88\u8d39\u80fd\u529b\u8f83\u5f3a\uff0c\u8d2d\u4e70\u529b\u5f3a\u5927\uff0c\u613f\u610f\u63a5\u53d7\u65b0\u751f\u4e8b\u7269","work_nature":"","company_name":"","work_position":"","school_name":"","work_nature_be_identified":"","work_nature_be_identified_time":"","creations":[],"pyq_account_daily_update_images":"","reference_gross_price_original_release":"","reference_gross_price_video_release":"","reference_gross_price_guerilla_advertising":"","reference_gross_price_filed_events":"2000.00","reference_gross_price_guerilla_advertising_live":"1500.00","reference_net_price_original_release":"","reference_net_price_video_release":"","reference_net_price_guerilla_advertising":"","reference_net_price_filed_events":"2000.00","reference_net_price_guerilla_advertising_live":"1500.00","account_level":6,"retweet_average_like_num":"","retweet_average_posts_num":"","retweet_average_send_num":"","tweet_average_like_num":"","tweet_average_posts_num":"","tweet_average_send_num":"","operation_tag":[],"fav_info":{"account_note":"","group_type":0},"average_play_num":0,"average_like_num":0,"average_posts_num":0,"max_live_audience_num":0,"average_live_audience_num":0,"average_bullet_screen_num":0,"is_select":true,"is_show_select":false,"in_picking_cart":false,"reservation_notice_short":"","external_reference_price":{"price_validity_period":{"start":"2018-05-16","end":"2018-06-30"},"filed_events":{"quote":3100},"guerilla_advertising_live":{"quote":2400}},"external_original_zhifa_price":null,"only_support_original":2,"has_pyq_account_daily_update_images":[],"in_shopping_cart":false,"screen_shot_qr_code":null,"weibo_name_cut":"mandy_014","video_type_cate":1,"detail_url":"\/single\/video?weibo_id=142092198&weibo_type=105&sign=b70ea1db02"}}]}}