{"code":1000,"msg":"success","data":{"start":5800,"limit":20,"total":6995,"checkable":false,"rows":[{"id":494292,"cells":{"audience_realfans_ratio":0,"can_origin":1,"snbt":0,"latest_update_time":1508417158,"reward":0,"max_play_num":268838,"average_play_num":"6\u4e07","average_comment_num":848,"account_id":494292,"average_like_num":"1\u4e07","average_bullet_screen_num":681,"snbt_exponent":0,"last_active_time":1508417158,"max_live_audience_num":"26\u4e07","average_live_audience_num":"6\u4e07","average_posts_num":848,"user_id":180634,"owner_admin_id":696,"weibo_id":"6161559","url":"https:\/\/space.bilibili.com\/6161559#\/","identity_name":"\u6851\u845a\u4e0a\u7684\u7334\u5b50","weibo_name":"&#x6851;&#x845a;&#x4e0a;&#x7684;&#x7334;&#x5b50;","followers_count":"4\u4e07","retweet_price":null,"tweet_price":null,"content_price":null,"original_zhifa_price":null,"soft_tweet_price":null,"soft_retweet_price":null,"orders_monthly":0,"orders_monthly_amount":"0.00","orders_weekly":0,"orders_weekly_amount":"0.00","reservation_order_complete_count_monthly":0,"reservation_order_complete_amount_monthly":0,"weibo_type":110,"verification_info":"","introduction":"","area_id":-1,"location":null,"freedata_picpath":null,"is_vip":2,"is_bluevip":2,"keywords":null,"hand_tags":"","content_tags":"","profit_grade":605,"account_type":null,"is_famous":1,"face_url":"http:\/\/i2.hdslb.com\/bfs\/face\/05bc2b7619789e1dc781c5b3ee536be922b23ba1.jpg","is_daren":2,"is_sensitive":2,"gender":1,"is_enable_micro_task":1,"is_extend":1,"active_score":"0.00","audience_female_ratio":"-1.000000","audience_gender":3,"follower_be_identified":2,"is_prepayment":2,"is_original_zhifa":2,"is_sign":2,"sign_note":null,"order_settings":0,"posts_avgretweet_count":"-1.000","posts_avgcomment_count":"-1.000","soft_single_graphic_price":null,"is_reservation_promotion":false,"age":0,"area_name":"","reservation_num":0,"price_maintain_time":"2017-05-22 15:42:17","account_avatar":"http:\/\/i2.hdslb.com\/bfs\/face\/05bc2b7619789e1dc781c5b3ee536be922b23ba1.jpg","video_play_num":null,"video_down_num_avg":null,"video_subscribe_num":null,"average_live_play_num":null,"video_up_num_total":null,"avg_collection_count":null,"follower_be_identified_time":"1970\u5e7401\u670801\u65e5","flag":0,"is_verify":2,"is_shield":2,"is_contacted":1,"is_fake":2,"is_open":1,"is_closed":2,"account_introduction":"\u7ffb\u5531UP\u4e3b\u3002\u5fae\u535a\/\u7f51\u6613\u4e91@\u6851\u845a\u4e0a\u7684\u7334\u5b50 \u5357\u5317\u8282\u6c14\u4e13\u9898cd\u300a\u8282\u6c14\u7269\u8bed\u300b\u901a\u8d29\u4e2d\uff01\u5730\u5740\uff1a http:\/\/t.cn\/RtodXZ2","id":"28299","pack_type":1,"pack_name":"\u6851\u845a\u4e0a\u7684\u7334\u5b50","pack_info":{"pack_name":"\u6851\u845a\u4e0a\u7684\u7334\u5b50","pack_type":1,"face_url":"http:\/\/i0.hdslb.com\/bfs\/face\/b24865e64a5d9a1d840cf7c227098541bbd058f0.jpg","sex":1,"pack_id":20879,"related_url_a":"","base_info":{"cooperation_index":null}},"domains":"","professions":"\u7f51\u7edc\u7ea2\u4eba","cooperation_index":"\u9ad8","reference_price_range_default":{"min":0,"max":0},"reference_price_range_multi_top":{"min":0,"max":0},"reference_price_range_multi_second":{"min":0,"max":0},"reference_price_range_multi_other":{"min":0,"max":0},"reference_price_range_single":{"min":0,"max":0},"audience_profile":"","work_nature":"","company_name":"","work_position":"","school_name":"","work_nature_be_identified":"","work_nature_be_identified_time":"","creations":[],"pyq_account_daily_update_images":"","reference_gross_price_original_release":"10000.00","reference_gross_price_video_release":"","reference_gross_price_guerilla_advertising":"","reference_gross_price_filed_events":"","reference_gross_price_guerilla_advertising_live":"","reference_net_price_original_release":"10000.00","reference_net_price_video_release":"","reference_net_price_guerilla_advertising":"","reference_net_price_filed_events":"","reference_net_price_guerilla_advertising_live":"","account_level":"","retweet_average_like_num":"","retweet_average_posts_num":"","retweet_average_send_num":"","tweet_average_like_num":"","tweet_average_posts_num":"","tweet_average_send_num":"","operation_tag":[],"fav_info":{"account_note":"","group_type":0},"is_select":true,"is_show_select":false,"in_picking_cart":false,"reservation_notice_short":"","external_reference_price":{"price_validity_period":{"start":"2018-03-30","end":"2018-04-30"},"original_release":{"quote":13600},"video_release":{"quote":0},"filed_events":{"quote":0},"guerilla_advertising_live":{"quote":0}},"external_original_zhifa_price":null,"only_support_original":2,"video_original_release_paly_net_price":0,"video_release_paly_net_price":0,"video_guerilla_advertising_paly_net_price":0,"operator_kol_inner_ratio_gender_pattern_top":[],"operator_kol_inner_ratio_age_pattern_top":[],"operator_kol_inner_ratio_province_pattern_top":[],"operator_kol_inner_ratio_interest_pattern_top":[],"has_pyq_account_daily_update_images":[],"in_shopping_cart":false,"screen_shot_qr_code":null,"weibo_name_cut":"&#x6851;&#x845a;&#x4e0a;&#x7684;&#x7334;&#x5b50;","video_type_cate":2,"detail_url":"\/single\/video?weibo_id=6161559&weibo_type=110&sign=f824983807"}},{"id":494290,"cells":{"audience_realfans_ratio":0,"can_origin":1,"snbt":0,"latest_update_time":1532073888,"reward":0,"max_play_num":657697,"average_play_num":"1\u4e07","average_comment_num":256,"account_id":494290,"average_like_num":1103,"average_bullet_screen_num":201,"snbt_exponent":0,"last_active_time":1532073888,"max_live_audience_num":"65\u4e07","average_live_audience_num":"1\u4e07","average_posts_num":256,"user_id":180633,"owner_admin_id":696,"weibo_id":"337006","url":"https:\/\/space.bilibili.com\/337006#\/","identity_name":"\u4e94\u8272\u77f3\u5357\u53f6","weibo_name":"&#x4e94;&#x8272;&#x77f3;&#x5357;&#x53f6;","followers_count":"13\u4e07","retweet_price":null,"tweet_price":null,"content_price":null,"original_zhifa_price":null,"soft_tweet_price":null,"soft_retweet_price":null,"orders_monthly":0,"orders_monthly_amount":"0.00","orders_weekly":0,"orders_weekly_amount":"0.00","reservation_order_complete_count_monthly":0,"reservation_order_complete_amount_monthly":0,"weibo_type":110,"verification_info":"","introduction":"\u661f\u4e4b\u58f0\u4e2d\u6587\u914d\u97f3\u7ec4\n","area_id":-1,"location":null,"freedata_picpath":null,"is_vip":2,"is_bluevip":2,"keywords":null,"hand_tags":"","content_tags":"","profit_grade":605,"account_type":null,"is_famous":1,"face_url":"http:\/\/i1.hdslb.com\/bfs\/face\/726f3b86151fa70bcfdfe68eb00268cfc5e981c4.jpg","is_daren":2,"is_sensitive":2,"gender":1,"is_enable_micro_task":1,"is_extend":1,"active_score":"0.00","audience_female_ratio":"-1.000000","audience_gender":3,"follower_be_identified":2,"is_prepayment":2,"is_original_zhifa":2,"is_sign":2,"sign_note":null,"order_settings":0,"posts_avgretweet_count":"-1.000","posts_avgcomment_count":"-1.000","soft_single_graphic_price":null,"is_reservation_promotion":false,"age":0,"area_name":"","reservation_num":2,"price_maintain_time":"2017-07-19 19:33:42","account_avatar":"http:\/\/i1.hdslb.com\/bfs\/face\/726f3b86151fa70bcfdfe68eb00268cfc5e981c4.jpg","operation_tag":[],"video_play_num":null,"video_down_num_avg":null,"video_subscribe_num":null,"average_live_play_num":null,"video_up_num_total":null,"avg_collection_count":null,"follower_be_identified_time":"1970\u5e7401\u670801\u65e5","flag":0,"is_verify":2,"is_shield":2,"is_contacted":1,"is_fake":2,"is_open":1,"is_closed":2,"account_introduction":"\u97f3\u4e50UP\u4e3b\u3002\u5fae\u535a\uff1a@\u4e94\u8272\u77f3\u5357\u53f6 ","id":"28298","pack_type":1,"pack_name":"\u4e94\u8272\u77f3\u5357\u53f6","pack_info":{"pack_name":"\u4e94\u8272\u77f3\u5357\u53f6","pack_type":1,"face_url":"http:\/\/i0.hdslb.com\/bfs\/face\/ee94984e97d2ca91d3f0864b77e9ee054051f931.jpg","sex":1,"pack_id":20878,"related_url_a":"","base_info":{"cooperation_index":null}},"domains":"","professions":"\u7f51\u7edc\u7ea2\u4eba","cooperation_index":"\u9ad8","reference_price_range_default":{"min":0,"max":0},"reference_price_range_multi_top":{"min":0,"max":0},"reference_price_range_multi_second":{"min":0,"max":0},"reference_price_range_multi_other":{"min":0,"max":0},"reference_price_range_single":{"min":0,"max":0},"audience_profile":"","work_nature":"","company_name":"","work_position":"","school_name":"","work_nature_be_identified":"","work_nature_be_identified_time":"","creations":[],"pyq_account_daily_update_images":"","reference_gross_price_original_release":"15000.00","reference_gross_price_video_release":"","reference_gross_price_guerilla_advertising":"","reference_gross_price_filed_events":"","reference_gross_price_guerilla_advertising_live":"","reference_net_price_original_release":"15000.00","reference_net_price_video_release":"","reference_net_price_guerilla_advertising":"","reference_net_price_filed_events":"","reference_net_price_guerilla_advertising_live":"","account_level":"","retweet_average_like_num":"","retweet_average_posts_num":"","retweet_average_send_num":"","tweet_average_like_num":"","tweet_average_posts_num":"","tweet_average_send_num":"","fav_info":{"account_note":"","group_type":0},"is_select":true,"is_show_select":false,"in_picking_cart":false,"reservation_notice_short":"","external_reference_price":{"price_validity_period":{"start":"2018-08-27","end":"2018-09-30"},"original_release":{"quote":20400},"video_release":{"quote":0},"filed_events":{"quote":0},"guerilla_advertising_live":{"quote":0}},"external_original_zhifa_price":null,"only_support_original":2,"video_original_release_paly_net_price":0,"video_release_paly_net_price":0,"video_guerilla_advertising_paly_net_price":0,"operator_kol_inner_ratio_gender_pattern_top":[],"operator_kol_inner_ratio_age_pattern_top":[],"operator_kol_inner_ratio_province_pattern_top":[],"operator_kol_inner_ratio_interest_pattern_top":[],"has_pyq_account_daily_update_images":[],"in_shopping_cart":false,"screen_shot_qr_code":null,"weibo_name_cut":"&#x4e94;&#x8272;&#x77f3;&#x5357;&#x53f6;","video_type_cate":2,"detail_url":"\/single\/video?weibo_id=337006&weibo_type=110&sign=c0346730c2"}},{"id":494289,"cells":{"audience_realfans_ratio":-1,"can_origin":1,"snbt":0,"latest_update_time":1533130261,"reward":0,"max_play_num":295696,"average_play_num":"6\u4e07","average_comment_num":209,"account_id":494289,"average_like_num":2576,"average_bullet_screen_num":838,"snbt_exponent":0,"last_active_time":1533130261,"max_live_audience_num":"29\u4e07","average_live_audience_num":"6\u4e07","average_posts_num":209,"user_id":223772,"owner_admin_id":715,"weibo_id":"21471064","url":"https:\/\/space.bilibili.com\/21471064#\/","identity_name":"\u9ed8\u5c0f\u5b9d","weibo_name":"Cynthia&#x9ed8;&#x5c0f;&#x5b9d;","followers_count":"26\u4e07","retweet_price":null,"tweet_price":null,"content_price":null,"original_zhifa_price":null,"soft_tweet_price":null,"soft_retweet_price":null,"orders_monthly":0,"orders_monthly_amount":"0.00","orders_weekly":0,"orders_weekly_amount":"0.00","reservation_order_complete_count_monthly":0,"reservation_order_complete_amount_monthly":0,"weibo_type":110,"verification_info":"","introduction":"","area_id":0,"location":null,"freedata_picpath":null,"is_vip":2,"is_bluevip":2,"keywords":null,"hand_tags":"","content_tags":"","profit_grade":668,"account_type":null,"is_famous":1,"face_url":"http:\/\/i2.hdslb.com\/bfs\/face\/5f385690a0dc66dcdf5276c3899bf25e6473989b.jpg","is_daren":2,"is_sensitive":2,"gender":2,"is_enable_micro_task":1,"is_extend":1,"active_score":"0.00","audience_female_ratio":"-1.000000","audience_gender":3,"follower_be_identified":2,"is_prepayment":2,"is_original_zhifa":2,"is_sign":2,"sign_note":null,"order_settings":0,"posts_avgretweet_count":"-1.000","posts_avgcomment_count":"-1.000","soft_single_graphic_price":null,"is_reservation_promotion":false,"age":0,"area_name":"","reservation_num":3,"price_maintain_time":"2018-03-29 17:19:29","account_avatar":"http:\/\/i2.hdslb.com\/bfs\/face\/5f385690a0dc66dcdf5276c3899bf25e6473989b.jpg","video_play_num":null,"video_down_num_avg":null,"video_subscribe_num":null,"average_live_play_num":null,"video_up_num_total":null,"avg_collection_count":null,"media_professional_degree_avg":null,"media_coordination_degree_avg":null,"media_appearance_degree_avg":null,"media_post_sale_review_count":null,"sale_professional_degree_avg":"4.00","sale_coordination_degree_avg":"4.00","sale_appearance_degree_avg":"4.00","sale_post_sale_review_count":1,"follower_be_identified_time":"1970\u5e7401\u670801\u65e5","flag":0,"is_verify":2,"is_shield":2,"is_contacted":1,"is_fake":2,"is_open":1,"is_closed":2,"account_introduction":"\u7f8e\u5986\u670d\u9970\u642d\u914d","id":"28297","pack_type":1,"pack_name":"Cynthia\u9ed8\u5c0f\u5b9d","pack_info":{"pack_name":"Cynthia\u9ed8\u5c0f\u5b9d","pack_type":1,"face_url":"http:\/\/i2.hdslb.com\/bfs\/face\/5f385690a0dc66dcdf5276c3899bf25e6473989b.jpg","brief_introduction":"","reservation_notice":"","location":"","choose_me_reason":"","success_case":"","industry":"","history_case":"","blood_type":"","hometown":"","height":"","alias":"","eng_name":"","birth_date":"","nationality":"","ethnic":"","education":"","feature":"","full_introduction":"","weight":"","achievement":"","related_url":"","sex":2,"pack_id":20877,"related_url_a":"","base_info":{"cooperation_index":null}},"domains":"","professions":"\u7f51\u7edc\u7ea2\u4eba","cooperation_index":"\u9ad8","reference_price_range_default":{"min":0,"max":0},"reference_price_range_multi_top":{"min":0,"max":0},"reference_price_range_multi_second":{"min":0,"max":0},"reference_price_range_multi_other":{"min":0,"max":0},"reference_price_range_single":{"min":0,"max":0},"audience_profile":"","work_nature":"","company_name":"","work_position":"","school_name":"","work_nature_be_identified":"","work_nature_be_identified_time":"","creations":[],"pyq_account_daily_update_images":"","reference_gross_price_original_release":"40000.00","reference_gross_price_video_release":"40000.00","reference_gross_price_guerilla_advertising":"","reference_gross_price_filed_events":"40000.00","reference_gross_price_guerilla_advertising_live":"","reference_net_price_original_release":"40000.00","reference_net_price_video_release":"40000.00","reference_net_price_guerilla_advertising":"","reference_net_price_filed_events":"40000.00","reference_net_price_guerilla_advertising_live":"","account_level":"","retweet_average_like_num":"","retweet_average_posts_num":"","retweet_average_send_num":"","tweet_average_like_num":"","tweet_average_posts_num":"","tweet_average_send_num":"","operation_tag":[],"fav_info":{"account_note":"","group_type":0},"is_select":true,"is_show_select":false,"in_picking_cart":false,"reservation_notice_short":"","external_reference_price":{"price_validity_period":{"start":"2018-09-19","end":"2018-10-31"},"original_release":{"quote":57300},"video_release":{"quote":57300},"filed_events":{"quote":57300},"guerilla_advertising_live":{"quote":0}},"external_original_zhifa_price":null,"only_support_original":2,"video_original_release_paly_net_price":0,"video_release_paly_net_price":0,"video_guerilla_advertising_paly_net_price":0,"operator_kol_inner_ratio_gender_pattern_top":[],"operator_kol_inner_ratio_age_pattern_top":[],"operator_kol_inner_ratio_province_pattern_top":[],"operator_kol_inner_ratio_interest_pattern_top":[],"has_pyq_account_daily_update_images":[],"in_shopping_cart":false,"screen_shot_qr_code":null,"weibo_name_cut":"Cynthia&#x9ed8;&#x5c0f;&#x5b9d;","video_type_cate":2,"detail_url":"\/single\/video?weibo_id=21471064&weibo_type=110&sign=dee7316e32"}},{"id":494288,"cells":{"audience_realfans_ratio":0,"can_origin":1,"snbt":0,"latest_update_time":1533016855,"reward":0,"max_play_num":1143422,"average_play_num":"18\u4e07","average_comment_num":832,"account_id":494288,"average_like_num":5647,"average_bullet_screen_num":1839,"snbt_exponent":0,"last_active_time":1533016855,"max_live_audience_num":"114\u4e07","average_live_audience_num":"18\u4e07","average_posts_num":832,"user_id":180631,"owner_admin_id":696,"weibo_id":"2689967","url":"https:\/\/space.bilibili.com\/2689967#\/","identity_name":"\u918b\u918bcucu","weibo_name":"&#x918b;&#x918b;cucu","followers_count":"30\u4e07","retweet_price":null,"tweet_price":null,"content_price":null,"original_zhifa_price":null,"soft_tweet_price":null,"soft_retweet_price":null,"orders_monthly":0,"orders_monthly_amount":"0.00","orders_weekly":0,"orders_weekly_amount":"0.00","reservation_order_complete_count_monthly":0,"reservation_order_complete_amount_monthly":0,"weibo_type":110,"verification_info":"","introduction":"","area_id":1012401,"location":null,"freedata_picpath":null,"is_vip":2,"is_bluevip":2,"keywords":null,"hand_tags":"","content_tags":"","profit_grade":605,"account_type":null,"is_famous":1,"face_url":"http:\/\/i2.hdslb.com\/bfs\/face\/df4575a48d76b9b547354716f635cf450f7484ad.jpg","is_daren":2,"is_sensitive":2,"gender":2,"is_enable_micro_task":1,"is_extend":1,"active_score":"0.00","audience_female_ratio":"-1.000000","audience_gender":3,"follower_be_identified":2,"is_prepayment":2,"is_original_zhifa":2,"is_sign":2,"sign_note":null,"order_settings":0,"posts_avgretweet_count":"-1.000","posts_avgcomment_count":"-1.000","soft_single_graphic_price":null,"is_reservation_promotion":false,"age":0,"area_name":"\u4e0a\u6d77","reservation_num":1,"price_maintain_time":"2017-05-22 11:46:18","account_avatar":"http:\/\/i2.hdslb.com\/bfs\/face\/df4575a48d76b9b547354716f635cf450f7484ad.jpg","operation_tag":[],"video_play_num":null,"video_down_num_avg":null,"video_subscribe_num":null,"average_live_play_num":null,"video_up_num_total":null,"avg_collection_count":null,"follower_be_identified_time":"1970\u5e7401\u670801\u65e5","flag":0,"is_verify":2,"is_shield":2,"is_contacted":1,"is_fake":2,"is_open":1,"is_closed":2,"account_introduction":"\u5b85\u821eUP\u4e3b\u3002\u840c\u59b9\u7eb8\u7684\u5b85\u821e\u6211\u53ef\u4ee5\u62b1\u7740\u770b\u4e00\u591c~~\u5fae\u535a@\u918b\u918bcucu","id":"28296","pack_type":1,"pack_name":"\u918b\u918bcucu","pack_info":{"pack_name":"\u918b\u918bcucu","pack_type":1,"face_url":"http:\/\/img.weiboyi.com\/img\/selfMedia\/151244187332322356235a26081174326.jpg","brief_introduction":"\u8fd1\u671f\u4f5c\u54c1\uff1a\u300a\u6597\u7834\u82cd\u7a79\u300b\u5c0f\u533b\u4ed9\u300a\u5929\u8c15\u300b\u77b3\u6d38\u300a\u5e7b\u7483\u955c\u300b","reservation_notice":"\u63d0\u524d\u6c9f\u901a","location":"\u4e0a\u6d77","choose_me_reason":"\u8fd1\u671f\u4f5c\u54c1\uff1a\u300a\u6597\u7834\u82cd\u7a79\u300b\u5c0f\u533b\u4ed9\u300a\u5929\u8c15\u300b\u77b3\u6d38\u300a\u5e7b\u7483\u955c\u300b","success_case":"","industry":"","history_case":"","blood_type":"","hometown":"","height":"","alias":"","eng_name":"","birth_date":"","nationality":"","ethnic":"","education":"","feature":"","full_introduction":"","weight":"","achievement":"","related_url":"","sex":2,"pack_id":20876,"related_url_a":"","base_info":{"cooperation_index":null}},"domains":"","professions":"\u7f51\u7edc\u7ea2\u4eba","cooperation_index":"\u9ad8","reference_price_range_default":{"min":0,"max":0},"reference_price_range_multi_top":{"min":0,"max":0},"reference_price_range_multi_second":{"min":0,"max":0},"reference_price_range_multi_other":{"min":0,"max":0},"reference_price_range_single":{"min":0,"max":0},"audience_profile":"","work_nature":"","company_name":"","work_position":"","school_name":"","work_nature_be_identified":"","work_nature_be_identified_time":"","creations":[],"pyq_account_daily_update_images":"","reference_gross_price_original_release":"60000.00","reference_gross_price_video_release":"","reference_gross_price_guerilla_advertising":"","reference_gross_price_filed_events":"","reference_gross_price_guerilla_advertising_live":"","reference_net_price_original_release":"60000.00","reference_net_price_video_release":"","reference_net_price_guerilla_advertising":"","reference_net_price_filed_events":"","reference_net_price_guerilla_advertising_live":"","account_level":"","retweet_average_like_num":"","retweet_average_posts_num":"","retweet_average_send_num":"","tweet_average_like_num":"","tweet_average_posts_num":"","tweet_average_send_num":"","fav_info":{"account_note":"","group_type":0},"is_select":true,"is_show_select":false,"in_picking_cart":false,"reservation_notice_short":"","external_reference_price":{"price_validity_period":{"start":"2018-08-27","end":"2018-09-30"},"original_release":{"quote":76900},"video_release":{"quote":0},"filed_events":{"quote":0},"guerilla_advertising_live":{"quote":0}},"external_original_zhifa_price":null,"only_support_original":2,"video_original_release_paly_net_price":0,"video_release_paly_net_price":0,"video_guerilla_advertising_paly_net_price":0,"operator_kol_inner_ratio_gender_pattern_top":[],"operator_kol_inner_ratio_age_pattern_top":[],"operator_kol_inner_ratio_province_pattern_top":[],"operator_kol_inner_ratio_interest_pattern_top":[],"has_pyq_account_daily_update_images":[],"in_shopping_cart":false,"screen_shot_qr_code":null,"weibo_name_cut":"&#x918b;&#x918b;cucu","video_type_cate":2,"detail_url":"\/single\/video?weibo_id=2689967&weibo_type=110&sign=185da3ae47"}},{"id":494287,"cells":{"audience_realfans_ratio":0,"can_origin":1,"snbt":0,"latest_update_time":1533207971,"reward":0,"max_play_num":1956821,"average_play_num":"65\u4e07","average_comment_num":3452,"account_id":494287,"average_like_num":"2\u4e07","average_bullet_screen_num":8260,"snbt_exponent":0,"last_active_time":1533207971,"max_live_audience_num":"195\u4e07","average_live_audience_num":"65\u4e07","average_posts_num":3452,"user_id":223571,"owner_admin_id":696,"weibo_id":"63231","url":"https:\/\/space.bilibili.com\/63231#\/","identity_name":"\u96ea\u745e","weibo_name":"&#x6cdb;&#x5f0f;","followers_count":"115\u4e07","retweet_price":null,"tweet_price":null,"content_price":null,"original_zhifa_price":null,"soft_tweet_price":null,"soft_retweet_price":null,"orders_monthly":0,"orders_monthly_amount":"0.00","orders_weekly":0,"orders_weekly_amount":"0.00","reservation_order_complete_count_monthly":0,"reservation_order_complete_amount_monthly":0,"weibo_type":110,"verification_info":"","introduction":"","area_id":-1,"location":null,"freedata_picpath":null,"is_vip":2,"is_bluevip":2,"keywords":null,"hand_tags":"","content_tags":"","profit_grade":605,"account_type":null,"is_famous":1,"face_url":"http:\/\/i0.hdslb.com\/bfs\/face\/7e04f2466f118369458cb30e5cdd47d2317454b8.jpg","is_daren":2,"is_sensitive":2,"gender":1,"is_enable_micro_task":1,"is_extend":1,"active_score":"0.00","audience_female_ratio":"-1.000000","audience_gender":3,"follower_be_identified":2,"is_prepayment":2,"is_original_zhifa":2,"is_sign":2,"sign_note":null,"order_settings":0,"posts_avgretweet_count":"-1.000","posts_avgcomment_count":"-1.000","soft_single_graphic_price":null,"is_reservation_promotion":false,"age":0,"area_name":"","reservation_num":0,"price_maintain_time":"2018-08-10 11:00:03","account_avatar":"http:\/\/i0.hdslb.com\/bfs\/face\/7e04f2466f118369458cb30e5cdd47d2317454b8.jpg","operation_tag":[],"video_play_num":null,"video_down_num_avg":null,"video_subscribe_num":null,"average_live_play_num":null,"video_up_num_total":null,"avg_collection_count":null,"follower_be_identified_time":"1970\u5e7401\u670801\u65e5","flag":0,"is_verify":2,"is_shield":2,"is_contacted":1,"is_fake":2,"is_open":1,"is_closed":2,"account_introduction":"\u52a8\u753bUP\u4e3b\u30022015\u5e74\u5ea6MAD\u8bc4\u8d4f\uff08MCA2015\uff09\u6700\u4f73\u89d2\u8272\u5851\u9020\u5956","id":"28295","pack_type":1,"pack_name":"\u6cdb\u5f0f","pack_info":{"pack_name":"\u6cdb\u5f0f","pack_type":1,"face_url":"http:\/\/i1.hdslb.com\/bfs\/face\/f9030f2b0d7efc562a843b68484c138552f2b4de.jpg","sex":1,"pack_id":20875,"related_url_a":"","base_info":{"cooperation_index":null}},"domains":"","professions":"\u7f51\u7edc\u7ea2\u4eba","cooperation_index":"\u9ad8","reference_price_range_default":{"min":0,"max":0},"reference_price_range_multi_top":{"min":0,"max":0},"reference_price_range_multi_second":{"min":0,"max":0},"reference_price_range_multi_other":{"min":0,"max":0},"reference_price_range_single":{"min":0,"max":0},"audience_profile":"","work_nature":"","company_name":"","work_position":"","school_name":"","work_nature_be_identified":"","work_nature_be_identified_time":"","creations":[],"pyq_account_daily_update_images":"","reference_gross_price_original_release":"90000.00","reference_gross_price_video_release":"","reference_gross_price_guerilla_advertising":"","reference_gross_price_filed_events":"","reference_gross_price_guerilla_advertising_live":"","reference_net_price_original_release":"90000.00","reference_net_price_video_release":"","reference_net_price_guerilla_advertising":"","reference_net_price_filed_events":"","reference_net_price_guerilla_advertising_live":"","account_level":"","retweet_average_like_num":"","retweet_average_posts_num":"","retweet_average_send_num":"","tweet_average_like_num":"","tweet_average_posts_num":"","tweet_average_send_num":"","fav_info":{"account_note":"","group_type":0},"is_select":true,"is_show_select":false,"in_picking_cart":false,"reservation_notice_short":"","external_reference_price":{"price_validity_period":{"start":"2018-08-10","end":"2018-09-30"},"original_release":{"quote":108500},"video_release":{"quote":0},"filed_events":{"quote":0},"guerilla_advertising_live":{"quote":0}},"external_original_zhifa_price":null,"only_support_original":2,"video_original_release_paly_net_price":0,"video_release_paly_net_price":0,"video_guerilla_advertising_paly_net_price":0,"operator_kol_inner_ratio_gender_pattern_top":[],"operator_kol_inner_ratio_age_pattern_top":[],"operator_kol_inner_ratio_province_pattern_top":[],"operator_kol_inner_ratio_interest_pattern_top":[],"has_pyq_account_daily_update_images":[],"in_shopping_cart":false,"screen_shot_qr_code":null,"weibo_name_cut":"&#x6cdb;&#x5f0f;","video_type_cate":2,"detail_url":"\/single\/video?weibo_id=63231&weibo_type=110&sign=13997e31aa"}},{"id":494286,"cells":{"audience_realfans_ratio":0,"can_origin":1,"snbt":0,"latest_update_time":1533702949,"reward":0,"max_play_num":348886,"average_play_num":6421,"average_comment_num":19,"account_id":494286,"average_like_num":226,"average_bullet_screen_num":29,"snbt_exponent":0,"last_active_time":1533702949,"max_live_audience_num":"34\u4e07","average_live_audience_num":6421,"average_posts_num":19,"user_id":180628,"owner_admin_id":696,"weibo_id":"4685336","url":"https:\/\/space.bilibili.com\/4685336#\/","identity_name":"\u536b\u5bab\u56db\u90de","weibo_name":"&#x536b;&#x5bab;&#x56db;&#x90de;","followers_count":"6\u4e07","retweet_price":null,"tweet_price":null,"content_price":null,"original_zhifa_price":null,"soft_tweet_price":null,"soft_retweet_price":null,"orders_monthly":0,"orders_monthly_amount":"0.00","orders_weekly":0,"orders_weekly_amount":"0.00","reservation_order_complete_count_monthly":0,"reservation_order_complete_amount_monthly":0,"weibo_type":110,"verification_info":"","introduction":"","area_id":-1,"location":null,"freedata_picpath":null,"is_vip":2,"is_bluevip":2,"keywords":null,"hand_tags":"","content_tags":"","profit_grade":605,"account_type":null,"is_famous":1,"face_url":"http:\/\/i1.hdslb.com\/bfs\/face\/97eea0a1c5ed4823bcfa4ba06b2ac456cdf37182.gif","is_daren":2,"is_sensitive":2,"gender":1,"is_enable_micro_task":1,"is_extend":1,"active_score":"0.00","audience_female_ratio":"-1.000000","audience_gender":3,"follower_be_identified":2,"is_prepayment":2,"is_original_zhifa":2,"is_sign":2,"sign_note":null,"order_settings":0,"posts_avgretweet_count":"-1.000","posts_avgcomment_count":"-1.000","soft_single_graphic_price":null,"is_reservation_promotion":false,"age":0,"area_name":"","reservation_num":0,"price_maintain_time":"2017-07-19 19:33:54","account_avatar":"http:\/\/i1.hdslb.com\/bfs\/face\/97eea0a1c5ed4823bcfa4ba06b2ac456cdf37182.gif","operation_tag":[],"video_play_num":null,"video_down_num_avg":null,"video_subscribe_num":null,"average_live_play_num":null,"video_up_num_total":null,"avg_collection_count":null,"follower_be_identified_time":"1970\u5e7401\u670801\u65e5","flag":0,"is_verify":2,"is_shield":2,"is_contacted":1,"is_fake":2,"is_open":1,"is_closed":2,"account_introduction":"\u5a31\u4e50UP\u4e3b\u3002\u76f8\u7ea6\u79cb\u540d\u5c71\uff0c\u901f\u5ea6\u4e0e\u57fa\u60c5\u3002\n \u8bf7\u7528\u53d1\u8d22\u7684\u5c0f\u624b\u5173\u6ce8\u65b0\u6d6a\u5fae\u535a@\u4e94\u82b1\u9a6c\u4e0b\u9152","id":"28294","pack_type":1,"pack_name":"\u536b\u5bab\u56db\u90de","pack_info":{"pack_name":"\u536b\u5bab\u56db\u90de","pack_type":1,"face_url":"http:\/\/i0.hdslb.com\/bfs\/face\/97eea0a1c5ed4823bcfa4ba06b2ac456cdf37182.gif","sex":1,"pack_id":20874,"related_url_a":"","base_info":{"cooperation_index":null}},"domains":"","professions":"\u7f51\u7edc\u7ea2\u4eba","cooperation_index":"\u9ad8","reference_price_range_default":{"min":0,"max":0},"reference_price_range_multi_top":{"min":0,"max":0},"reference_price_range_multi_second":{"min":0,"max":0},"reference_price_range_multi_other":{"min":0,"max":0},"reference_price_range_single":{"min":0,"max":0},"audience_profile":"","work_nature":"","company_name":"","work_position":"","school_name":"","work_nature_be_identified":"","work_nature_be_identified_time":"","creations":[],"pyq_account_daily_update_images":"","reference_gross_price_original_release":"10000.00","reference_gross_price_video_release":"","reference_gross_price_guerilla_advertising":"","reference_gross_price_filed_events":"","reference_gross_price_guerilla_advertising_live":"","reference_net_price_original_release":"10000.00","reference_net_price_video_release":"","reference_net_price_guerilla_advertising":"","reference_net_price_filed_events":"","reference_net_price_guerilla_advertising_live":"","account_level":"","retweet_average_like_num":"","retweet_average_posts_num":"","retweet_average_send_num":"","tweet_average_like_num":"","tweet_average_posts_num":"","tweet_average_send_num":"","fav_info":{"account_note":"","group_type":0},"is_select":true,"is_show_select":false,"in_picking_cart":false,"reservation_notice_short":"","external_reference_price":{"price_validity_period":{"start":"2018-04-28","end":"2018-05-31"},"original_release":{"quote":13600},"video_release":{"quote":0},"filed_events":{"quote":0},"guerilla_advertising_live":{"quote":0}},"external_original_zhifa_price":null,"only_support_original":2,"video_original_release_paly_net_price":2.118,"video_release_paly_net_price":0,"video_guerilla_advertising_paly_net_price":0,"operator_kol_inner_ratio_gender_pattern_top":[],"operator_kol_inner_ratio_age_pattern_top":[],"operator_kol_inner_ratio_province_pattern_top":[],"operator_kol_inner_ratio_interest_pattern_top":[],"has_pyq_account_daily_update_images":[],"in_shopping_cart":false,"screen_shot_qr_code":null,"weibo_name_cut":"&#x536b;&#x5bab;&#x56db;&#x90de;","video_type_cate":2,"detail_url":"\/single\/video?weibo_id=4685336&weibo_type=110&sign=55d80bcd7a"}},{"id":494285,"cells":{"audience_realfans_ratio":-1,"can_origin":1,"snbt":0,"latest_update_time":1532084414,"reward":0,"max_play_num":1395515,"average_play_num":"28\u4e07","average_comment_num":2006,"account_id":494285,"average_like_num":9145,"average_bullet_screen_num":3079,"snbt_exponent":0,"last_active_time":1532084414,"max_live_audience_num":"139\u4e07","average_live_audience_num":"28\u4e07","average_posts_num":2006,"user_id":226514,"owner_admin_id":696,"weibo_id":"639647","url":"https:\/\/space.bilibili.com\/639647#\/","identity_name":"1MILLION_OFFICIAL","weibo_name":"KAYACHANOWO","followers_count":"37\u4e07","retweet_price":null,"tweet_price":null,"content_price":null,"original_zhifa_price":null,"soft_tweet_price":null,"soft_retweet_price":null,"orders_monthly":0,"orders_monthly_amount":"0.00","orders_weekly":0,"orders_weekly_amount":"0.00","reservation_order_complete_count_monthly":0,"reservation_order_complete_amount_monthly":0,"weibo_type":110,"verification_info":"","introduction":"","area_id":-1,"location":null,"freedata_picpath":null,"is_vip":2,"is_bluevip":2,"keywords":null,"hand_tags":"","content_tags":"","profit_grade":605,"account_type":null,"is_famous":1,"face_url":"http:\/\/static.hdslb.com\/images\/member\/noface.gif","is_daren":2,"is_sensitive":2,"gender":2,"is_enable_micro_task":1,"is_extend":1,"active_score":"0.00","audience_female_ratio":"-1.000000","audience_gender":3,"follower_be_identified":2,"is_prepayment":2,"is_original_zhifa":2,"is_sign":2,"sign_note":null,"order_settings":0,"posts_avgretweet_count":"-1.000","posts_avgcomment_count":"-1.000","soft_single_graphic_price":null,"is_reservation_promotion":false,"age":0,"area_name":"","reservation_num":2,"price_maintain_time":"2017-11-24 15:50:03","account_avatar":"http:\/\/static.hdslb.com\/images\/member\/noface.gif","operation_tag":[],"video_play_num":null,"video_down_num_avg":null,"video_subscribe_num":null,"average_live_play_num":null,"video_up_num_total":null,"avg_collection_count":null,"follower_be_identified_time":"1970\u5e7401\u670801\u65e5","flag":0,"is_verify":2,"is_shield":2,"is_contacted":1,"is_fake":2,"is_open":1,"is_closed":2,"account_introduction":"\u5b85\u821eUP\u4e3b\u3002","id":"28293","pack_type":1,"pack_name":"KAYACHANOWO","pack_info":{"pack_name":"KAYACHANOWO","pack_type":1,"face_url":"http:\/\/static.hdslb.com\/images\/member\/noface.gif","sex":2,"pack_id":20873,"related_url_a":"","base_info":{"cooperation_index":null}},"domains":"","professions":"\u7f51\u7edc\u7ea2\u4eba","cooperation_index":"\u9ad8","reference_price_range_default":{"min":0,"max":0},"reference_price_range_multi_top":{"min":0,"max":0},"reference_price_range_multi_second":{"min":0,"max":0},"reference_price_range_multi_other":{"min":0,"max":0},"reference_price_range_single":{"min":0,"max":0},"audience_profile":"","work_nature":"","company_name":"","work_position":"","school_name":"","work_nature_be_identified":"","work_nature_be_identified_time":"","creations":[],"pyq_account_daily_update_images":"","reference_gross_price_original_release":"70000.00","reference_gross_price_video_release":"","reference_gross_price_guerilla_advertising":"","reference_gross_price_filed_events":"","reference_gross_price_guerilla_advertising_live":"","reference_net_price_original_release":"70000.00","reference_net_price_video_release":"","reference_net_price_guerilla_advertising":"","reference_net_price_filed_events":"","reference_net_price_guerilla_advertising_live":"","account_level":"","retweet_average_like_num":"","retweet_average_posts_num":"","retweet_average_send_num":"","tweet_average_like_num":"","tweet_average_posts_num":"","tweet_average_send_num":"","fav_info":{"account_note":"","group_type":0},"is_select":true,"is_show_select":false,"in_picking_cart":false,"reservation_notice_short":"","external_reference_price":{"price_validity_period":{"start":"2018-08-27","end":"2018-09-30"},"original_release":{"quote":84400},"video_release":{"quote":0},"filed_events":{"quote":0},"guerilla_advertising_live":{"quote":0}},"external_original_zhifa_price":null,"only_support_original":2,"video_original_release_paly_net_price":0,"video_release_paly_net_price":0,"video_guerilla_advertising_paly_net_price":0,"operator_kol_inner_ratio_gender_pattern_top":[],"operator_kol_inner_ratio_age_pattern_top":[],"operator_kol_inner_ratio_province_pattern_top":[],"operator_kol_inner_ratio_interest_pattern_top":[],"has_pyq_account_daily_update_images":[],"in_shopping_cart":false,"screen_shot_qr_code":null,"weibo_name_cut":"KAYACHANOWO","video_type_cate":2,"detail_url":"\/single\/video?weibo_id=639647&weibo_type=110&sign=d7b188aa2f"}},{"id":494284,"cells":{"audience_realfans_ratio":0,"can_origin":1,"snbt":0,"latest_update_time":1533643253,"reward":0,"max_play_num":2974112,"average_play_num":"25\u4e07","average_comment_num":2608,"account_id":494284,"average_like_num":"1\u4e07","average_bullet_screen_num":2008,"snbt_exponent":0,"last_active_time":1533643253,"max_live_audience_num":"297\u4e07","average_live_audience_num":"25\u4e07","average_posts_num":2608,"user_id":180626,"owner_admin_id":696,"weibo_id":"282994","url":"https:\/\/space.bilibili.com\/282994#\/","identity_name":"\u6ce0\u9e22yousa","weibo_name":"&#x6ce0;&#x9e22;yousa","followers_count":"122\u4e07","retweet_price":null,"tweet_price":null,"content_price":null,"original_zhifa_price":null,"soft_tweet_price":null,"soft_retweet_price":null,"orders_monthly":0,"orders_monthly_amount":"0.00","orders_weekly":0,"orders_weekly_amount":"0.00","reservation_order_complete_count_monthly":0,"reservation_order_complete_amount_monthly":0,"weibo_type":110,"verification_info":"","introduction":"","area_id":1012501,"location":null,"freedata_picpath":null,"is_vip":2,"is_bluevip":2,"keywords":null,"hand_tags":"","content_tags":"","profit_grade":605,"account_type":null,"is_famous":1,"face_url":"http:\/\/i1.hdslb.com\/bfs\/face\/3cd9998cdb9444528a4e62ed2b4e69d64282dbeb.jpg","is_daren":2,"is_sensitive":2,"gender":2,"is_enable_micro_task":1,"is_extend":1,"active_score":"0.00","audience_female_ratio":"-1.000000","audience_gender":3,"follower_be_identified":2,"is_prepayment":2,"is_original_zhifa":2,"is_sign":2,"sign_note":null,"order_settings":0,"posts_avgretweet_count":"-1.000","posts_avgcomment_count":"-1.000","soft_single_graphic_price":null,"is_reservation_promotion":false,"age":0,"area_name":"\u56db\u5ddd.\u6210\u90fd","reservation_num":4,"price_maintain_time":"2018-07-27 14:40:05","account_avatar":"http:\/\/i1.hdslb.com\/bfs\/face\/3cd9998cdb9444528a4e62ed2b4e69d64282dbeb.jpg","operation_tag":[],"video_play_num":null,"video_down_num_avg":null,"video_subscribe_num":null,"average_live_play_num":null,"video_up_num_total":null,"avg_collection_count":null,"follower_be_identified_time":"1970\u5e7401\u670801\u65e5","flag":0,"is_verify":2,"is_shield":2,"is_contacted":1,"is_fake":2,"is_open":1,"cooperation_type":1,"is_closed":2,"account_introduction":"\u7ffb\u5531UP\u4e3b\u3002bilibili \u77e5\u540dUP\u4e3b","id":"28292","pack_type":1,"pack_name":"\u6ce0\u9e22yousa","pack_info":{"pack_name":"\u6ce0\u9e22yousa","pack_type":1,"face_url":"http:\/\/i1.hdslb.com\/bfs\/face\/3cd9998cdb9444528a4e62ed2b4e69d64282dbeb.jpg","sex":2,"pack_id":20872,"related_url_a":"","base_info":{"cooperation_index":null}},"domains":"","professions":"\u7f51\u7edc\u7ea2\u4eba","cooperation_index":"\u9ad8","reference_price_range_default":{"min":0,"max":0},"reference_price_range_multi_top":{"min":0,"max":0},"reference_price_range_multi_second":{"min":0,"max":0},"reference_price_range_multi_other":{"min":0,"max":0},"reference_price_range_single":{"min":0,"max":0},"audience_profile":"","work_nature":"","company_name":"","work_position":"","school_name":"","work_nature_be_identified":"","work_nature_be_identified_time":"","creations":[],"pyq_account_daily_update_images":"","reference_gross_price_original_release":"98800.00","reference_gross_price_video_release":"","reference_gross_price_guerilla_advertising":"","reference_gross_price_filed_events":"","reference_gross_price_guerilla_advertising_live":"","reference_net_price_original_release":"98800.00","reference_net_price_video_release":"","reference_net_price_guerilla_advertising":"","reference_net_price_filed_events":"","reference_net_price_guerilla_advertising_live":"","account_level":"","retweet_average_like_num":"","retweet_average_posts_num":"","retweet_average_send_num":"","tweet_average_like_num":"","tweet_average_posts_num":"","tweet_average_send_num":"","fav_info":{"account_note":"","group_type":0},"is_select":true,"is_show_select":false,"in_picking_cart":false,"reservation_notice_short":"","external_reference_price":{"price_validity_period":{"start":"2018-07-27","end":"2018-08-31"},"original_release":{"quote":119800},"video_release":{"quote":0},"filed_events":{"quote":0},"guerilla_advertising_live":{"quote":0}},"external_original_zhifa_price":null,"only_support_original":2,"video_original_release_paly_net_price":0,"video_release_paly_net_price":0,"video_guerilla_advertising_paly_net_price":0,"operator_kol_inner_ratio_gender_pattern_top":[],"operator_kol_inner_ratio_age_pattern_top":[],"operator_kol_inner_ratio_province_pattern_top":[],"operator_kol_inner_ratio_interest_pattern_top":[],"has_pyq_account_daily_update_images":[],"in_shopping_cart":false,"screen_shot_qr_code":null,"weibo_name_cut":"&#x6ce0;&#x9e22;yousa","video_type_cate":2,"detail_url":"\/single\/video?weibo_id=282994&weibo_type=110&sign=95e90170a8"}},{"id":494283,"cells":{"audience_realfans_ratio":-1,"can_origin":1,"snbt":0,"latest_update_time":1493373648,"reward":0,"max_play_num":928276,"average_play_num":0,"average_comment_num":0,"account_id":494283,"average_like_num":0,"average_bullet_screen_num":0,"snbt_exponent":0,"last_active_time":1493373648,"max_live_audience_num":"92\u4e07","average_live_audience_num":0,"average_posts_num":0,"user_id":180623,"owner_admin_id":696,"weibo_id":"608","url":"https:\/\/space.bilibili.com\/608#\/","identity_name":"\u665a\u9999\u7389b","weibo_name":"&#x665a;&#x9999;&#x7389;","followers_count":"13\u4e07","retweet_price":null,"tweet_price":null,"content_price":null,"original_zhifa_price":null,"soft_tweet_price":null,"soft_retweet_price":null,"orders_monthly":0,"orders_monthly_amount":"0.00","orders_weekly":0,"orders_weekly_amount":"0.00","reservation_order_complete_count_monthly":0,"reservation_order_complete_amount_monthly":0,"weibo_type":110,"verification_info":"","introduction":"","area_id":-1,"location":null,"freedata_picpath":null,"is_vip":2,"is_bluevip":2,"keywords":null,"hand_tags":"","content_tags":"","profit_grade":605,"account_type":null,"is_famous":1,"face_url":"http:\/\/i1.hdslb.com\/bfs\/face\/846f8be5302745ab5e5f0e3d86b02089f380500c.jpg","is_daren":2,"is_sensitive":2,"gender":2,"is_enable_micro_task":1,"is_extend":1,"active_score":"0.00","audience_female_ratio":"-1.000000","audience_gender":3,"follower_be_identified":2,"is_prepayment":2,"is_original_zhifa":2,"is_sign":2,"sign_note":null,"order_settings":0,"posts_avgretweet_count":"-1.000","posts_avgcomment_count":"-1.000","soft_single_graphic_price":null,"is_reservation_promotion":false,"age":0,"area_name":"","reservation_num":0,"price_maintain_time":"2017-07-19 19:34:12","account_avatar":"http:\/\/i1.hdslb.com\/bfs\/face\/846f8be5302745ab5e5f0e3d86b02089f380500c.jpg","operation_tag":[],"video_play_num":null,"video_down_num_avg":null,"video_subscribe_num":null,"average_live_play_num":null,"video_up_num_total":null,"avg_collection_count":null,"follower_be_identified_time":"1970\u5e7401\u670801\u65e5","flag":0,"is_verify":2,"is_shield":2,"is_contacted":1,"is_fake":2,"is_open":1,"is_closed":2,"account_introduction":"\u5b85\u821eUP\u4e3b\u3002bilibili \u77e5\u540d\u821e\u89c1","id":"28291","pack_type":1,"pack_name":"\u665a\u9999\u7389","pack_info":{"pack_name":"\u665a\u9999\u7389","pack_type":1,"face_url":"http:\/\/i0.hdslb.com\/bfs\/face\/3d3555a0b8d6184e08a0db2b52c66523878bc734.jpg","sex":2,"pack_id":20871,"related_url_a":"","base_info":{"cooperation_index":null}},"domains":"","professions":"\u7f51\u7edc\u7ea2\u4eba","cooperation_index":"\u9ad8","reference_price_range_default":{"min":0,"max":0},"reference_price_range_multi_top":{"min":0,"max":0},"reference_price_range_multi_second":{"min":0,"max":0},"reference_price_range_multi_other":{"min":0,"max":0},"reference_price_range_single":{"min":0,"max":0},"audience_profile":"","work_nature":"","company_name":"","work_position":"","school_name":"","work_nature_be_identified":"","work_nature_be_identified_time":"","creations":[],"pyq_account_daily_update_images":"","reference_gross_price_original_release":"30000.00","reference_gross_price_video_release":"","reference_gross_price_guerilla_advertising":"","reference_gross_price_filed_events":"","reference_gross_price_guerilla_advertising_live":"","reference_net_price_original_release":"30000.00","reference_net_price_video_release":"","reference_net_price_guerilla_advertising":"","reference_net_price_filed_events":"","reference_net_price_guerilla_advertising_live":"","account_level":"","retweet_average_like_num":"","retweet_average_posts_num":"","retweet_average_send_num":"","tweet_average_like_num":"","tweet_average_posts_num":"","tweet_average_send_num":"","fav_info":{"account_note":"","group_type":0},"is_select":true,"is_show_select":false,"in_picking_cart":false,"reservation_notice_short":"","external_reference_price":{"price_validity_period":{"start":"2018-08-27","end":"2018-09-30"},"original_release":{"quote":38500},"video_release":{"quote":0},"filed_events":{"quote":0},"guerilla_advertising_live":{"quote":0}},"external_original_zhifa_price":null,"only_support_original":2,"video_original_release_paly_net_price":0,"video_release_paly_net_price":0,"video_guerilla_advertising_paly_net_price":0,"operator_kol_inner_ratio_gender_pattern_top":[],"operator_kol_inner_ratio_age_pattern_top":[],"operator_kol_inner_ratio_province_pattern_top":[],"operator_kol_inner_ratio_interest_pattern_top":[],"has_pyq_account_daily_update_images":[],"in_shopping_cart":false,"screen_shot_qr_code":null,"weibo_name_cut":"&#x665a;&#x9999;&#x7389;","video_type_cate":2,"detail_url":"\/single\/video?weibo_id=608&weibo_type=110&sign=e05ebc7bf2"}},{"id":494281,"cells":{"audience_realfans_ratio":0,"can_origin":1,"snbt":0,"latest_update_time":1532587780,"reward":0,"max_play_num":1868876,"average_play_num":"10\u4e07","average_comment_num":341,"account_id":494281,"average_like_num":2596,"average_bullet_screen_num":804,"snbt_exponent":0,"last_active_time":1532587780,"max_live_audience_num":"186\u4e07","average_live_audience_num":"10\u4e07","average_posts_num":341,"user_id":180620,"owner_admin_id":696,"weibo_id":"11443550","url":"https:\/\/space.bilibili.com\/11443550#\/","identity_name":"Mr\u4e36Yuan","weibo_name":"Mr&#x4e36;Yuan","followers_count":"25\u4e07","retweet_price":null,"tweet_price":null,"content_price":null,"original_zhifa_price":null,"soft_tweet_price":null,"soft_retweet_price":null,"orders_monthly":0,"orders_monthly_amount":"0.00","orders_weekly":0,"orders_weekly_amount":"0.00","reservation_order_complete_count_monthly":0,"reservation_order_complete_amount_monthly":0,"weibo_type":110,"verification_info":"","introduction":"","area_id":1011701,"location":null,"freedata_picpath":null,"is_vip":2,"is_bluevip":2,"keywords":null,"hand_tags":"","content_tags":"","profit_grade":605,"account_type":null,"is_famous":1,"face_url":"http:\/\/i0.hdslb.com\/bfs\/face\/d06556d06591e63801c937976861026e81f00ffd.jpg","is_daren":2,"is_sensitive":2,"gender":1,"is_enable_micro_task":1,"is_extend":1,"active_score":"0.00","audience_female_ratio":"-1.000000","audience_gender":3,"follower_be_identified":2,"is_prepayment":2,"is_original_zhifa":2,"is_sign":2,"sign_note":null,"order_settings":0,"posts_avgretweet_count":"-1.000","posts_avgcomment_count":"-1.000","soft_single_graphic_price":null,"is_reservation_promotion":false,"age":0,"area_name":"\u8fbd\u5b81.\u6c88\u9633","reservation_num":1,"price_maintain_time":"2017-09-29 15:15:02","account_avatar":"http:\/\/i0.hdslb.com\/bfs\/face\/d06556d06591e63801c937976861026e81f00ffd.jpg","operation_tag":[],"video_play_num":null,"video_down_num_avg":null,"video_subscribe_num":null,"average_live_play_num":null,"video_up_num_total":null,"avg_collection_count":null,"follower_be_identified_time":"1970\u5e7401\u670801\u65e5","flag":0,"is_verify":2,"is_shield":2,"is_contacted":1,"is_fake":2,"is_open":1,"cooperation_type":1,"is_closed":2,"account_introduction":"\u52a8\u753b\u7c7bUP\u4e3b\u3002\u6ca1\u7075\u611f...\u75db\u82e6....\u5fae\u535a@\u54b8\u9c7c\u7684Yuan","id":"28288","pack_type":1,"pack_name":"Mr\u4e36Yuan","pack_info":{"pack_name":"Mr\u4e36Yuan","pack_type":1,"face_url":"http:\/\/i1.hdslb.com\/bfs\/face\/b7e6a9e86a87529f2d3c0593b6911257179610ce.jpg","sex":1,"pack_id":20870,"related_url_a":"","base_info":{"cooperation_index":null}},"domains":"","professions":"\u7f51\u7edc\u7ea2\u4eba","cooperation_index":"\u9ad8","reference_price_range_default":{"min":0,"max":0},"reference_price_range_multi_top":{"min":0,"max":0},"reference_price_range_multi_second":{"min":0,"max":0},"reference_price_range_multi_other":{"min":0,"max":0},"reference_price_range_single":{"min":0,"max":0},"audience_profile":"","work_nature":"","company_name":"","work_position":"","school_name":"","work_nature_be_identified":"","work_nature_be_identified_time":"","creations":[],"pyq_account_daily_update_images":"","reference_gross_price_original_release":"18000.00","reference_gross_price_video_release":"","reference_gross_price_guerilla_advertising":"","reference_gross_price_filed_events":"","reference_gross_price_guerilla_advertising_live":"","reference_net_price_original_release":"18000.00","reference_net_price_video_release":"","reference_net_price_guerilla_advertising":"","reference_net_price_filed_events":"","reference_net_price_guerilla_advertising_live":"","account_level":"","retweet_average_like_num":"","retweet_average_posts_num":"","retweet_average_send_num":"","tweet_average_like_num":"","tweet_average_posts_num":"","tweet_average_send_num":"","fav_info":{"account_note":"","group_type":0},"is_select":true,"is_show_select":false,"in_picking_cart":false,"reservation_notice_short":"","external_reference_price":{"price_validity_period":{"start":"2018-08-27","end":"2018-09-30"},"original_release":{"quote":24500},"video_release":{"quote":0},"filed_events":{"quote":0},"guerilla_advertising_live":{"quote":0}},"external_original_zhifa_price":null,"only_support_original":2,"video_original_release_paly_net_price":0,"video_release_paly_net_price":0,"video_guerilla_advertising_paly_net_price":0,"operator_kol_inner_ratio_gender_pattern_top":[],"operator_kol_inner_ratio_age_pattern_top":[],"operator_kol_inner_ratio_province_pattern_top":[],"operator_kol_inner_ratio_interest_pattern_top":[],"has_pyq_account_daily_update_images":[],"in_shopping_cart":false,"screen_shot_qr_code":null,"weibo_name_cut":"Mr&#x4e36;Yuan","video_type_cate":2,"detail_url":"\/single\/video?weibo_id=11443550&weibo_type=110&sign=38846de3f5"}},{"id":494251,"cells":{"audience_realfans_ratio":-1,"can_origin":1,"snbt":0,"latest_update_time":1511858511,"reward":0,"max_play_num":631530,"average_play_num":0,"average_comment_num":0,"account_id":494251,"average_like_num":0,"average_bullet_screen_num":0,"snbt_exponent":0,"last_active_time":1511858511,"max_live_audience_num":"63\u4e07","average_live_audience_num":0,"average_posts_num":0,"user_id":180594,"owner_admin_id":696,"weibo_id":"3171301","url":"https:\/\/space.bilibili.com\/3171301#\/","identity_name":"Manager\u96f6","weibo_name":"Manager&#x96f6;","followers_count":"6\u4e07","retweet_price":null,"tweet_price":null,"content_price":null,"original_zhifa_price":null,"soft_tweet_price":null,"soft_retweet_price":null,"orders_monthly":0,"orders_monthly_amount":"0.00","orders_weekly":0,"orders_weekly_amount":"0.00","reservation_order_complete_count_monthly":0,"reservation_order_complete_amount_monthly":0,"weibo_type":110,"verification_info":"","introduction":"","area_id":-1,"location":null,"freedata_picpath":null,"is_vip":2,"is_bluevip":2,"keywords":null,"hand_tags":"","content_tags":"","profit_grade":605,"account_type":null,"is_famous":1,"face_url":"http:\/\/i2.hdslb.com\/bfs\/face\/2fabae8855cfbc0ef4fff180d5e4c131df477b87.jpg","is_daren":2,"is_sensitive":2,"gender":1,"is_enable_micro_task":1,"is_extend":1,"active_score":"0.00","audience_female_ratio":"-1.000000","audience_gender":3,"follower_be_identified":2,"is_prepayment":2,"is_original_zhifa":2,"is_sign":2,"sign_note":null,"order_settings":0,"posts_avgretweet_count":"-1.000","posts_avgcomment_count":"-1.000","soft_single_graphic_price":null,"is_reservation_promotion":false,"age":0,"area_name":"","reservation_num":0,"price_maintain_time":"2017-07-19 19:33:06","account_avatar":"http:\/\/i2.hdslb.com\/bfs\/face\/2fabae8855cfbc0ef4fff180d5e4c131df477b87.jpg","operation_tag":[],"video_play_num":null,"video_down_num_avg":null,"video_subscribe_num":null,"average_live_play_num":null,"video_up_num_total":null,"avg_collection_count":null,"follower_be_identified_time":"1970\u5e7401\u670801\u65e5","flag":0,"is_verify":2,"is_shield":2,"is_contacted":1,"is_fake":2,"is_open":1,"is_closed":2,"account_introduction":"\u7ffb\u5531UP\u4e3b\u3002\u96f6\u7684\u5fae\u535a\uff1a@\u96f6Singer","id":"28286","pack_type":1,"pack_name":"Manager\u96f6","pack_info":{"pack_name":"Manager\u96f6","pack_type":1,"face_url":"http:\/\/i1.hdslb.com\/bfs\/face\/2fabae8855cfbc0ef4fff180d5e4c131df477b87.jpg","sex":1,"pack_id":20869,"related_url_a":"","base_info":{"cooperation_index":null}},"domains":"","professions":"\u7f51\u7edc\u7ea2\u4eba","cooperation_index":"\u9ad8","reference_price_range_default":{"min":0,"max":0},"reference_price_range_multi_top":{"min":0,"max":0},"reference_price_range_multi_second":{"min":0,"max":0},"reference_price_range_multi_other":{"min":0,"max":0},"reference_price_range_single":{"min":0,"max":0},"audience_profile":"","work_nature":"","company_name":"","work_position":"","school_name":"","work_nature_be_identified":"","work_nature_be_identified_time":"","creations":[],"pyq_account_daily_update_images":"","reference_gross_price_original_release":"50000.00","reference_gross_price_video_release":"","reference_gross_price_guerilla_advertising":"","reference_gross_price_filed_events":"","reference_gross_price_guerilla_advertising_live":"","reference_net_price_original_release":"50000.00","reference_net_price_video_release":"","reference_net_price_guerilla_advertising":"","reference_net_price_filed_events":"","reference_net_price_guerilla_advertising_live":"","account_level":"","retweet_average_like_num":"","retweet_average_posts_num":"","retweet_average_send_num":"","tweet_average_like_num":"","tweet_average_posts_num":"","tweet_average_send_num":"","fav_info":{"account_note":"","group_type":0},"is_select":true,"is_show_select":false,"in_picking_cart":false,"reservation_notice_short":"","external_reference_price":{"price_validity_period":{"start":"2018-06-19","end":"2018-07-31"},"original_release":{"quote":64100},"video_release":{"quote":0},"filed_events":{"quote":0},"guerilla_advertising_live":{"quote":0}},"external_original_zhifa_price":null,"only_support_original":2,"video_original_release_paly_net_price":0,"video_release_paly_net_price":0,"video_guerilla_advertising_paly_net_price":0,"operator_kol_inner_ratio_gender_pattern_top":[],"operator_kol_inner_ratio_age_pattern_top":[],"operator_kol_inner_ratio_province_pattern_top":[],"operator_kol_inner_ratio_interest_pattern_top":[],"has_pyq_account_daily_update_images":[],"in_shopping_cart":false,"screen_shot_qr_code":null,"weibo_name_cut":"Manager&#x96f6;","video_type_cate":2,"detail_url":"\/single\/video?weibo_id=3171301&weibo_type=110&sign=f20a36615a"}},{"id":494248,"cells":{"audience_realfans_ratio":0,"can_origin":1,"snbt":0,"latest_update_time":1532780462,"reward":0,"max_play_num":1698374,"average_play_num":"8\u4e07","average_comment_num":534,"account_id":494248,"average_like_num":5936,"average_bullet_screen_num":660,"snbt_exponent":0,"last_active_time":1532780462,"max_live_audience_num":"169\u4e07","average_live_audience_num":"8\u4e07","average_posts_num":534,"user_id":179513,"owner_admin_id":696,"weibo_id":"6792899","url":"https:\/\/space.bilibili.com\/6792899#\/","identity_name":"\u7af9\u68d8","weibo_name":"&#x7af9;&#x68d8;","followers_count":"12\u4e07","retweet_price":null,"tweet_price":null,"content_price":null,"original_zhifa_price":null,"soft_tweet_price":null,"soft_retweet_price":null,"orders_monthly":0,"orders_monthly_amount":"0.00","orders_weekly":0,"orders_weekly_amount":"0.00","reservation_order_complete_count_monthly":0,"reservation_order_complete_amount_monthly":0,"weibo_type":110,"verification_info":"","introduction":"","area_id":-1,"location":null,"freedata_picpath":null,"is_vip":2,"is_bluevip":2,"keywords":null,"hand_tags":"","content_tags":"","profit_grade":605,"account_type":null,"is_famous":1,"face_url":"http:\/\/i2.hdslb.com\/bfs\/face\/8310355d95645f2943cc0a72a771a9552c536d18.jpg","is_daren":2,"is_sensitive":2,"gender":2,"is_enable_micro_task":1,"is_extend":1,"active_score":"0.00","audience_female_ratio":"-1.000000","audience_gender":3,"follower_be_identified":2,"is_prepayment":2,"is_original_zhifa":2,"is_sign":2,"sign_note":null,"order_settings":0,"posts_avgretweet_count":"-1.000","posts_avgcomment_count":"-1.000","soft_single_graphic_price":null,"is_reservation_promotion":false,"age":0,"area_name":"","reservation_num":3,"price_maintain_time":"2017-07-19 19:34:02","account_avatar":"http:\/\/i2.hdslb.com\/bfs\/face\/8310355d95645f2943cc0a72a771a9552c536d18.jpg","operation_tag":[],"video_play_num":null,"video_down_num_avg":null,"video_subscribe_num":null,"average_live_play_num":null,"video_up_num_total":null,"avg_collection_count":null,"follower_be_identified_time":"1970\u5e7401\u670801\u65e5","flag":0,"is_verify":2,"is_shield":2,"is_contacted":1,"is_fake":2,"is_open":1,"is_closed":2,"account_introduction":"\u5267\u8bc4UP\u4e3b\u3002\u4e0d\u5b9a\u671f\u66f4\u65b0\u3010\u56f4\u8116\u3011@\u7af9\u68d8sumi\u3010\u6b22\u8fce\u65e5\u996d\u52fe\u642d\u73a9\u800dw\u3011","id":"28285","pack_type":1,"pack_name":"\u7af9\u68d8","pack_info":{"pack_name":"\u7af9\u68d8","pack_type":1,"face_url":"http:\/\/i1.hdslb.com\/bfs\/face\/8310355d95645f2943cc0a72a771a9552c536d18.jpg","sex":2,"pack_id":20868,"related_url_a":"","base_info":{"cooperation_index":null}},"domains":"","professions":"\u7f51\u7edc\u7ea2\u4eba","cooperation_index":"\u9ad8","reference_price_range_default":{"min":0,"max":0},"reference_price_range_multi_top":{"min":0,"max":0},"reference_price_range_multi_second":{"min":0,"max":0},"reference_price_range_multi_other":{"min":0,"max":0},"reference_price_range_single":{"min":0,"max":0},"audience_profile":"","work_nature":"","company_name":"","work_position":"","school_name":"","work_nature_be_identified":"","work_nature_be_identified_time":"","creations":[],"pyq_account_daily_update_images":"","reference_gross_price_original_release":"15000.00","reference_gross_price_video_release":"5000.00","reference_gross_price_guerilla_advertising":"","reference_gross_price_filed_events":"","reference_gross_price_guerilla_advertising_live":"","reference_net_price_original_release":"15000.00","reference_net_price_video_release":"","reference_net_price_guerilla_advertising":"","reference_net_price_filed_events":"","reference_net_price_guerilla_advertising_live":"","account_level":"","retweet_average_like_num":"","retweet_average_posts_num":"","retweet_average_send_num":"","tweet_average_like_num":"","tweet_average_posts_num":"","tweet_average_send_num":"","fav_info":{"account_note":"","group_type":0},"is_select":true,"is_show_select":false,"in_picking_cart":false,"reservation_notice_short":"","external_reference_price":{"price_validity_period":{"start":"2018-08-27","end":"2018-09-30"},"original_release":{"quote":20400},"video_release":{"quote":0},"filed_events":{"quote":0},"guerilla_advertising_live":{"quote":0}},"external_original_zhifa_price":null,"only_support_original":2,"video_original_release_paly_net_price":0,"video_release_paly_net_price":0,"video_guerilla_advertising_paly_net_price":0,"operator_kol_inner_ratio_gender_pattern_top":[],"operator_kol_inner_ratio_age_pattern_top":[],"operator_kol_inner_ratio_province_pattern_top":[],"operator_kol_inner_ratio_interest_pattern_top":[],"has_pyq_account_daily_update_images":[],"in_shopping_cart":false,"screen_shot_qr_code":null,"weibo_name_cut":"&#x7af9;&#x68d8;","video_type_cate":2,"detail_url":"\/single\/video?weibo_id=6792899&weibo_type=110&sign=a2cf8bbbf2"}},{"id":494245,"cells":{"audience_realfans_ratio":-1,"can_origin":1,"snbt":0,"latest_update_time":1532347254,"reward":0,"max_play_num":684180,"average_play_num":"20\u4e07","average_comment_num":887,"account_id":494245,"average_like_num":5540,"average_bullet_screen_num":1657,"snbt_exponent":0,"last_active_time":1532347254,"max_live_audience_num":"68\u4e07","average_live_audience_num":"20\u4e07","average_posts_num":887,"user_id":180588,"owner_admin_id":696,"weibo_id":"137952","url":"https:\/\/space.bilibili.com\/137952#\/","identity_name":"\u4f9d\u7136\u5c0f\u667a\u969c","weibo_name":"&#x4f9d;&#x7136;&#x5c0f;&#x667a;","followers_count":"41\u4e07","retweet_price":null,"tweet_price":null,"content_price":null,"original_zhifa_price":null,"soft_tweet_price":null,"soft_retweet_price":null,"orders_monthly":0,"orders_monthly_amount":"0.00","orders_weekly":0,"orders_weekly_amount":"0.00","reservation_order_complete_count_monthly":0,"reservation_order_complete_amount_monthly":0,"weibo_type":110,"verification_info":"","introduction":"","area_id":1012102,"location":null,"freedata_picpath":null,"is_vip":2,"is_bluevip":2,"keywords":null,"hand_tags":"","content_tags":"","profit_grade":605,"account_type":null,"is_famous":1,"face_url":"http:\/\/i2.hdslb.com\/bfs\/face\/4c0602c552e1d5a1d5690bb2daada9257e87ef96.jpg","is_daren":2,"is_sensitive":2,"gender":3,"is_enable_micro_task":1,"is_extend":1,"active_score":"0.00","audience_female_ratio":"-1.000000","audience_gender":3,"follower_be_identified":2,"is_prepayment":2,"is_original_zhifa":2,"is_sign":2,"sign_note":null,"order_settings":0,"posts_avgretweet_count":"-1.000","posts_avgcomment_count":"-1.000","soft_single_graphic_price":null,"is_reservation_promotion":false,"age":0,"area_name":"\u5c71\u4e1c.\u9752\u5c9b","reservation_num":3,"price_maintain_time":"2018-04-12 15:50:03","account_avatar":"http:\/\/i2.hdslb.com\/bfs\/face\/4c0602c552e1d5a1d5690bb2daada9257e87ef96.jpg","operation_tag":[],"video_play_num":null,"video_down_num_avg":null,"video_subscribe_num":null,"average_live_play_num":null,"video_up_num_total":null,"avg_collection_count":null,"follower_be_identified_time":"1970\u5e7401\u670801\u65e5","flag":0,"is_verify":2,"is_shield":2,"is_contacted":1,"is_fake":2,"is_open":1,"cooperation_type":1,"is_closed":2,"account_introduction":"\u52a8\u753b\u7c7bUP\u4e3b\u3002\u65b0\u6d6a\u5fae\u535aweibo.com\/edwardstraysky","id":"28283","pack_type":1,"pack_name":"\u4f9d\u7136\u5c0f\u667a","pack_info":{"pack_name":"\u4f9d\u7136\u5c0f\u667a","pack_type":1,"face_url":"http:\/\/i0.hdslb.com\/bfs\/face\/4c0602c552e1d5a1d5690bb2daada9257e87ef96.jpg","sex":3,"pack_id":20866,"related_url_a":"","base_info":{"cooperation_index":null}},"domains":"","professions":"\u7f51\u7edc\u7ea2\u4eba","cooperation_index":"\u9ad8","reference_price_range_default":{"min":0,"max":0},"reference_price_range_multi_top":{"min":0,"max":0},"reference_price_range_multi_second":{"min":0,"max":0},"reference_price_range_multi_other":{"min":0,"max":0},"reference_price_range_single":{"min":0,"max":0},"audience_profile":"","work_nature":"","company_name":"","work_position":"","school_name":"","work_nature_be_identified":"","work_nature_be_identified_time":"","creations":[],"pyq_account_daily_update_images":"","reference_gross_price_original_release":"98000.00","reference_gross_price_video_release":"","reference_gross_price_guerilla_advertising":"","reference_gross_price_filed_events":"","reference_gross_price_guerilla_advertising_live":"25000.00","reference_net_price_original_release":"98000.00","reference_net_price_video_release":"","reference_net_price_guerilla_advertising":"","reference_net_price_filed_events":"","reference_net_price_guerilla_advertising_live":"25000.00","account_level":"","retweet_average_like_num":"","retweet_average_posts_num":"","retweet_average_send_num":"","tweet_average_like_num":"","tweet_average_posts_num":"","tweet_average_send_num":"","fav_info":{"account_note":"","group_type":0},"is_select":true,"is_show_select":false,"in_picking_cart":false,"reservation_notice_short":"","external_reference_price":{"price_validity_period":{"start":"2018-08-27","end":"2018-09-30"},"original_release":{"quote":118900},"video_release":{"quote":0},"filed_events":{"quote":0},"guerilla_advertising_live":{"quote":34000}},"external_original_zhifa_price":null,"only_support_original":2,"video_original_release_paly_net_price":0,"video_release_paly_net_price":0,"video_guerilla_advertising_paly_net_price":0,"operator_kol_inner_ratio_gender_pattern_top":[],"operator_kol_inner_ratio_age_pattern_top":[],"operator_kol_inner_ratio_province_pattern_top":[],"operator_kol_inner_ratio_interest_pattern_top":[],"has_pyq_account_daily_update_images":[],"in_shopping_cart":false,"screen_shot_qr_code":null,"weibo_name_cut":"&#x4f9d;&#x7136;&#x5c0f;&#x667a;","video_type_cate":2,"detail_url":"\/single\/video?weibo_id=137952&weibo_type=110&sign=789e83625e"}},{"id":494244,"cells":{"audience_realfans_ratio":0,"can_origin":1,"snbt":0,"latest_update_time":1533662553,"reward":0,"max_play_num":295831,"average_play_num":"1\u4e07","average_comment_num":160,"account_id":494244,"average_like_num":185,"average_bullet_screen_num":797,"snbt_exponent":0,"last_active_time":1533662553,"max_live_audience_num":"29\u4e07","average_live_audience_num":"1\u4e07","average_posts_num":160,"user_id":180588,"owner_admin_id":696,"weibo_id":"2970476","url":"https:\/\/space.bilibili.com\/2970476#\/","identity_name":"\u4f9d\u7136\u5c0f\u667a\u969c","weibo_name":"&#x4f9d;&#x7136;&#x5c0f;&#x667a;&#x969c;","followers_count":"16\u4e07","retweet_price":null,"tweet_price":null,"content_price":null,"original_zhifa_price":null,"soft_tweet_price":null,"soft_retweet_price":null,"orders_monthly":0,"orders_monthly_amount":"0.00","orders_weekly":0,"orders_weekly_amount":"0.00","reservation_order_complete_count_monthly":0,"reservation_order_complete_amount_monthly":0,"weibo_type":110,"verification_info":"","introduction":"","area_id":-1,"location":null,"freedata_picpath":null,"is_vip":2,"is_bluevip":2,"keywords":null,"hand_tags":"","content_tags":"","profit_grade":605,"account_type":null,"is_famous":1,"face_url":"http:\/\/i2.hdslb.com\/bfs\/face\/6b404e9c41647f047e2d47a1d86fc513da36a3d4.jpg","is_daren":2,"is_sensitive":2,"gender":3,"is_enable_micro_task":1,"is_extend":1,"active_score":"0.00","audience_female_ratio":"-1.000000","audience_gender":3,"follower_be_identified":2,"is_prepayment":2,"is_original_zhifa":2,"is_sign":2,"sign_note":null,"order_settings":0,"posts_avgretweet_count":"-1.000","posts_avgcomment_count":"-1.000","soft_single_graphic_price":null,"is_reservation_promotion":false,"age":0,"area_name":"","reservation_num":0,"price_maintain_time":"2017-09-07 17:35:02","account_avatar":"http:\/\/i2.hdslb.com\/bfs\/face\/6b404e9c41647f047e2d47a1d86fc513da36a3d4.jpg","operation_tag":[],"video_play_num":null,"video_down_num_avg":null,"video_subscribe_num":null,"average_live_play_num":null,"video_up_num_total":null,"avg_collection_count":null,"follower_be_identified_time":"1970\u5e7401\u670801\u65e5","flag":0,"is_verify":2,"is_shield":2,"is_contacted":1,"is_fake":2,"is_open":1,"is_closed":2,"account_introduction":"\u6e38\u620f\u89e3\u8bf4up\u4e3b\u3002\u4f9d\u7136\u5c0f\u667a\u7684\u5c0f\u53f7\uff0cID\u662f\u6d6e\u4e91\uff01\uff01\u65b0\u6d6a\u5fae\u535a\uff1ahttp:\/\/weibo.com\/edwardstraysky","id":"28282","pack_type":1,"pack_name":"\u4f9d\u7136\u5c0f\u667a\u969c","pack_info":{"pack_name":"\u4f9d\u7136\u5c0f\u667a\u969c","pack_type":1,"face_url":"http:\/\/i2.hdslb.com\/bfs\/face\/6b404e9c41647f047e2d47a1d86fc513da36a3d4.jpg","sex":3,"pack_id":20865,"related_url_a":"","base_info":{"cooperation_index":null}},"domains":"","professions":"\u7f51\u7edc\u7ea2\u4eba","cooperation_index":"\u9ad8","reference_price_range_default":{"min":0,"max":0},"reference_price_range_multi_top":{"min":0,"max":0},"reference_price_range_multi_second":{"min":0,"max":0},"reference_price_range_multi_other":{"min":0,"max":0},"reference_price_range_single":{"min":0,"max":0},"audience_profile":"","work_nature":"","company_name":"","work_position":"","school_name":"","work_nature_be_identified":"","work_nature_be_identified_time":"","creations":[],"pyq_account_daily_update_images":"","reference_gross_price_original_release":"80000.00","reference_gross_price_video_release":"","reference_gross_price_guerilla_advertising":"","reference_gross_price_filed_events":"","reference_gross_price_guerilla_advertising_live":"","reference_net_price_original_release":"80000.00","reference_net_price_video_release":"","reference_net_price_guerilla_advertising":"","reference_net_price_filed_events":"","reference_net_price_guerilla_advertising_live":"","account_level":"","retweet_average_like_num":"","retweet_average_posts_num":"","retweet_average_send_num":"","tweet_average_like_num":"","tweet_average_posts_num":"","tweet_average_send_num":"","fav_info":{"account_note":"","group_type":0},"is_select":true,"is_show_select":false,"in_picking_cart":false,"reservation_notice_short":"","external_reference_price":{"price_validity_period":{"start":"2018-08-27","end":"2018-09-30"},"original_release":{"quote":102600},"video_release":{"quote":0},"filed_events":{"quote":0},"guerilla_advertising_live":{"quote":0}},"external_original_zhifa_price":null,"only_support_original":2,"video_original_release_paly_net_price":0,"video_release_paly_net_price":0,"video_guerilla_advertising_paly_net_price":0,"operator_kol_inner_ratio_gender_pattern_top":[],"operator_kol_inner_ratio_age_pattern_top":[],"operator_kol_inner_ratio_province_pattern_top":[],"operator_kol_inner_ratio_interest_pattern_top":[],"has_pyq_account_daily_update_images":[],"in_shopping_cart":false,"screen_shot_qr_code":null,"weibo_name_cut":"&#x4f9d;&#x7136;&#x5c0f;&#x667a;&#x969c;","video_type_cate":2,"detail_url":"\/single\/video?weibo_id=2970476&weibo_type=110&sign=ec597c8448"}},{"id":494243,"cells":{"audience_realfans_ratio":0,"can_origin":1,"snbt":0,"latest_update_time":1533645058,"reward":0,"max_play_num":301456,"average_play_num":"1\u4e07","average_comment_num":211,"account_id":494243,"average_like_num":400,"average_bullet_screen_num":239,"snbt_exponent":0,"last_active_time":1533645058,"max_live_audience_num":"30\u4e07","average_live_audience_num":"1\u4e07","average_posts_num":211,"user_id":232735,"owner_admin_id":696,"weibo_id":"307108","url":"https:\/\/space.bilibili.com\/307108#\/","identity_name":"\u52fe\u753b\u7f51\u7edcMCN","weibo_name":"E&#x9505;&#x9505;","followers_count":"19\u4e07","retweet_price":null,"tweet_price":null,"content_price":null,"original_zhifa_price":null,"soft_tweet_price":null,"soft_retweet_price":null,"orders_monthly":0,"orders_monthly_amount":"0.00","orders_weekly":0,"orders_weekly_amount":"0.00","reservation_order_complete_count_monthly":0,"reservation_order_complete_amount_monthly":0,"weibo_type":110,"verification_info":"","introduction":"","area_id":-1,"location":null,"freedata_picpath":null,"is_vip":2,"is_bluevip":2,"keywords":null,"hand_tags":"","content_tags":"","profit_grade":668,"account_type":null,"is_famous":1,"face_url":"http:\/\/i1.hdslb.com\/bfs\/face\/4523cf93f2e69896049ac9f69143ef4652ca0ed0.jpg","is_daren":2,"is_sensitive":2,"gender":3,"is_enable_micro_task":1,"is_extend":1,"active_score":"0.00","audience_female_ratio":"-1.000000","audience_gender":3,"follower_be_identified":2,"is_prepayment":1,"is_original_zhifa":2,"is_sign":2,"sign_note":null,"order_settings":0,"posts_avgretweet_count":"-1.000","posts_avgcomment_count":"-1.000","soft_single_graphic_price":null,"is_reservation_promotion":false,"age":0,"area_name":"","reservation_num":6,"price_maintain_time":"2018-07-06 18:34:08","account_avatar":"http:\/\/i1.hdslb.com\/bfs\/face\/4523cf93f2e69896049ac9f69143ef4652ca0ed0.jpg","operation_tag":[],"video_play_num":null,"video_down_num_avg":null,"video_subscribe_num":null,"average_live_play_num":null,"video_up_num_total":null,"avg_collection_count":null,"media_professional_degree_avg":null,"media_coordination_degree_avg":null,"media_appearance_degree_avg":null,"media_post_sale_review_count":null,"sale_professional_degree_avg":"5.00","sale_coordination_degree_avg":"5.00","sale_appearance_degree_avg":"5.00","sale_post_sale_review_count":1,"follower_be_identified_time":"1970\u5e7401\u670801\u65e5","flag":0,"is_verify":2,"is_shield":2,"is_contacted":1,"is_fake":2,"is_open":1,"is_closed":2,"account_introduction":"\u65f6\u5c1a\u7f8e\u5986UP\u4e3b\u3001\u8bf7\u52a1\u5fc5\u5173\u6ce8UP\u4e3b\u7684\u5fae\u535a\uff0cweibo:EMOI_E\u9505\u9505 ","id":"28281","pack_type":1,"pack_name":"E\u9505\u9505","pack_info":{"pack_name":"E\u9505\u9505","pack_type":1,"face_url":"http:\/\/i0.hdslb.com\/bfs\/face\/e46e181185fed9a1fba155143182753aa8e05c19.gif","sex":3,"pack_id":20864,"related_url_a":"","base_info":{"cooperation_index":null}},"domains":"","professions":"\u7f51\u7edc\u7ea2\u4eba","cooperation_index":"\u9ad8","reference_price_range_default":{"min":0,"max":0},"reference_price_range_multi_top":{"min":0,"max":0},"reference_price_range_multi_second":{"min":0,"max":0},"reference_price_range_multi_other":{"min":0,"max":0},"reference_price_range_single":{"min":0,"max":0},"audience_profile":"","work_nature":"","company_name":"","work_position":"","school_name":"","work_nature_be_identified":"","work_nature_be_identified_time":"","creations":[],"pyq_account_daily_update_images":"","reference_gross_price_original_release":"10000.00","reference_gross_price_video_release":"","reference_gross_price_guerilla_advertising":"","reference_gross_price_filed_events":"","reference_gross_price_guerilla_advertising_live":"","reference_net_price_original_release":"10000.00","reference_net_price_video_release":"","reference_net_price_guerilla_advertising":"","reference_net_price_filed_events":"","reference_net_price_guerilla_advertising_live":"","account_level":"","retweet_average_like_num":"","retweet_average_posts_num":"","retweet_average_send_num":"","tweet_average_like_num":"","tweet_average_posts_num":"","tweet_average_send_num":"","fav_info":{"account_note":"","group_type":0},"is_select":true,"is_show_select":false,"in_picking_cart":false,"reservation_notice_short":"","external_reference_price":{"price_validity_period":{"start":"2018-09-01","end":"2018-09-30"},"original_release":{"quote":12800},"video_release":{"quote":0},"filed_events":{"quote":0},"guerilla_advertising_live":{"quote":0}},"external_original_zhifa_price":null,"only_support_original":2,"video_original_release_paly_net_price":0,"video_release_paly_net_price":0,"video_guerilla_advertising_paly_net_price":0,"operator_kol_inner_ratio_gender_pattern_top":[],"operator_kol_inner_ratio_age_pattern_top":[],"operator_kol_inner_ratio_province_pattern_top":[],"operator_kol_inner_ratio_interest_pattern_top":[],"has_pyq_account_daily_update_images":[],"in_shopping_cart":false,"screen_shot_qr_code":null,"weibo_name_cut":"E&#x9505;&#x9505;","video_type_cate":2,"detail_url":"\/single\/video?weibo_id=307108&weibo_type=110&sign=061fb6f54b"}},{"id":494242,"cells":{"audience_realfans_ratio":0,"can_origin":1,"snbt":0,"latest_update_time":1532696026,"reward":0,"max_play_num":325826,"average_play_num":2699,"average_comment_num":68,"account_id":494242,"average_like_num":28,"average_bullet_screen_num":81,"snbt_exponent":0,"last_active_time":1532696026,"max_live_audience_num":"32\u4e07","average_live_audience_num":2699,"average_posts_num":68,"user_id":180586,"owner_admin_id":696,"weibo_id":"18842010","url":"https:\/\/space.bilibili.com\/18842010#\/","identity_name":"\u9a6c\u4e01\u7684\u65e9\u6668\u4e0d\u8d77\u5e8a","weibo_name":"&#x9a6c;&#x4e01;&#x7684;&#x65e9;&#x6668;&#x4e0d;&#x8d77;&#x5e8a;","followers_count":"5\u4e07","retweet_price":null,"tweet_price":null,"content_price":null,"original_zhifa_price":null,"soft_tweet_price":null,"soft_retweet_price":null,"orders_monthly":0,"orders_monthly_amount":"0.00","orders_weekly":0,"orders_weekly_amount":"0.00","reservation_order_complete_count_monthly":0,"reservation_order_complete_amount_monthly":0,"weibo_type":110,"verification_info":"","introduction":"","area_id":1010217,"location":null,"freedata_picpath":null,"is_vip":2,"is_bluevip":2,"keywords":null,"hand_tags":"","content_tags":"","profit_grade":605,"account_type":null,"is_famous":1,"face_url":"http:\/\/i0.hdslb.com\/bfs\/face\/f3c6a5f48851fbcaaa56a1bea9d30d65b02fccc8.jpg","is_daren":2,"is_sensitive":2,"gender":1,"is_enable_micro_task":1,"is_extend":1,"active_score":"0.00","audience_female_ratio":"-1.000000","audience_gender":3,"follower_be_identified":2,"is_prepayment":2,"is_original_zhifa":2,"is_sign":2,"sign_note":null,"order_settings":0,"posts_avgretweet_count":"-1.000","posts_avgcomment_count":"-1.000","soft_single_graphic_price":null,"is_reservation_promotion":false,"age":0,"area_name":"\u5b89\u5fbd.\u5408\u80a5","reservation_num":1,"price_maintain_time":"2017-07-19 19:33:59","account_avatar":"http:\/\/i0.hdslb.com\/bfs\/face\/f3c6a5f48851fbcaaa56a1bea9d30d65b02fccc8.jpg","operation_tag":[],"video_play_num":null,"video_down_num_avg":null,"video_subscribe_num":null,"average_live_play_num":null,"video_up_num_total":null,"avg_collection_count":null,"follower_be_identified_time":"1970\u5e7401\u670801\u65e5","flag":0,"is_verify":2,"is_shield":2,"is_contacted":1,"is_fake":2,"is_open":1,"is_closed":2,"account_introduction":"\u65f6\u5c1a\u7f8e\u5986\u7537UP\u4e3b\u3002\u5f88\u61d2\u5f88\u61d2\u7684\u7f8e\u5986up \u5fae\u535a\uff1a\u516b\u8db3\u9a6c\u4e01","id":"28280","pack_type":1,"pack_name":"\u9a6c\u4e01\u7684\u65e9\u6668\u4e0d\u8d77\u5e8a","pack_info":{"pack_name":"\u9a6c\u4e01\u7684\u65e9\u6668\u4e0d\u8d77\u5e8a","pack_type":1,"face_url":"http:\/\/i2.hdslb.com\/bfs\/face\/f3c6a5f48851fbcaaa56a1bea9d30d65b02fccc8.jpg","sex":1,"pack_id":20863,"related_url_a":"","base_info":{"cooperation_index":null}},"domains":"","professions":"\u7f51\u7edc\u7ea2\u4eba","cooperation_index":"\u9ad8","reference_price_range_default":{"min":0,"max":0},"reference_price_range_multi_top":{"min":0,"max":0},"reference_price_range_multi_second":{"min":0,"max":0},"reference_price_range_multi_other":{"min":0,"max":0},"reference_price_range_single":{"min":0,"max":0},"audience_profile":"","work_nature":"","company_name":"","work_position":"","school_name":"","work_nature_be_identified":"","work_nature_be_identified_time":"","creations":[],"pyq_account_daily_update_images":"","reference_gross_price_original_release":"12000.00","reference_gross_price_video_release":"","reference_gross_price_guerilla_advertising":"","reference_gross_price_filed_events":"","reference_gross_price_guerilla_advertising_live":"","reference_net_price_original_release":"12000.00","reference_net_price_video_release":"","reference_net_price_guerilla_advertising":"","reference_net_price_filed_events":"","reference_net_price_guerilla_advertising_live":"","account_level":"","retweet_average_like_num":"","retweet_average_posts_num":"","retweet_average_send_num":"","tweet_average_like_num":"","tweet_average_posts_num":"","tweet_average_send_num":"","fav_info":{"account_note":"","group_type":0},"is_select":true,"is_show_select":false,"in_picking_cart":false,"reservation_notice_short":"","external_reference_price":{"price_validity_period":{"start":"2018-05-01","end":"2018-05-31"},"original_release":{"quote":16400},"video_release":{"quote":0},"filed_events":{"quote":0},"guerilla_advertising_live":{"quote":0}},"external_original_zhifa_price":null,"only_support_original":2,"video_original_release_paly_net_price":6.076,"video_release_paly_net_price":0,"video_guerilla_advertising_paly_net_price":0,"operator_kol_inner_ratio_gender_pattern_top":[],"operator_kol_inner_ratio_age_pattern_top":[],"operator_kol_inner_ratio_province_pattern_top":[],"operator_kol_inner_ratio_interest_pattern_top":[],"has_pyq_account_daily_update_images":[],"in_shopping_cart":false,"screen_shot_qr_code":null,"weibo_name_cut":"&#x9a6c;&#x4e01;&#x7684;&#x65e9;&#x6668;&#x4e0d;&#x8d77;&#x5e8a;","video_type_cate":2,"detail_url":"\/single\/video?weibo_id=18842010&weibo_type=110&sign=b72308d185"}},{"id":494241,"cells":{"audience_realfans_ratio":-1,"can_origin":1,"snbt":0,"latest_update_time":1532766154,"reward":0,"max_play_num":920861,"average_play_num":"31\u4e07","average_comment_num":1663,"account_id":494241,"average_like_num":3090,"average_bullet_screen_num":4439,"snbt_exponent":0,"last_active_time":1532766154,"max_live_audience_num":"92\u4e07","average_live_audience_num":"31\u4e07","average_posts_num":1663,"user_id":180585,"owner_admin_id":696,"weibo_id":"1885078","url":"https:\/\/space.bilibili.com\/1885078#\/","identity_name":"nya\u9171\u7684\u4e00\u751f","weibo_name":"nya&#x9171;&#x7684;&#x4e00;&#x751f;","followers_count":"89\u4e07","retweet_price":null,"tweet_price":null,"content_price":null,"original_zhifa_price":null,"soft_tweet_price":null,"soft_retweet_price":null,"orders_monthly":0,"orders_monthly_amount":"0.00","orders_weekly":0,"orders_weekly_amount":"0.00","reservation_order_complete_count_monthly":0,"reservation_order_complete_amount_monthly":0,"weibo_type":110,"verification_info":"","introduction":"","area_id":-1,"location":null,"freedata_picpath":null,"is_vip":2,"is_bluevip":2,"keywords":null,"hand_tags":"","content_tags":"","profit_grade":605,"account_type":null,"is_famous":1,"face_url":"http:\/\/i2.hdslb.com\/bfs\/face\/0c96e4cc4f86dd7e2a6c02aeba4c793ffc05068b.jpg","is_daren":2,"is_sensitive":2,"gender":3,"is_enable_micro_task":1,"is_extend":1,"active_score":"0.00","audience_female_ratio":"-1.000000","audience_gender":3,"follower_be_identified":2,"is_prepayment":2,"is_original_zhifa":2,"is_sign":2,"sign_note":null,"order_settings":0,"posts_avgretweet_count":"-1.000","posts_avgcomment_count":"-1.000","soft_single_graphic_price":null,"is_reservation_promotion":false,"age":0,"area_name":"","reservation_num":2,"price_maintain_time":"2018-07-27 16:20:06","account_avatar":"http:\/\/i2.hdslb.com\/bfs\/face\/0c96e4cc4f86dd7e2a6c02aeba4c793ffc05068b.jpg","operation_tag":[],"video_play_num":null,"video_down_num_avg":null,"video_subscribe_num":null,"average_live_play_num":null,"video_up_num_total":null,"avg_collection_count":null,"media_professional_degree_avg":null,"media_coordination_degree_avg":null,"media_appearance_degree_avg":null,"media_post_sale_review_count":null,"sale_professional_degree_avg":"5.00","sale_coordination_degree_avg":"5.00","sale_appearance_degree_avg":"5.00","sale_post_sale_review_count":2,"follower_be_identified_time":"1970\u5e7401\u670801\u65e5","flag":0,"is_verify":2,"is_shield":2,"is_contacted":1,"is_fake":2,"is_open":1,"is_closed":2,"account_introduction":"\u65f6\u5c1aUP\u4e3b\u3002\u968f\u7f18\u4ed9\u5973 \u5fae\u535a\uff1a\u888b\u9f20\u56fd\u7684\u55b5\u9171 ","id":"28279","pack_type":1,"pack_name":"nya\u9171\u7684\u4e00\u751f","pack_info":{"pack_name":"nya\u9171\u7684\u4e00\u751f","pack_type":1,"face_url":"http:\/\/i2.hdslb.com\/bfs\/face\/9c6191d0e686749c756dd0d561dca9fa59e7d41c.gif","sex":3,"pack_id":20862,"related_url_a":"","base_info":{"cooperation_index":null}},"domains":"","professions":"\u7f51\u7edc\u7ea2\u4eba","cooperation_index":"\u9ad8","reference_price_range_default":{"min":0,"max":0},"reference_price_range_multi_top":{"min":0,"max":0},"reference_price_range_multi_second":{"min":0,"max":0},"reference_price_range_multi_other":{"min":0,"max":0},"reference_price_range_single":{"min":0,"max":0},"audience_profile":"","work_nature":"","company_name":"","work_position":"","school_name":"","work_nature_be_identified":"","work_nature_be_identified_time":"","creations":[],"pyq_account_daily_update_images":"","reference_gross_price_original_release":"100000.00","reference_gross_price_video_release":"","reference_gross_price_guerilla_advertising":"","reference_gross_price_filed_events":"","reference_gross_price_guerilla_advertising_live":"","reference_net_price_original_release":"100000.00","reference_net_price_video_release":"","reference_net_price_guerilla_advertising":"","reference_net_price_filed_events":"","reference_net_price_guerilla_advertising_live":"","account_level":"","retweet_average_like_num":"","retweet_average_posts_num":"","retweet_average_send_num":"","tweet_average_like_num":"","tweet_average_posts_num":"","tweet_average_send_num":"","fav_info":{"account_note":"","group_type":0},"is_select":true,"is_show_select":false,"in_picking_cart":false,"reservation_notice_short":"","external_reference_price":{"price_validity_period":{"start":"2018-09-26","end":"2018-10-31"},"original_release":{"quote":121300},"video_release":{"quote":0},"filed_events":{"quote":0},"guerilla_advertising_live":{"quote":0}},"external_original_zhifa_price":null,"only_support_original":2,"video_original_release_paly_net_price":0,"video_release_paly_net_price":0,"video_guerilla_advertising_paly_net_price":0,"operator_kol_inner_ratio_gender_pattern_top":[],"operator_kol_inner_ratio_age_pattern_top":[],"operator_kol_inner_ratio_province_pattern_top":[],"operator_kol_inner_ratio_interest_pattern_top":[],"has_pyq_account_daily_update_images":[],"in_shopping_cart":false,"screen_shot_qr_code":null,"weibo_name_cut":"nya&#x9171;&#x7684;&#x4e00;&#x751f;","video_type_cate":2,"detail_url":"\/single\/video?weibo_id=1885078&weibo_type=110&sign=f1812ea2e2"}},{"id":494238,"cells":{"audience_realfans_ratio":0,"can_origin":1,"snbt":0,"latest_update_time":1533374708,"reward":0,"max_play_num":82246,"average_play_num":"1\u4e07","average_comment_num":91,"account_id":494238,"average_like_num":388,"average_bullet_screen_num":189,"snbt_exponent":0,"last_active_time":1533374708,"max_live_audience_num":"8\u4e07","average_live_audience_num":"1\u4e07","average_posts_num":91,"user_id":180583,"owner_admin_id":949,"weibo_id":"1648768","url":"https:\/\/space.bilibili.com\/1648768#\/","identity_name":"JoyceLemon721","weibo_name":"JoyceLemon721","followers_count":"13\u4e07","retweet_price":null,"tweet_price":null,"content_price":null,"original_zhifa_price":null,"soft_tweet_price":null,"soft_retweet_price":null,"orders_monthly":0,"orders_monthly_amount":"0.00","orders_weekly":0,"orders_weekly_amount":"0.00","reservation_order_complete_count_monthly":0,"reservation_order_complete_amount_monthly":0,"weibo_type":110,"verification_info":"","introduction":"","area_id":-1,"location":null,"freedata_picpath":null,"is_vip":2,"is_bluevip":2,"keywords":null,"hand_tags":"","content_tags":"","profit_grade":412,"account_type":null,"is_famous":1,"face_url":"http:\/\/i1.hdslb.com\/bfs\/face\/4499e7b45e9b79f657b5148ec18346fa6bb59dbf.jpg","is_daren":2,"is_sensitive":2,"gender":2,"is_enable_micro_task":1,"is_extend":1,"active_score":"0.00","audience_female_ratio":"-1.000000","audience_gender":3,"follower_be_identified":2,"is_prepayment":2,"is_original_zhifa":2,"is_sign":2,"sign_note":null,"order_settings":0,"posts_avgretweet_count":"-1.000","posts_avgcomment_count":"-1.000","soft_single_graphic_price":null,"is_reservation_promotion":false,"age":0,"area_name":"","reservation_num":2,"price_maintain_time":"2018-07-23 20:10:08","account_avatar":"http:\/\/i1.hdslb.com\/bfs\/face\/4499e7b45e9b79f657b5148ec18346fa6bb59dbf.jpg","video_play_num":null,"video_down_num_avg":null,"video_subscribe_num":null,"average_live_play_num":null,"video_up_num_total":null,"avg_collection_count":null,"follower_be_identified_time":"1970\u5e7401\u670801\u65e5","flag":0,"is_verify":2,"is_shield":2,"is_contacted":1,"is_fake":2,"is_open":1,"is_closed":2,"account_introduction":"\u65f6\u5c1a\u7f8e\u5986\u8fbe\u4eba","id":"180908","pack_type":1,"pack_name":"JoyceLemon721","pack_info":{"pack_name":"JoyceLemon721","pack_type":1,"face_url":"http:\/\/i1.hdslb.com\/bfs\/face\/4499e7b45e9b79f657b5148ec18346fa6bb59dbf.jpg","sex":2,"pack_id":174367,"related_url_a":"","base_info":{"cooperation_index":null}},"domains":"","professions":"\u7f51\u7edc\u7ea2\u4eba","cooperation_index":"\u9ad8","reference_price_range_default":{"min":0,"max":0},"reference_price_range_multi_top":{"min":0,"max":0},"reference_price_range_multi_second":{"min":0,"max":0},"reference_price_range_multi_other":{"min":0,"max":0},"reference_price_range_single":{"min":0,"max":0},"audience_profile":"","work_nature":"","company_name":"","work_position":"","school_name":"","work_nature_be_identified":"","work_nature_be_identified_time":"","creations":[],"pyq_account_daily_update_images":"","reference_gross_price_original_release":"10000.00","reference_gross_price_video_release":"","reference_gross_price_guerilla_advertising":"","reference_gross_price_filed_events":"","reference_gross_price_guerilla_advertising_live":"","reference_net_price_original_release":"10000.00","reference_net_price_video_release":"","reference_net_price_guerilla_advertising":"","reference_net_price_filed_events":"","reference_net_price_guerilla_advertising_live":"","account_level":"","retweet_average_like_num":"","retweet_average_posts_num":"","retweet_average_send_num":"","tweet_average_like_num":"","tweet_average_posts_num":"","tweet_average_send_num":"","operation_tag":[],"fav_info":{"account_note":"","group_type":0},"is_select":true,"is_show_select":false,"in_picking_cart":false,"reservation_notice_short":"","external_reference_price":{"price_validity_period":{"start":"2018-07-23","end":"2018-08-21"},"original_release":{"quote":13600},"video_release":{"quote":0},"filed_events":{"quote":0},"guerilla_advertising_live":{"quote":0}},"external_original_zhifa_price":null,"only_support_original":2,"video_original_release_paly_net_price":0,"video_release_paly_net_price":0,"video_guerilla_advertising_paly_net_price":0,"operator_kol_inner_ratio_gender_pattern_top":[],"operator_kol_inner_ratio_age_pattern_top":[],"operator_kol_inner_ratio_province_pattern_top":[],"operator_kol_inner_ratio_interest_pattern_top":[],"has_pyq_account_daily_update_images":[],"in_shopping_cart":false,"screen_shot_qr_code":null,"weibo_name_cut":"JoyceLemon721","video_type_cate":2,"detail_url":"\/single\/video?weibo_id=1648768&weibo_type=110&sign=45735e15e3"}},{"id":494237,"cells":{"audience_realfans_ratio":-1,"can_origin":1,"snbt":0,"latest_update_time":1533709846,"reward":0,"max_play_num":919290,"average_play_num":"1\u4e07","average_comment_num":57,"account_id":494237,"average_like_num":167,"average_bullet_screen_num":73,"snbt_exponent":0,"last_active_time":1533709846,"max_live_audience_num":"91\u4e07","average_live_audience_num":"1\u4e07","average_posts_num":57,"user_id":226514,"owner_admin_id":696,"weibo_id":"429251","url":"https:\/\/space.bilibili.com\/429251#\/","identity_name":"1MILLION_OFFICIAL","weibo_name":"&#x5927;&#x5b9d;&#x5251;&#x8054;&#x76df;","followers_count":"75\u4e07","retweet_price":null,"tweet_price":null,"content_price":null,"original_zhifa_price":null,"soft_tweet_price":null,"soft_retweet_price":null,"orders_monthly":0,"orders_monthly_amount":"0.00","orders_weekly":0,"orders_weekly_amount":"0.00","reservation_order_complete_count_monthly":0,"reservation_order_complete_amount_monthly":0,"weibo_type":110,"verification_info":"","introduction":"","area_id":1012401,"location":null,"freedata_picpath":null,"is_vip":2,"is_bluevip":2,"keywords":null,"hand_tags":"","content_tags":"","profit_grade":605,"account_type":null,"is_famous":1,"face_url":"http:\/\/i0.hdslb.com\/bfs\/face\/98968f1ad04d2500983aba9abdc309d4d9b88892.jpg","is_daren":2,"is_sensitive":2,"gender":2,"is_enable_micro_task":1,"is_extend":1,"active_score":"0.00","audience_female_ratio":"-1.000000","audience_gender":3,"follower_be_identified":2,"is_prepayment":2,"is_original_zhifa":2,"is_sign":2,"sign_note":null,"order_settings":0,"posts_avgretweet_count":"-1.000","posts_avgcomment_count":"-1.000","soft_single_graphic_price":null,"is_reservation_promotion":false,"age":0,"area_name":"\u4e0a\u6d77","reservation_num":0,"price_maintain_time":"2018-07-27 14:40:06","account_avatar":"http:\/\/i0.hdslb.com\/bfs\/face\/98968f1ad04d2500983aba9abdc309d4d9b88892.jpg","operation_tag":[],"video_play_num":null,"video_down_num_avg":null,"video_subscribe_num":null,"average_live_play_num":null,"video_up_num_total":null,"avg_collection_count":null,"media_professional_degree_avg":null,"media_coordination_degree_avg":null,"media_appearance_degree_avg":null,"media_post_sale_review_count":null,"sale_professional_degree_avg":null,"sale_coordination_degree_avg":null,"sale_appearance_degree_avg":null,"sale_post_sale_review_count":null,"follower_be_identified_time":"1970\u5e7401\u670801\u65e5","flag":0,"is_verify":2,"is_shield":2,"is_contacted":1,"is_fake":2,"is_open":1,"cooperation_type":1,"is_closed":2,"account_introduction":"\u751f\u6d3b\u7c7bUP\u4e3b","id":"28277","pack_type":1,"pack_name":"\u5927\u5b9d\u5251\u8054\u76df","pack_info":{"pack_name":"\u5927\u5b9d\u5251\u8054\u76df","pack_type":1,"face_url":"http:\/\/i1.hdslb.com\/bfs\/face\/14589d3c438d2e90d4a10b984417ec76ee2c1d9e.jpg","sex":3,"pack_id":20860,"related_url_a":"","base_info":{"cooperation_index":null}},"domains":"","professions":"\u7f51\u7edc\u7ea2\u4eba","cooperation_index":"\u9ad8","reference_price_range_default":{"min":0,"max":0},"reference_price_range_multi_top":{"min":0,"max":0},"reference_price_range_multi_second":{"min":0,"max":0},"reference_price_range_multi_other":{"min":0,"max":0},"reference_price_range_single":{"min":0,"max":0},"audience_profile":"","work_nature":"","company_name":"","work_position":"","school_name":"","work_nature_be_identified":"","work_nature_be_identified_time":"","creations":[],"pyq_account_daily_update_images":"","reference_gross_price_original_release":"120000.00","reference_gross_price_video_release":"20000.00","reference_gross_price_guerilla_advertising":"","reference_gross_price_filed_events":"","reference_gross_price_guerilla_advertising_live":"","reference_net_price_original_release":"120000.00","reference_net_price_video_release":"","reference_net_price_guerilla_advertising":"","reference_net_price_filed_events":"","reference_net_price_guerilla_advertising_live":"","account_level":"","retweet_average_like_num":"","retweet_average_posts_num":"","retweet_average_send_num":"","tweet_average_like_num":"","tweet_average_posts_num":"","tweet_average_send_num":"","fav_info":{"account_note":"","group_type":0},"is_select":true,"is_show_select":false,"in_picking_cart":false,"reservation_notice_short":"","external_reference_price":{"price_validity_period":{"start":"2018-07-27","end":"2018-08-31"},"original_release":{"quote":136800},"video_release":{"quote":0},"filed_events":{"quote":0},"guerilla_advertising_live":{"quote":0}},"external_original_zhifa_price":null,"only_support_original":2,"video_original_release_paly_net_price":0,"video_release_paly_net_price":0,"video_guerilla_advertising_paly_net_price":0,"operator_kol_inner_ratio_gender_pattern_top":[],"operator_kol_inner_ratio_age_pattern_top":[],"operator_kol_inner_ratio_province_pattern_top":[],"operator_kol_inner_ratio_interest_pattern_top":[],"has_pyq_account_daily_update_images":[],"in_shopping_cart":false,"screen_shot_qr_code":null,"weibo_name_cut":"&#x5927;&#x5b9d;&#x5251;&#x8054;&#x76df;","video_type_cate":2,"detail_url":"\/single\/video?weibo_id=429251&weibo_type=110&sign=596efebb8a"}},{"id":494236,"cells":{"audience_realfans_ratio":0,"can_origin":1,"snbt":0,"latest_update_time":1533647933,"reward":0,"max_play_num":153198,"average_play_num":"3\u4e07","average_comment_num":169,"account_id":494236,"average_like_num":566,"average_bullet_screen_num":228,"snbt_exponent":0,"last_active_time":1533647933,"max_live_audience_num":"15\u4e07","average_live_audience_num":"3\u4e07","average_posts_num":169,"user_id":180580,"owner_admin_id":696,"weibo_id":"2981561","url":"https:\/\/space.bilibili.com\/2981561#\/","identity_name":"\u9752\u4e91\u7ea2\u8845","weibo_name":"&#x9752;&#x4e91;&#x7ea2;&#x8845;","followers_count":"10\u4e07","retweet_price":null,"tweet_price":null,"content_price":null,"original_zhifa_price":null,"soft_tweet_price":null,"soft_retweet_price":null,"orders_monthly":0,"orders_monthly_amount":"0.00","orders_weekly":0,"orders_weekly_amount":"0.00","reservation_order_complete_count_monthly":0,"reservation_order_complete_amount_monthly":0,"weibo_type":110,"verification_info":"","introduction":"","area_id":0,"location":null,"freedata_picpath":null,"is_vip":2,"is_bluevip":2,"keywords":null,"hand_tags":"","content_tags":"","profit_grade":668,"account_type":null,"is_famous":1,"face_url":"http:\/\/i0.hdslb.com\/bfs\/face\/f6e797eab8c4d770e8af51119c770a6fec94bf13.jpg","is_daren":2,"is_sensitive":2,"gender":2,"is_enable_micro_task":1,"is_extend":1,"active_score":"0.00","audience_female_ratio":"-1.000000","audience_gender":3,"follower_be_identified":2,"is_prepayment":2,"is_original_zhifa":2,"is_sign":2,"sign_note":null,"order_settings":0,"posts_avgretweet_count":"-1.000","posts_avgcomment_count":"-1.000","soft_single_graphic_price":null,"is_reservation_promotion":false,"age":22,"area_name":"","reservation_num":1,"price_maintain_time":"2017-07-19 19:33:20","account_avatar":"http:\/\/i0.hdslb.com\/bfs\/face\/f6e797eab8c4d770e8af51119c770a6fec94bf13.jpg","operation_tag":[],"video_play_num":null,"video_down_num_avg":null,"video_subscribe_num":null,"average_live_play_num":null,"video_up_num_total":null,"avg_collection_count":null,"follower_be_identified_time":"1970\u5e7401\u670801\u65e5","flag":0,"is_verify":2,"is_shield":2,"is_contacted":1,"is_fake":2,"is_open":1,"is_closed":2,"account_introduction":"\u65f6\u5c1a\u7f8e\u5986UP\u4e3b\u3002\u5fae\u535a@\u9752\u4e91\u7ea2\u8845 \u72ec\u7acb\u5986\u5a18 coser \u8fc7\u6c14B\u7ad9\u72ec\u5bb6up","id":"28276","pack_type":1,"pack_name":"\u9752\u4e91\u7ea2\u8845","pack_info":{"pack_name":"\u9752\u4e91\u7ea2\u8845","pack_type":1,"face_url":"http:\/\/i2.hdslb.com\/bfs\/face\/8d65bae713bc5df73e9ef740f35bd0c9a314ef1a.jpg","sex":3,"pack_id":20859,"related_url_a":"","base_info":{"cooperation_index":null}},"domains":"","professions":"\u7f51\u7edc\u7ea2\u4eba","cooperation_index":"\u9ad8","reference_price_range_default":{"min":0,"max":0},"reference_price_range_multi_top":{"min":0,"max":0},"reference_price_range_multi_second":{"min":0,"max":0},"reference_price_range_multi_other":{"min":0,"max":0},"reference_price_range_single":{"min":0,"max":0},"audience_profile":"","work_nature":"","company_name":"","work_position":"","school_name":"","work_nature_be_identified":"","work_nature_be_identified_time":"","creations":[],"pyq_account_daily_update_images":"","reference_gross_price_original_release":"20000.00","reference_gross_price_video_release":"","reference_gross_price_guerilla_advertising":"","reference_gross_price_filed_events":"","reference_gross_price_guerilla_advertising_live":"","reference_net_price_original_release":"20000.00","reference_net_price_video_release":"","reference_net_price_guerilla_advertising":"","reference_net_price_filed_events":"","reference_net_price_guerilla_advertising_live":"","account_level":"","retweet_average_like_num":"","retweet_average_posts_num":"","retweet_average_send_num":"","tweet_average_like_num":"","tweet_average_posts_num":"","tweet_average_send_num":"","fav_info":{"account_note":"","group_type":0},"is_select":true,"is_show_select":false,"in_picking_cart":false,"reservation_notice_short":"","external_reference_price":{"price_validity_period":{"start":"2018-08-27","end":"2018-09-30"},"original_release":{"quote":27200},"video_release":{"quote":0},"filed_events":{"quote":0},"guerilla_advertising_live":{"quote":0}},"external_original_zhifa_price":null,"only_support_original":2,"video_original_release_paly_net_price":0,"video_release_paly_net_price":0,"video_guerilla_advertising_paly_net_price":0,"operator_kol_inner_ratio_gender_pattern_top":[],"operator_kol_inner_ratio_age_pattern_top":[],"operator_kol_inner_ratio_province_pattern_top":[],"operator_kol_inner_ratio_interest_pattern_top":[],"has_pyq_account_daily_update_images":[],"in_shopping_cart":false,"screen_shot_qr_code":null,"weibo_name_cut":"&#x9752;&#x4e91;&#x7ea2;&#x8845;","video_type_cate":2,"detail_url":"\/single\/video?weibo_id=2981561&weibo_type=110&sign=4a8d904292"}}]}}